Workbook
Name ___r: #REF!
Name ___r: #REF!
Name ___r: #REF!
Name ___r: #REF!
Name __r: #REF!
Name __r: #REF!
Name __r: #REF!
Name __r: #REF!
Name _r: #REF!
Name _r: #REF!
Name _r: #REF!
Name _r: #REF!
Name _r: #REF!
Name _r: #REF!
Name _r: #REF!
Name _r: #REF!
Name _r: #REF!
Name _r: #REF!
Name _r: #REF!
Name _r: #REF!
Name _Regression_Int: 1
Name A_impresión_IM: #REF!
Name A_impresión_IM: #REF!
Name A_impresión_IM: #REF!
Name A_impresión_IM: #REF!
Name ActualBeyond: 'Control Producción'!PeriodInActual*(#REF!>0)
Name ActualBeyond: PeriodInActual*('[4]Planificador de proyectos'!$E1>0)
Name agno: #REF!
Name agno: [5]EstadoCAPEX!$C$1
Name AREA_DE_IMPRESI: #REF!
Name AREA_DE_IMPRESI: [6]hed99!$A$237:$S$275
Name avFísicoPROG: #REF!
Name avFísicoPROG: [5]ProyGANTT!$I$44
Name avFísicoREAL: #REF!
Name avFísicoREAL: [5]ProyGANTT!$J$44
Name b: #REF!
Name b: #REF!
Name b: #REF!
Name b: #REF!
Name b: #REF!
Name b: #REF!
Name b: #REF!
Name b: #REF!
Name b: #REF!
Name b: #REF!
Name b: #REF!
Name b: #REF!
Name b: #REF!
Name Bal: #REF!
Name Bal: #REF!
Name Bal: #REF!
Name Bal: #REF!
Name Bal: #REF!
Name Bal: #REF!
Name Bal: #REF!
Name Bal: #REF!
Name Bal: #REF!
Name Bal: #REF!
Name Bal: #REF!
Name Bal: #REF!

Sheet Factores
B2: Mes Actual : | D2: 46082.792
B3: Fecha Actualización: | D3: 46098.792 | E3: <- Poner la fecha dia anPerior en celda "D3".
D6: Deduccion Metalurgica (Bdgt) | E6: Deduccion Metalurgica | F6: Deduccion Metalurgica (real)
C7: Cu | D7: =+E7 -> 0.962 | E7: 0.962 | F7: 0.962
C8: Mo | D8: 0.995 | E8: 0.995 | F8: 0.995
C9: Relacion Mo/Cu | D9: 2.899 | E9: 2.899 | F9: 2.899
C12: Cu en CuCons | D12: Pagable Cu
C13: 15 | D13: 0.927
C14: 16 | D14: 0.931
C15: 17 | D15: 0.935
C16: 18 | D16: 0.939
C17: 19 | D17: 0.942
C18: 20 | D18: 0.945
C19: 21 | D19: 0.948
C20: 22 | D20: 0.95
C21: 23 | D21: 0.952
C22: 24 | D22: 0.958
C23: 25 | D23: 0.96
C24: 26 | D24: 0.962
... C39: 41 | D39: 0.968
C40: 42 | D40: 0.968 | AS40: =#N/A -> #N/A
C41: 43 | D41: 0.968
C42: 44 | D42: 0.968
C43: 45 | D43: 0.968

Sheet Comparacion (Sin BM)
B1: INFORME : | E1: B : BudgeP
B2: MES : | C2: =[16]FacPores!D2 -> #REF! | E2: F : Forecast | O2: DELTA INVENTARIO MES | Q2: R+P | R2: ST | T2: Q | V2: DELTA INVENTARIO MES | X2: REAL | Y2: S.T.
B3: Fecha Actualización: | C3: =[17]Hoja1!K3 -> 41623.792 | E3: S.T.: Short Term | O3: Cu Fino Filtrado | Q3: =+Q15/0.966 -> 27.335085 | R3: =+R15/0.966 -> 28.188194 | V3: Cu Fino Filtrado | X3: =Real!AQ40/1000 -> 13.096116 | Y3: ='ST Original'!GF37/1000 -> 0 | AK3: CuFFP Real vs ST
E4: P : Proyeccion | O4: Delta Inventario Cu | Q4: =+Q3-Q14 -> -0.02693531 | R4: =+R3-R14 -> -0.13015778 | T4: =+Q4-R4 -> 0.10322247 | V4: Delta Inventario Cu | X4: =+X3-X14 -> 0.12176294 | Y4: =+Y3-Y14 -> -13.540082 | AA4: =+X4-Y4 -> 13.661845 | AC4: CUMPLIMIENTO REAL vs ST ACUM. MES | AK4: Dias | AQ4: 0.966 | AV4: Dias | BE4: Dias | BK4: 0.995
E5: R : Real | O5: Mo Fin o Envasado | Q5: =+Q19/0.995 -> 1.0004937 | R5: =+R19/0.995 -> 0.88119476 | V5: Mo Fin o Envasado | X5: =Real!AA40/1000 -> 0.56844523 | Y5: ='ST Original'!GA37/1000 -> 0 | AC5: Dias | AK5: =AC6 -> 1 | AL5: TPH | AM5: CM | AN5: Ley Cu | AO5: Rec Cu | AP5: Inv | AQ5: FP | AR5: TMF | AS5: dif | AV5: =+AC6 -> 1 | AW5: TPH | AX5: CM | AY5: Ley Mo | AZ5: RMoCol, % | BA5: RMoSel, % | BB5: Mo Fino, ton | BC5: dif | BE5: =+AC6 -> 1 | BF5: TPH | BG5: CM | BH5: Ley Mo | BI5: RMoCol, % | BJ5: RMoSel, % | BK5: Inv | BL5: FP | BM5: TMF | BN5: dif
B6: Nota : Se usó valores de comercialización de | F6: =Factores!D3 -> 46098.792 | O6: Delta Inventario Mo | Q6: =+Q5-Q18 -> 0.092866388 | R6: =+R5-R18 -> 0.073248003 | T6: =+Q6-R6 -> 0.019618384 | V6: Delta Inventario Mo | X6: =+X5-X18 -> 0.073101146 | Y6: =+Y5-Y18 -> -0.45280369 | AA6: =+X6-Y6 -> 0.52590483 | AC6: 1 | AD6: TPH | AE6: CM | AF6: Ley Cu | AG6: Rec Cu | AH6: TMF | AI6: dif | AK6: ST | AL6: =+AD7 -> 8414.2412 | AM6: =+AE7 -> 88.216548 | AN6: =+AF7 -> 0.51107742 | AO6: =+AG7 -> 90.302073 | AP6: =+Y4*1000*AQ4 -> -13079.72 | AQ6: =+AR6*$AQ$4+AP6 -> -12285.505 | AR6: =+((AL6*24*AM6/100*$AC$6)*AN6*AO6)/10000 -> 822.1682 | AS6: =+AQ6 -> -12285.505 | AV6: ST | AW6: =+AD7 -> 8414.2412 | AX6: =+AE7 -> 88.216548 | AY6: =+Y39/10000 -> 0.019092613 | AZ6: =+Y41 -> 92.043617 | BA6: =+Y42 -> 87.824161 | BB6: =+((AW6*24*AX6/100*$AV$5)*AY6*AZ6*BA6)/1000000 -> 27.494721 | BC6: =+BB6 -> 27.494721 | BE6: ST | BF6: =+AD7 -> 8414.2412 | BG6: =+AE7 -> 88.216548 | BH6: =+Y39/10000 -> 0.019092613 | BI6: =+Y41 -> 92.043617 | BJ6: =+Y42 -> 87.824161 | BK6: =+Y6*1000 -> -452.80369 | BL6: =+BM6*$BK$4+BK6 -> -425.44644 | BM6: =+((BF6*24*BG6/100*$AC$6)*BH6*BI6*BJ6)/1000000 -> 27.494721 | BN6: =+BL6 -> -425.44644
AC7: ST | AD7: =+AF70 -> 8414.2412 | AE7: =+Y32 -> 88.216548 | AF7: =+Y34 -> 0.51107742 | AG7: =+Y35 -> 90.302073 | AH7: =+((AD7*24*AE7/100*$AC$6)*AF7*AG7)/10000 -> 822.1682 | AI7: =+AH7 -> 822.1682 | AK7: Rendimiento | AL7: =+$AD$24 -> 0 | AM7: =+AM6 -> 88.216548 | AN7: =+$AF$7 -> 0.51107742 | AO7: =+$AG$7 -> 90.302073 | AP7: =+AP6 -> -13079.72 | AQ7: =+AR7*$AQ$4+AP7 -> -13079.72 | AR7: =+((AL7*24*AM7/100*$AC$6)*AN7*AO7)/10000 -> 0 | AS7: =+AQ7-AQ6 -> -794.21448 | AV7: TPH | AW7: =+AW24 -> 0 | AX7: =+AX6 -> 88.216548 | AY7: =+AY6 -> 0.019092613 | AZ7: =+AZ6 -> 92.043617 | BA7: =+BA6 -> 87.824161 | BB7: =+((AW7*24*AX7/100*$AV$5)*AY7*AZ7*BA7)/1000000 -> 0 | BC7: =+BB7-BB6 -> -27.494721 | BE7: Rendimiento | BF7: =+BF13 -> 0 | BG7: =+BG6 -> 88.216548 | BH7: =+BH6 -> 0.019092613 | BI7: =+BI6 -> 92.043617 | BJ7: =+BJ6 -> 87.824161 | BK7: =+BK6 -> -452.80369 | BL7: =+BM7*$BK$4+BK7 -> -452.80369 | BM7: =+((BF7*24*BG7/100*$AC$6)*BH7*BI7*BJ7)/1000000 -> 0 | BN7: =+BL7-BL6 -> -27.357248
A8: COMPARACION SHORT TERM ORIGINAL VS BUDGET | H8: COMPARACION SHORT TERM ORIGINAL VS FORECAST | O8: COMPARACION REAL+PROYECCION VS SHORT TERM | V8: REAL VS SHORT TERM | AC8: Rendimiento | AD8: =+$AD$24 -> 0 | AE8: =+AE7 -> 88.216548 | AF8: =+$AF$7 -> 0.51107742 | AG8: =+$AG$7 -> 90.302073 | AH8: =+((AD8*24*AE8/100*$AC$6)*AF8*AG8)/10000 -> 0 | AI8: =+AH8-AH7 -> -822.1682 | AK8: C.M. | AL8: =+$AD$24 -> 0 | AM8: =+$AE$24 -> 0 | AN8: =+$AF$7 -> 0.51107742 | AO8: =+$AG$7 -> 90.302073 | AP8: =+AP6 -> -13079.72 | AQ8: =+AR8*$AQ$4+AP8 -> -13079.72 | AR8: =+((AL8*24*AM8/100*$AC$6)*AN8*AO8)/10000 -> 0 | AS8: =+AQ8-AQ7 -> 0 | AV8: CM | AW8: =+AW24 -> 0 | AX8: =+AX24 -> 0 | AY8: =+AY6 -> 0.019092613 | AZ8: =+AZ6 -> 92.043617 | BA8: =+BA6 -> 87.824161 | BB8: =+((AW8*24*AX8/100*$AV$5)*AY8*AZ8*BA8)/1000000 -> 0 | BC8: =+BB8-BB7 -> 0 | BE8: CM | BF8: =+BF13 -> 0 | BG8: =+BG13 -> 0 | BH8: =+BH6 -> 0.019092613 | BI8: =+BI6 -> 92.043617 | BJ8: =+BJ6 -> 87.824161 | BK8: =+BK6 -> -452.80369 | BL8: =+BM8*$BK$4+BK8 -> -452.80369 | BM8: =+((BF8*24*BG8/100*$AC$6)*BH8*BI8*BJ8)/1000000 -> 0 | BN8: =+BL8-BL7 -> 0
A9: PARA EL MES | B9: =C2 -> #REF! | E9: VARIACION | H9: PARA EL MES | I9: =C2 -> #REF! | L9: VARIACION | O9: PARA EL MES | P9: =C2 -> #REF! | S9: VARIACION | V9: PARA EL DIA | W9: =C2 -> #REF! | Z9: VARIACION | AC9: C.M. | AD9: =+$AD$24 -> 0 | AE9: =+$AE$24 -> 0 | AF9: =+$AF$7 -> 0.51107742 | AG9: =+$AG$7 -> 90.302073 | AH9: =+((AD9*24*AE9/100*$AC$6)*AF9*AG9)/10000 -> 0 | AI9: =+AH9-AH8 -> 0 | AK9: Ley Cab. Cu,% | AL9: =+$AD$24 -> 0 | AM9: =+$AE$24 -> 0 | AN9: =+$AF$24 -> 0 | AO9: =+$AG$7 -> 90.302073 | AP9: =+AP6 -> -13079.72 | AQ9: =+AR9*$AQ$4+AP9 -> -13079.72 | AR9: =+((AL9*24*AM9/100*$AC$6)*AN9*AO9)/10000 -> 0 | AS9: =+AQ9-AQ8 -> 0 | AV9: Ley Mo | AW9: =+AW24 -> 0 | AX9: =+AX24 -> 0 | AY9: =+AY24 -> 0 | AZ9: =+AZ6 -> 92.043617 | BA9: =+BA6 -> 87.824161 | BB9: =+((AW9*24*AX9/100*$AV$5)*AY9*AZ9*BA9)/1000000 -> 0 | BC9: =+BB9-BB8 -> 0 | BE9: Ley Mo | BF9: =+BF13 -> 0 | BG9: =+BG13 -> 0 | BH9: =+BH13 -> 0.020905586 | BI9: =+BI6 -> 92.043617 | BJ9: =+BJ6 -> 87.824161 | BK9: =+BK6 -> -452.80369 | BL9: =+BM9*$BK$4+BK9 -> -452.80369 | BM9: =+((BF9*24*BG9/100*$AC$6)*BH9*BI9*BJ9)/1000000 -> 0 | BN9: =+BL9-BL8 -> 0
B10: UNIDAD | C10: S.T. | D10: B | E10: Q | F10: % | I10: UNIDAD | J10: S.T. | K10: F | L10: Q | M10: % | P10: UNIDAD | Q10: R+P | R10: S.T. | S10: Q | T10: % | W10: UNIDAD | X10: REAL | Y10: S.T. | Z10: Q | AA10: % | AC10: Ley Cab. Cu,% | AD10: =+$AD$24 -> 0 | AE10: =+$AE$24 -> 0 | AF10: =+$AF$24 -> 0 | AG10: =+$AG$7 -> 90.302073 | AH10: =+((AD10*24*AE10/100*$AC$6)*AF10*AG10)/10000 -> 0 | AI10: =+AH10-AH9 -> 0 | AK10: RCu, % | AL10: =+$AD$24 -> 0 | AM10: =+$AE$24 -> 0 | AN10: =+$AF$24 -> 0 | AO10: =+$AG$24 -> 0 | AP10: =+AP6 -> -13079.72 | AQ10: =+AR10*$AQ$4+AP10 -> -13079.72 | AR10: =+((AL10*24*AM10/100*$AC$6)*AN10*AO10)/10000 -> 0 | AS10: =+AQ10-AQ9 -> 0 | AV10: RMoCol, % | AW10: =+AW24 -> 0 | AX10: =+AX24 -> 0 | AY10: =+AY24 -> 0 | AZ10: =+AZ24 -> 0 | BA10: =+BA9 -> 87.824161 | BB10: =+((AW10*24*AX10/100*$AV$5)*AY10*AZ10*BA10)/1000000 -> 0 | BC10: =+BB10-BB9 -> 0 | BE10: RMoCol, % | BF10: =+BF13 -> 0 | BG10: =+BG13 -> 0 | BH10: =+BH13 -> 0.020905586 | BI10: =+BI13 -> 89.313167 | BJ10: =+BJ9 -> 87.824161 | BK10: =+BK6 -> -452.80369 | BL10: =+BM10*$BK$4+BK10 -> -452.80369 | BM10: =+((BF10*24*BG10/100*$AC$6)*BH10*BI10*BJ10)/1000000 -> 0 | BN10: =+BL10-BL9 -> 0
A11: Cu Fino Eq. Producido | B11: Kton | C11: ='ST Original'!#REF!/1000 -> #REF! | D11: =+BDGT!H7+BDGT!H9*BDGT!$H$60 -> 22.933613 | E11: =+C11-D11 -> #REF! | F11: =+E11/D11 -> #REF! | H11: Cu Fino Eq. Producido | I11: Kton | J11: =C11 -> #REF! | K11: ='ST Original'!#REF!/1000 -> #REF! | L11: =+J11-K11 -> #REF! | M11: =+L11/K11 -> #REF! | O11: Cu Fino Eq. Producido | P11: Kton | Q11: ='R+P'!AF39/1000 -> 29.993232 | R11: =C11 -> #REF! | S11: =+Q11-R11 -> #REF! | T11: =+S11/R11 -> #REF! | V11: Cu Fino Eq. Producido | W11: Kton | X11: =+Real!Q40/1000 -> 12.974353 | Y11: =C11 -> #REF! | Z11: =+X11-Y11 -> #REF! | AA11: =+Z11/Y11 -> #REF! | AC11: RCu, % | AD11: =+$AD$24 -> 0 | AE11: =+$AE$24 -> 0 | AF11: =+$AF$24 -> 0 | AG11: =+$AG$24 -> 0 | AH11: =+((AD11*24*AE11/100*$AC$6)*AF11*AG11)/10000 -> 0 | AI11: =+AH11-AH10 -> 0 | AK11: Inv | AL11: =+$AD$24 -> 0 | AM11: =+$AE$24 -> 0 | AN11: =+$AF$24 -> 0 | AO11: =+$AG$24 -> 0 | AP11: =+X4*1000*AQ4 -> 117.623 | AQ11: =+AR11*$AQ$4+AP11 -> 117.623 | AR11: =+((AL11*24*AM11/100*$AC$6)*AN11*AO11)/10000 -> 0 | AS11: =+AQ11-AQ10 -> 13197.343 | AV11: RMoSel, % | AW11: =+AW10 -> 0 | AX11: =+AX10 -> 0 | AY11: =+AY10 -> 0 | AZ11: =+AZ10 -> 0 | BA11: =+BA24 -> 0 | BB11: =+((AW11*24*AX11/100*$AV$5)*AY11*AZ11*BA11)/1000000 -> 0 | BC11: =+BB11-BB10 -> 0 | BE11: RMoSel, % | BF11: =+BF13 -> 0 | BG11: =+BG13 -> 0 | BH11: =+BH13 -> 0.020905586 | BI11: =+BI13 -> 89.313167 | BJ11: =+BJ13 -> 90.883109 | BK11: =+BK6 -> -452.80369 | BL11: =+BM11*$BK$4+BK11 -> -452.80369 | BM11: =+((BF11*24*BG11/100*$AC$6)*BH11*BI11*BJ11)/1000000 -> 0 | BN11: =+BL11-BL10 -> 0
A12: Cu Fino Eq. Filtrado (Ppto) | B12: Kton | C12: =C15+C19*Factores!$D$9 -> 29.771606 | D12: =D15+D19*Factores!$D$9 -> 33.406194 | E12: =+C24-D24 -> 0 | F12: =+E24/D24 -> #DIV/0! | H12: Cu Fino Eq. Filtrado (Ppto) | I12: Kton | J12: =C24 -> 0 | K12: =K15+K19*Factores!$D$9 -> #REF! | L12: =+J24-K24 -> 0 | M12: =+L24/K24 -> #DIV/0! | O12: Cu Fino Eq. Filtrado (Bdgt) | P12: Kton | Q12: =Q15+Q19*Factores!$D$9 -> 29.291621 | R12: =R15+R19*Factores!$D$9 -> 29.771606 | S12: =+Q24-R24 -> -25.560003 | T12: =+S24/R24 -> -0.11618183 | V12: Cu Fino Eq. Filtrado | W12: Kton | X12: =X15+X19*Factores!$D$9 -> 14.238147 | Y12: =C24 -> 0 | Z12: =+X24-Y24 -> 169.20919 | AA12: =+Z24/Y24 -> #DIV/0! | AC12: Real | AD12: =+AE70 -> 8365.4531 | AE12: =+X32 -> 88.117328 | AF12: =+X34 -> 0.49046726 | AG12: =+X35 -> 90.621182 | AH12: =+((AD24*24*AE24/100*$AC$6)*AF24*AG24)/10000 -> 0 | AI12: =SUM(AI7:AI11) -> 0 | AK12: Real | AL12: =+AD24 -> 0 | AM12: =+AE24 -> 0 | AN12: =+AF24 -> 0 | AO12: =+AG24 -> 0 | AP12: 1020 | AQ12: =+AR24*$AQ$4+AP24 -> 0 | AR12: =+((AL24*24*AM24/100*$AC$6)*AN24*AO24)/10000 -> 0 | AS12: =SUM(AS6:AS11) -> 117.623 | AV12: Real | AW12: =+AD24 -> 0 | AX12: =+AE24 -> 0 | AY12: =+X39/10000 -> 0.020905586 | AZ12: =+X41 -> 89.313167 | BA12: =+X42 -> 90.883109 | BB12: =+((AW24*24*AX24/100*$AV$5)*AY24*AZ24*BA24)/1000000 -> 0 | BC12: =SUM(BC6:BC11) -> 0 | BE12: Inv | BF12: =+BF13 -> 0 | BG12: =+BG13 -> 0 | BH12: =+BH13 -> 0.020905586 | BI12: =+BI13 -> 89.313167 | BJ12: =+BJ13 -> 90.883109 | BK12: =+X6*1000 -> 73.101146 | BL12: =+BM24*$BK$4+BK24 -> 0 | BM12: =+((BF24*24*BG24/100*$AC$6)*BH24*BI24*BJ24)/1000000 -> 0 | BN12: =+BL24-BL11 -> 452.80369
A13: Cu Fino Eq. Filtrado (Real) | B13: Kton | C13: =C16+C20*Factores!$F$9 -> 29.771606 | D13: =D16+D20*Factores!$F$9 -> 33.406194 | E13: =+C13-D13 -> -3.6345876 | F13: =+E13/D13 -> -0.10879981 | H13: Cu Fino Eq. Filtrado (Real) | I13: Kton | J13: =J16+J20*Factores!$F$9 -> 27.229795 | K13: =K16+K20*Factores!$F$9 -> #REF! | L13: =+J13-K13 -> #REF! | M13: =+L13/K13 -> #REF! | O13: Cu Fino Eq. Filtrado (Real) | P13: Kton | Q13: =Q16+Q20*Factores!$F$9 -> 29.291621 | R13: =R16+R20*Factores!$F$9 -> 29.771606 | S13: =+Q13-R13 -> -0.47998473 | T13: =+S13/R13 -> -0.016122232 | V13: Cu Fino Eq. Filtrado | W13: Kton | X13: =X16+X20*Factores!$F$9 -> 14.238147 | Y13: =C13 -> 29.771606 | Z13: =+X13-Y13 -> -15.533459 | AA13: =+Z13/Y13 -> -0.52175415 | BE13: Real | BF13: =+AD24 -> 0 | BG13: =+AE24 -> 0 | BH13: =+X39/10000 -> 0.020905586 | BI13: =+X41 -> 89.313167 | BJ13: =+X42 -> 90.883109 | BK13: =+BK24 -> 0 | BL13: =+BM13*$BK$4+BK13 -> 0 | BM13: =+((BF13*24*BG13/100*$AC$6)*BH13*BI13*BJ13)/1000000 -> 0
A14: Cu Fino Producido | B14: Kton | C14: =+'ST Original'!V39/1000 -> 28.318352 | D14: =+BDGT!H7 -> 22.933613 | E14: =+C14-D14 -> 5.3847386 | F14: =+E14/D14 -> 0.23479678 | H14: Cu Fino Producido | I14: Kton | J14: =C14 -> 28.318352 | K14: ='ST Original'!#REF!/1000 -> #REF! | L14: =+J14-K14 -> #REF! | M14: =+L14/K14 -> #REF! | O14: Cu Fino Producido | P14: Kton | Q14: ='R+P'!R47/1000 -> 27.36202 | R14: =C14 -> 28.318352 | S14: =+Q14-R14 -> -0.95633141 | T14: =+S14/R14 -> -0.03377073 | V14: Cu Fino Producido | W14: Kton | X14: =Real!$P$40/1000 -> 12.974353 | Y14: ='ST Original'!FQ39/1000 -> 13.540082 | Z14: =+X14-Y14 -> -0.56572901 | AA14: =+Z14/Y14 -> -0.0417818
A15: Cu Fino Filtrado Pagable (Ppto) | B15: Kton | C15: =+'ST Original'!AW39/1000 -> 27.229795 | D15: =+BDGT!J8 -> 31.316639 | E15: =+C15-D15 -> -4.0868432 | F15: =+E15/D15 -> -0.1305007 | H15: Cu Fino Filtrado Pagable (Ppto) | I15: Kton | J15: =C15 -> 27.229795 | K15: ='ST Original'!#REF!/1000*Factores!D7 -> #REF! | L15: =+J15-K15 -> #REF! | M15: =+L15/K15 -> #REF! | O15: Cu Fino Filtrado Pagable (Bdgt) | P15: Kton | Q15: ='R+P'!AO39*Factores!$D$7/1000 -> 26.405692 | R15: =C15 -> 27.229795 | S15: =+Q15-R15 -> -0.82410323 | T15: =+S15/R15 -> -0.03026476 | V15: Cu Fino Filtrado Pagable | W15: Kton | X15: =Real!AQ40*Factores!F7/1000 -> 12.598464 | Y15: ='ST Original'!$GF$39/1000*Factores!D7 -> 12.114235 | Z15: =+X15-Y15 -> 0.48422847 | AA15: =+Z15/Y15 -> 0.039971856
A16: Cu Fino Filtrado Pagable (Real) | B16: Kton | C16: =C15 -> 27.229795 | D16: =D15/Factores!$D$7*Factores!$F$7 -> 31.316639 | E16: =+C16-D16 -> -4.0868432 | F16: =+E16/D16 -> -0.1305007 | H16: Cu Fino Filtrado Pagable (Real) | I16: Kton | J16: =J15/Factores!$D$7*Factores!$F$7 -> 27.229795 | K16: =K15/Factores!$D$7*Factores!$F$7 -> #REF! | L16: =+J16-K16 -> #REF! | M16: =+L16/K16 -> #REF! | O16: Cu Fino Filtrado Pagable (Real) | P16: Kton | Q16: =Q15/Factores!$D$7*Factores!$F$7 -> 26.405692 | R16: =R15/Factores!$D$7*Factores!$F$7 -> 27.229795 | S16: =+Q16-R16 -> -0.82410323 | T16: =+S16/R16 -> -0.03026476 | V16: Cu Fino Filtrado pagable real | W16: Kton | X16: =X15/Factores!$D$7*Factores!$F$7 -> 12.598464 | Y16: ='ST Original'!$GF$39/1000*Factores!F7 -> 12.114235 | Z16: =+X16-Y16 -> 0.48422847 | AA16: =+Z16/Y16 -> 0.039971856
A17: Delta Inventario Cu Fino | B17: Kton | H17: Delta Inventario Cu Fino | I17: Kton | O17: Delta Inventario Cu Fino | P17: Kton | Q17: =Q14-Q15/Factores!D7 -> -0.086724087 | V17: Delta Inventario Cu Fino | W17: Kton | X17: =X14-X15/Factores!D7 -> -0.12176294 | Y17: =Y14-Y15/Factores!D7 -> 0.94732206
A18: Mo Fino Producido | B18: Kton | C18: ='ST Original'!AF39/1000 -> 0.80794675 | D18: =+BDGT!H9 -> 0.49377314 | E18: =+C18-D18 -> 0.31417361 | F18: =+E18/D18 -> 0.63627117 | H18: Mo Fino Producido | I18: Kton | J18: =C18 -> 0.80794675 | K18: ='ST Original'!#REF!/1000 -> #REF! | L18: =+J18-K18 -> #REF! | M18: =+L18/K18 -> #REF! | O18: Mo Fino Producido | P18: Kton | Q18: ='R+P'!AA39/1000 -> 0.90762735 | R18: =C18 -> 0.80794675 | S18: =+Q18-R18 -> 0.099680594 | T18: =+S18/R18 -> 0.1233752 | V18: Mo Fino Producido | W18: Kton | X18: =Real!$Y$40/1000 -> 0.49534409 | Y18: ='ST Original'!FY39/1000 -> 0.45280369 | Z18: =+X18-Y18 -> 0.042540401 | AA18: =+Z18/Y18 -> 0.093948884
A19: Mo Fino Envasado Pagable (Ppto) | B19: Kton | C19: ='ST Original'!AG39/1000*Factores!$D$8 -> 0.87678878 | D19: =+BDGT!J10 -> 0.72078476 | E19: =+C19-D19 -> 0.15600402 | F19: =+E19/D19 -> 0.21643635 | H19: Mo Fino Envasado Pagable (Ppto) | I19: Kton | K19: ='ST Original'!#REF!/1000*Factores!D8 -> #REF! | L19: =+J19-K19 -> #REF! | M19: =+L19/K19 -> #REF! | O19: Mo Fino Envasado Pagable (Bdgt) | P19: Kton | Q19: ='R+P'!AC39/1000*Factores!$D$8 -> 0.99549127 | R19: =C19 -> 0.87678878 | S19: =+Q19-R19 -> 0.11870248 | T19: =+S19/R19 -> 0.13538321 | V19: Mo Fino Envasado Pagable (Bdgt) | W19: Kton | X19: =Real!AA40/1000*Factores!$D$8 -> 0.56560301 | Y19: ='ST Original'!GA39/1000*Factores!D8 -> 0.44690052 | Z19: =+X19-Y19 -> 0.11870248 | AA19: =+Z19/Y19 -> 0.26561276
A20: Mo Fino Envasado Pagable (Real) | B20: Kton | C20: =C19/Factores!$D$8*Factores!$F$8 -> 0.87678878 | D20: =D19/Factores!$D$8*Factores!$F$8 -> 0.72078476 | E20: =+C20-D20 -> 0.15600402 | F20: =+E20/D20 -> 0.21643635 | H20: Mo Fino Envasado Pagable (Real) | I20: Kton | J20: =J19/Factores!$D$8*Factores!$F$8 -> 0 | K20: =K19/Factores!$D$8*Factores!$F$8 -> #REF! | L20: =+J20-K20 -> #REF! | M20: =+L20/K20 -> #REF! | O20: Mo Fino Envasado Pagable (Real) | P20: Kton | Q20: =Q19/Factores!$D$8*Factores!$F$8 -> 0.99549127 | R20: =R19/Factores!$D$8*Factores!$F$8 -> 0.87678878 | S20: =+Q20-R20 -> 0.11870248 | T20: =+S20/R20 -> 0.13538321 | V20: Mo Fino Envasado Pagable (Real) | W20: Kton | X20: =X19/Factores!$D$8*Factores!$F$8 -> 0.56560301 | Y20: ='ST Original'!GA39/1000*Factores!F8 -> 0.44690052 | Z20: =+X20-Y20 -> 0.11870248 | AA20: =+Z20/Y20 -> 0.26561276
A21: Delta Inventario Mo Fino | B21: Kton | H21: Delta Inventario Mo Fino | I21: Kton | O21: Delta Inventario Mo Fino | P21: Kton | Q21: =Q18-Q19/Factores!D8 -> -0.092866388 | V21: Delta Inventario Mo Fino | W21: Kton | X21: =X18-X19/Factores!D8 -> -0.073101146 | Y21: =C21 -> 0 | AC21: Deducción Metalúrgica del Mo | AD21: =Factores!#REF! -> #REF!
O22: Stockpile Fin de Mes | P22: Kton | Q22: =+'R+P'!#REF!/1000 -> #REF! | R22: =+'ST Original'!#REF!/1000 -> #REF! | S22: =+Q22-R22 -> #REF! | T22: =+S22/R22 -> #REF! | Y22: =C22 -> 0
O23: Tonelaje Enviado STMG | P23: Kton | Q23: ='R+P'!D39/1000 -> 6027.6399 | R23: ='ST Original'!D37/1000 -> 672.09613 | S23: =+Q23-R23 -> 5355.5438 | T23: =+S23/R23 -> 7.9684193 | V23: Tonelaje Enviado STMG | W23: Kton | X23: =Real!D40/1000 -> 2876.5563 | Y23: =C23 -> 0 | Z23: =+X23-Y23 -> 2876.5563 | AA23: =+Z23/Y23 -> #DIV/0!
O24: Toneladas enviado STMG por día | P24: Ktpd | Q24: ='R+P'!C39/1000 -> 194.44 | R24: ='ST Original'!C37/1000 -> 220 | S24: =+Q24-R24 -> -25.560003 | T24: =+S24/R24 -> -0.11618183 | V24: Toneladas enviado STMG por día | W24: Ktpd | X24: =Real!C40/1000 -> 169.20919 | Y24: =C24 -> 0 | Z24: =+X24-Y24 -> 169.20919 | AA24: =+Z24/Y24 -> #DIV/0!
A26: Extracción | B26: Kton | C26: ='ST Original'!#REF! -> #REF! | D26: ='ST Original'!#REF! -> #REF! | E26: =+C26-D26 -> #REF! | F26: =+E26/D26 -> #REF! | H26: Extracción | I26: Kton | J26: =C26 -> #REF! | K26: ='ST Original'!#REF! -> #REF! | L26: =+J26-K26 -> #REF! | M26: =+L26/K26 -> #REF! | O26: Extracción | P26: Kton | Q26: ='R+P'!#REF!/1000 -> #REF! | R26: =C26 -> #REF! | S26: =+Q26-R26 -> #REF! | T26: =+S26/R26 -> #REF! | V26: Extracción | W26: Kton | X26: =Real!$AW$40/1000 -> 7028.6855 | Y26: ='ST Original'!#REF!/1000 -> #REF! | Z26: =+X26-Y26 -> #REF! | AA26: =+Z26/Y26 -> #REF!
A27: Tonelaje Procesado | B27: Kton | C27: =+'ST Original'!E39/1000 -> 5857.1988 | D27: ='ST Original'!#REF! -> #REF! | E27: =+C27-D27 -> #REF! | F27: =+E27/D27 -> #REF! | H27: Tonelaje Procesado | I27: Kton | J27: =C27 -> 5857.1988 | K27: ='ST Original'!#REF! -> #REF! | L27: =+J27-K27 -> #REF! | M27: =+L27/K27 -> #REF! | O27: Tonelaje Procesado | P27: Kton | Q27: =+'R+P'!E47 -> 5834.851 | R27: =C27 -> 5857.1988 | S27: =+Q27-R27 -> -22.347735 | T27: =+S27/R27 -> -0.0038154305 | V27: Tonelaje Procesado | W27: Kton | X27: =Real!$F$40/1000 -> 2919.0798 | Y27: ='ST Original'!$FG$39/1000 -> 2933.8431 | Z27: =+X27-Y27 -> -14.763304 | AA27: =+Z27/Y27 -> -0.0050320699
A28: Toneladas por día | B28: Ktpd | C28: ='ST Original'!E39/COUNT('ST Original'!B8:B38)/1000 -> 188.9419 | D28: ='ST Original'!#REF!/COUNT('ST Original'!B8:B36) -> #REF! | E28: =+C28-D28 -> #REF! | F28: =+E28/D28 -> #REF! | H28: Toneladas por día | I28: Ktpd | J28: =C28 -> 188.9419 | K28: ='ST Original'!#REF!/COUNT('ST Original'!B8:B36) -> #REF! | L28: =+J28-K28 -> #REF! | M28: =+L28/K28 -> #REF! | O28: Toneladas por día | P28: Ktpd | Q28: ='R+P'!E39/COUNT('R+P'!B8:B38)/1000 -> 188.221 | R28: =C28 -> 188.9419 | S28: =+Q28-R28 -> -0.72089467 | T28: =+S28/R28 -> -0.0038154305 | V28: Toneladas por día | W28: Ktpd | X28: =Real!$E$40/1000 -> 2919.0798 | Y28: ='ST Original'!$FF$39/1000 -> 172.57901 | Z28: =+X28-Y28 -> 2746.5008 | AA28: =+Z28/Y28 -> 15.914455
A29: Rendimiento | B29: Tph | C29: =+'ST Original'!BT39 -> 8502.7682 | D29: ='ST Original'!#REF!*1000/(24*COUNT('ST Original'!B8:B38)*D32/100) -> #REF! | E29: =+C29-D29 -> #REF! | F29: =+E29/D29 -> #REF! | H29: Rendimiento | I29: Tph | J29: =C29 -> 8502.7682 | K29: =IF(ISNUMBER('ST Original'!#REF!*1000/(24*COUNT('ST Original'!B8:B36)*'ST Original'!#REF!/100)),'ST Original'!#REF!*1000/(24*COUNT('ST Original'!B8:B36)*'ST Original'!#REF!/100)," ") | L29: =IF(ISNUMBER(J29-K29),J29-K29," ") | M29: =+L29/K29 -> #VALUE! | O29: Rendimiento | P29: Tph | Q29: ='R+P'!BH39 -> 8494.565 | R29: =C29 -> 8502.7682 | S29: =+Q29-R29 -> -8.2032069 | T29: =+S29/R29 -> -0.00096476897 | V29: Rendimiento | W29: Tph | X29: =X27/(24*COUNT(Real!C9:C39))/X32% -> 8.1194104 | Y29: ='ST Original'!$FI$39 -> 8414.2412 | Z29: =+X29-Y29 -> -8406.1217 | AA29: =+Z29/Y29 -> -0.99903504
A30: Mineral Duro | B30: % | C30: ='ST Original'!K39 -> 73.985882 | D30: ='ST Original'!#REF! -> #REF! | E30: =+C30-D30 -> #REF! | F30: =+E30/D30 -> #REF! | H30: Mineral Duro | I30: % | J30: =C30 -> 73.985882 | K30: ='ST Original'!#REF! -> #REF! | L30: =+J30-K30 -> #REF! | M30: =+L30/K30 -> #REF! | O30: Mineral Duro | P30: % | Q30: ='R+P'!K39 -> 67.341178 | R30: =C30 -> 73.985882 | S30: =+R30-Q30 -> 6.6447044 | T30: =+S30/R30 -> 0.089810437 | V30: Mineral Duro | W30: % | X30: =Real!AD40 -> 62.153208 | Y30: ='ST Original'!$FJ$39 -> 73.498171 | Z30: =+X30-Y30 -> -11.344963 | AA30: =+Z30/Y30 -> -0.15435708
A31: F80 | B31: % | C31: =+'ST Original'!AX39 -> 4.2028666 | D31: ='ST Original'!#REF! -> #REF! | E31: =+C31-D31 -> #REF! | F31: =+E31/D31 -> #REF! | O31: F80 | P31: % | Q31: ='R+P'!BD39 -> 4.4644232 | R31: =C31 -> 4.2028666 | S31: =+R31-Q31 -> -0.26155667 | T31: =+S31/R31 -> -0.062232922 | V31: F80 | W31: In | X31: =+Real!AS40 -> 4.6902586 | Y31: ='ST Original'!$FA$39 -> 4.1675369 | Z31: =+X31-Y31 -> 0.5227217 | AA31: =+Z31/Y31 -> 0.12542701
A32: Coeficiente de Marcha | B32: % | C32: ='ST Original'!J39 -> 92.650689 | D32: ='ST Original'!#REF! -> #REF! | E32: =+C32-D32 -> #REF! | F32: =+E32/D32 -> #REF! | H32: Coeficiente de Marcha | I32: % | J32: =C32 -> 92.650689 | K32: ='ST Original'!#REF! -> #REF! | L32: =+J32-K32 -> #REF! | M32: =+L32/K32 -> #REF! | O32: Coeficiente de Marcha | P32: % | Q32: ='R+P'!J39 -> 92.32423 | R32: =C32 -> 92.650689 | S32: =+Q32-R32 -> -0.32645839 | T32: =+S32/R32 -> -0.0035235398 | V32: Coeficiente de Marcha | W32: % | X32: =Real!J40 -> 88.117328 | Y32: ='ST Original'!$FH$39 -> 88.216548 | Z32: =+X32-Y32 -> -0.099220776 | AA32: =+Z32/Y32 -> -0.0011247411
A33: AxB | B33: ton/kwh | C33: =+'ST Original'!AT39 -> 37.368349 | D33: =+'ST Original'!#REF! -> #REF! | E33: =+C33-D33 -> #REF! | F33: =+E33/D33 -> #REF! | O33: Axb | P33: ton/kwh | Q33: =+'R+P'!BE39 -> 37.97411 | R33: =C33 -> 37.368349 | S33: =+R33-Q33 -> -0.6057616 | T33: =+S33/R33 -> -0.016210553 | V33: AxB | W33: % | X33: =Real!AU40 -> 37.942958 | Y33: ='ST Original'!$GU$39 -> 36.900097 | Z33: =+X33-Y33 -> 1.0428608 | AA33: =+Z33/Y33 -> 0.028261735
A34: Ley Alim. Cu | B34: % | C34: =+'ST Original'!L39 -> 0.53544933 | D34: ='ST Original'!#REF! -> #REF! | E34: =+C34-D34 -> #REF! | F34: =+E34/D34 -> #REF! | H34: Ley Alim. Cu | I34: % | J34: =C34 -> 0.53544933 | K34: ='ST Original'!#REF! -> #REF! | L34: =+J34-K34 -> #REF! | M34: =+L34/K34 -> #REF! | O34: Ley Alim. Cu | P34: % | Q34: ='R+P'!$L$47 -> 0.51875622 | R34: =C34 -> 0.53544933 | S34: =+Q34-R34 -> -0.016693109 | T34: =+S34/R34 -> -0.03117589 | V34: Ley Alim. Cu | W34: % | X34: =Real!K40 -> 0.49046726 | Y34: ='ST Original'!$FK$39 -> 0.51107742 | Z34: =+X34-Y34 -> -0.020610154 | AA34: =+Z34/Y34 -> -0.040326872
A35: Rec. Cu | B35: % | C35: ='ST Original'!M39 -> 90.294153 | D35: ='ST Original'!#REF! -> #REF! | E35: =+C35-D35 -> #REF! | F35: =+E35/D35 -> #REF! | H35: Rec. Cu | I35: % | J35: =C35 -> 90.294153 | K35: ='ST Original'!#REF! -> #REF! | L35: =+J35-K35 -> #REF! | M35: =+L35/K35 -> #REF! | O35: Rec. Cu | P35: % | Q35: ='R+P'!$M$47 -> 90.397219 | R35: =C35 -> 90.294153 | S35: =+Q35-R35 -> 0.10306589 | T35: =+S35/R35 -> 0.0011414459 | V35: Rec. Cu | W35: % | X35: =Real!L40 -> 90.621182 | Y35: ='ST Original'!$FL$39 -> 90.302073 | Z35: =+X35-Y35 -> 0.31910823 | AA35: =+Z35/Y35 -> 0.0035337863 | AC35: Cu Fino Producido R+P vs ST | AQ35: 0.966 | AV35: Dias | BE35: Dias | BK35: =+Factores!F8 -> 0.995
A36: Conc Cu Producido | B36: Kton | C36: ='ST Original'!R39/1000 -> 105.75347 | D36: ='ST Original'!#REF!/1000 -> #REF! | E36: =+C36-D36 -> #REF! | F36: =+E36/D36 -> #REF! | H36: Conc Cu Producido | I36: Kton | J36: =C36 -> 105.75347 | K36: ='ST Original'!#REF!/1000 -> #REF! | L36: =+J36-K36 -> #REF! | M36: =+L36/K36 -> #REF! | O36: Conc Cu Producido | P36: Kton | Q36: ='R+P'!$P$47/1000 -> 103.61851 | R36: =C36 -> 105.75347 | S36: =+Q36-R36 -> -2.1349564 | T36: =+S36/R36 -> -0.020188051 | V36: Conc Cu Producido | W36: Kton | X36: =Real!N40/1000 -> 50.032932 | Y36: ='ST Original'!$FN$39/1000 -> 51.308583 | Z36: =+X36-Y36 -> -1.2756513 | AA36: =+Z36/Y36 -> -0.024862337 | AK36: =AC6 -> 1 | AL36: TPH | AM36: CM | AN36: Ley Cu | AO36: Rec Cu | AP36: Inv | AQ36: FP | AR36: TMF | AS36: dif | AV36: =AC6 -> 1 | AW36: TPH | AX36: CM | AY36: Ley Mo | AZ36: RMoCol, % | BA36: RMoSel, % | BB36: Mo Fino, ton | BC36: dif | BE36: =AC6 -> 1 | BF36: TPH | BG36: CM | BH36: Ley Mo | BI36: RMoCol, % | BJ36: RMoSel, % | BK36: Inv | BL36: FP | BM36: TMF | BN36: dif
A37: Ley Conc. Cu | B37: % | C37: ='ST Original'!N39 -> 26.777705 | D37: ='ST Original'!N39 -> 26.777705 | E37: =+C37-D37 -> 0 | F37: =+E37/D37 -> 0 | H37: Ley Conc. Cu | I37: % | J37: =C37 -> 26.777705 | K37: ='ST Original'!#REF! -> #REF! | L37: =+J37-K37 -> #REF! | M37: =+L37/K37 -> #REF! | O37: Ley Conc. Cu | P37: % | Q37: ='R+P'!$N$47 -> 26.406498 | R37: =C37 -> 26.777705 | S37: =+Q37-R37 -> -0.37120691 | T37: =+S37/R37 -> -0.013862536 | V37: Ley Conc. Cu | W37: % | X37: =Real!M40 -> 25.931627 | Y37: ='ST Original'!$FM$39 -> 26.389507 | Z37: =+X37-Y37 -> -0.45788027 | AA37: =+Z37/Y37 -> -0.017350846 | AC37: 10.5 | AD37: TPH | AE37: CM | AF37: Ley Cu | AG37: Rec Cu | AH37: TMF | AI37: dif | AK37: ST | AL37: =+AD38 -> 8502.7682 | AM37: =+AE38 -> 92.650689 | AN37: =+AF38 -> 0.53544933 | AO37: =+AG38 -> 90.294153 | AP37: =+R4*1000*AQ35 -> -125.73242 | AQ37: =+AR37*$AQ$4+AP37 -> 9146.0806 | AR37: =+((AL37*24*AM37/100*$AC$37)*AN37*AO37)/10000 -> 9598.1501 | AS37: =+AQ37 -> 9146.0806 | AV37: ST | AW37: =+AD38 -> 8502.7682 | AX37: =+AE38 -> 92.650689 | AY37: =+R39/10000 -> 0.017118629 | AZ37: =+R41 -> 91.633787 | BA37: =+R42 -> 87.936295 | BB37: =+((AW37*24*AX37/100*$AV$36)*AY37*AZ37*BA37)/1000000 -> 26.080326 | BC37: =+BB37 -> 26.080326 | BE37: ST | BF37: =+AD38 -> 8502.7682 | BG37: =+AE38 -> 92.650689 | BH37: =+R39/10000 -> 0.017118629 | BI37: =+R41 -> 91.633787 | BJ37: =+R42 -> 87.936295 | BK37: =+R6*1000 -> 73.248003 | BL37: =+BM37*$BK$4+BK37 -> 99.197927 | BM37: =+((BF37*24*BG37/100*$BE$36)*BH37*BI37*BJ37)/1000000 -> 26.080326 | BN37: =+BL37 -> 99.197927
AC38: ST | AD38: =+R29 -> 8502.7682 | AE38: =+R32 -> 92.650689 | AF38: =+R34 -> 0.53544933 | AG38: =+R35 -> 90.294153 | AH38: =+((AD38*24*AE38/100*$AC$37)*AF38*AG38)/10000 -> 9598.1501 | AI38: =+AH38 -> 9598.1501 | AK38: Rendimiento | AL38: =+AL43 -> 8494.565 | AM38: =+AM37 -> 92.650689 | AN38: =+AN37 -> 0.53544933 | AO38: =+AO37 -> 90.294153 | AP38: =+AP37 -> -125.73242 | AQ38: =+AR38*$AQ$4+AP38 -> 9137.1354 | AR38: =+((AL38*24*AM38/100*$AC$37)*AN38*AO38)/10000 -> 9588.8901 | AS38: =+AQ38-AQ37 -> -8.9451575 | AV38: TPH | AW38: =+AW43 -> 8494.565 | AX38: =+AX37 -> 92.650689 | AY38: =+AY37 -> 0.017118629 | AZ38: =+AZ37 -> 91.633787 | BA38: =+BA37 -> 87.936295 | BB38: =+((AW38*24*AX38/100*$AV$36)*AY38*AZ38*BA38)/1000000 -> 26.055164 | BC38: =+BB38-BB37 -> -0.025161489 | BE38: Rendimiento | BF38: =+BF44 -> 8494.565 | BG38: =+BG37 -> 92.650689 | BH38: =+BH37 -> 0.017118629 | BI38: =+BI37 -> 91.633787 | BJ38: =+BJ37 -> 87.936295 | BK38: =+BK37 -> 73.248003 | BL38: =+BM38*$BK$4+BK38 -> 99.172892 | BM38: =+((BF38*24*BG38/100*$BE$36)*BH38*BI38*BJ38)/1000000 -> 26.055164 | BN38: =+BL38-BL37 -> -0.025035681
A39: Ley Alim. Mo | B39: ppm | C39: ='ST Original'!W39 -> 171.18629 | D39: ='ST Original'!#REF! -> #REF! | E39: =+C39-D39 -> #REF! | F39: =+E39/D39 -> #REF! | H39: Ley Alim. Mo | I39: ppm | J39: =C39 -> 171.18629 | K39: ='ST Original'!#REF! -> #REF! | L39: =+J39-K39 -> #REF! | M39: =+L39/K39 -> #REF! | O39: Ley Alim. Mo | P39: ppm | Q39: ='R+P'!$S$47 -> 192.88224 | R39: =C39 -> 171.18629 | S39: =+Q39-R39 -> 21.695952 | T39: =+S39/R39 -> 0.12673884 | V39: Ley Alim. Mo | W39: ppm | X39: =Real!R40 -> 209.05586 | Y39: ='ST Original'!$FR$39 -> 190.92613 | Z39: =+X39-Y39 -> 18.129727 | AA39: =+Z39/Y39 -> 0.09495676 | AC39: Rendimiento | AD39: =+AD43 -> 8494.565 | AE39: =+AE38 -> 92.650689 | AF39: =+AF38 -> 0.53544933 | AG39: =+AG38 -> 90.294153 | AH39: =+((AD39*24*AE39/100*$AC$37)*AF39*AG39)/10000 -> 9588.8901 | AI39: =+AH39-AH38 -> -9.2599974 | AK39: C.M. | AL39: =+AL43 -> 8494.565 | AM39: =+AM43 -> 92.32423 | AN39: =+AN37 -> 0.53544933 | AO39: =+AO37 -> 90.294153 | AP39: =+AP37 -> -125.73242 | AQ39: =+AR39*$AQ$4+AP39 -> 9104.4974 | AR39: =+((AL39*24*AM39/100*$AC$37)*AN39*AO39)/10000 -> 9555.1033 | AS39: =+AQ39-AQ38 -> -32.638084 | AV39: CM | AW39: =+AW43 -> 8494.565 | AX39: =+AX43 -> 92.32423 | AY39: =+AY37 -> 0.017118629 | AZ39: =+AZ37 -> 91.633787 | BA39: =+BA37 -> 87.936295 | BB39: =+((AW39*24*AX39/100*$AV$36)*AY39*AZ39*BA39)/1000000 -> 25.963358 | BC39: =+BB39-BB38 -> -0.091806408 | BE39: CM | BF39: =+BF44 -> 8494.565 | BG39: =+BG44 -> 92.32423 | BH39: =+BH37 -> 0.017118629 | BI39: =+BI37 -> 91.633787 | BJ39: =+BJ37 -> 87.936295 | BK39: =+BK37 -> 73.248003 | BL39: =+BM39*$BK$4+BK39 -> 99.081544 | BM39: =+((BF39*24*BG39/100*$BE$36)*BH39*BI39*BJ39)/1000000 -> 25.963358 | BN39: =+BL39-BL38 -> -0.091347376
A40: Rec. Mo Global | B40: % | C40: ='ST Original'!Z39 -> 80.579357 | D40: ='ST Original'!#REF! -> #REF! | E40: =+C40-D40 -> #REF! | F40: =+E40/D40 -> #REF! | H40: Rec. Mo Global | I40: % | J40: =C40 -> 80.579357 | K40: ='ST Original'!#REF! -> #REF! | L40: =+J40-K40 -> #REF! | M40: =+L40/K40 -> #REF! | O40: Rec. Mo Global | P40: % | Q40: ='R+P'!$V$47 -> 80.646505 | R40: =C40 -> 80.579357 | S40: =+Q40-R40 -> 0.067148601 | T40: =+S40/R40 -> 0.00083332262 | V40: Rec. Mo Global | W40: % | X40: =Real!U40 -> 81.170583 | Y40: ='ST Original'!$FU$39 -> 80.836534 | Z40: =+X40-Y40 -> 0.33404839 | AA40: =+Z40/Y40 -> 0.0041323938 | AC40: C.M. | AD40: =+AD43 -> 8494.565 | AE40: =+AE43 -> 92.32423 | AF40: =+AF38 -> 0.53544933 | AG40: =+AG38 -> 90.294153 | AH40: =+((AD40*24*AE40/100*$AC$37)*AF40*AG40)/10000 -> 9555.1033 | AI40: =+AH40-AH39 -> -33.786836 | AK40: Ley Cab. Cu,% | AL40: =+AL43 -> 8494.565 | AM40: =+AM43 -> 92.32423 | AN40: =+AN43 -> 0.51875622 | AO40: =+AO37 -> 90.294153 | AP40: =+AP37 -> -125.73242 | AQ40: =+AR40*$AQ$4+AP40 -> 8816.7367 | AR40: =+((AL40*24*AM40/100*$AC$37)*AN40*AO40)/10000 -> 9257.2144 | AS40: =+AQ40-AQ39 -> -287.76063 | AV40: Ley Mo | AW40: =+AW43 -> 8494.565 | AX40: =+AX43 -> 92.32423 | AY40: =+AY43 -> 0.019288224 | AZ40: =+AZ37 -> 91.633787 | BA40: =+BA37 -> 87.936295 | BB40: =+((AW40*24*AX40/100*$AV$36)*AY40*AZ40*BA40)/1000000 -> 29.253924 | BC40: =+BB40-BB39 -> 3.2905659 | BE40: Ley Mo | BF40: =+BF44 -> 8494.565 | BG40: =+BG44 -> 92.32423 | BH40: =+BH44 -> 0.019288224 | BI40: =+BI37 -> 91.633787 | BJ40: =+BJ37 -> 87.936295 | BK40: =+BK37 -> 73.248003 | BL40: =+BM40*$BK$4+BK40 -> 102.35566 | BM40: =+((BF40*24*BG40/100*$BE$36)*BH40*BI40*BJ40)/1000000 -> 29.253924 | BN40: =+BL40-BL39 -> 3.274113
A41: Rec. Mo Colectiva | B41: % | C41: ='ST Original'!X39 -> 91.633787 | D41: ='ST Original'!#REF! -> #REF! | E41: =+C41-D41 -> #REF! | F41: =+E41/D41 -> #REF! | H41: Rec. Mo Colectiva | I41: % | J41: =C41 -> 91.633787 | K41: ='ST Original'!#REF! -> #REF! | L41: =+J41-K41 -> #REF! | M41: =+L41/K41 -> #REF! | O41: Rec. Mo Colectiva | P41: % | Q41: ='R+P'!$T$47 -> 89.806766 | R41: =C41 -> 91.633787 | S41: =+Q41-R41 -> -1.8270206 | T41: =+S41/R41 -> -0.019938285 | V41: Rec. Mo Colectiva | W41: % | X41: =Real!S40 -> 89.313167 | Y41: ='ST Original'!$FS$39 -> 92.043617 | Z41: =+X41-Y41 -> -2.7304503 | AA41: =+Z41/Y41 -> -0.029664744 | AC41: Ley Cab. Cu,% | AD41: =+AD43 -> 8494.565 | AE41: =+AE43 -> 92.32423 | AF41: =+AF43 -> 0.51875622 | AG41: =+AG38 -> 90.294153 | AH41: =+((AD41*24*AE41/100*$AC$37)*AF41*AG41)/10000 -> 9257.2144 | AI41: =+AH41-AH40 -> -297.88885 | AK41: RCu, % | AL41: =+AL43 -> 8494.565 | AM41: =+AM43 -> 92.32423 | AN41: =+AN43 -> 0.51875622 | AO41: =+AO43 -> 90.397219 | AP41: =+AP37 -> -125.73242 | AQ41: =+AR41*$AQ$4+AP41 -> 8826.9441 | AR41: =+((AL41*24*AM41/100*$AC$37)*AN41*AO41)/10000 -> 9267.7811 | AS41: =+AQ41-AQ40 -> 10.207345 | AV41: RMoCol, % | AW41: =+AW43 -> 8494.565 | AX41: =+AX43 -> 92.32423 | AY41: =+AY43 -> 0.019288224 | AZ41: =+AZ43 -> 89.806766 | BA41: =+BA40 -> 87.936295 | BB41: =+((AW41*24*AX41/100*$AV$36)*AY41*AZ41*BA41)/1000000 -> 28.670651 | BC41: =+BB41-BB40 -> -0.58327307 | BE41: RMoCol, % | BF41: =+BF44 -> 8494.565 | BG41: =+BG44 -> 92.32423 | BH41: =+BH44 -> 0.019288224 | BI41: =+BI44 -> 89.806766 | BJ41: =+BJ40 -> 87.936295 | BK41: =+BK37 -> 73.248003 | BL41: =+BM41*$BK$4+BK41 -> 101.7753 | BM41: =+((BF41*24*BG41/100*$BE$36)*BH41*BI41*BJ41)/1000000 -> 28.670651 | BN41: =+BL41-BL40 -> -0.5803567
A42: Rec. Mo Selectiva | B42: % | C42: ='ST Original'!Y39 -> 87.936295 | D42: ='ST Original'!#REF! -> #REF! | E42: =+C42-D42 -> #REF! | F42: =+E42/D42 -> #REF! | H42: Rec. Mo Selectiva | I42: % | J42: =C42 -> 87.936295 | K42: ='ST Original'!#REF! -> #REF! | L42: =+J42-K42 -> #REF! | M42: =+L42/K42 -> #REF! | O42: Rec. Mo Selectiva | P42: % | Q42: ='R+P'!$U$47 -> 89.800033 | R42: =C42 -> 87.936295 | S42: =+Q42-R42 -> 1.863738 | T42: =+S42/R42 -> 0.021194183 | V42: Rec. Mo Selectiva | W42: % | X42: =Real!T40 -> 90.883109 | Y42: ='ST Original'!$FT$39 -> 87.824161 | Z42: =+X42-Y42 -> 3.0589481 | AA42: =+Z42/Y42 -> 0.034830371 | AC42: RCu, % | AD42: =+AD43 -> 8494.565 | AE42: =+AE43 -> 92.32423 | AF42: =+AF43 -> 0.51875622 | AG42: =+AG43 -> 90.397219 | AH42: =+((AD42*24*AE42/100*$AC$37)*AF42*AG42)/10000 -> 9267.7811 | AI42: =+AH42-AH41 -> 10.566609 | AK42: Inv | AL42: =+AL41 -> 8494.565 | AM42: =+AM41 -> 92.32423 | AN42: =+AN41 -> 0.51875622 | AO42: =+AO41 -> 90.397219 | AP42: =+Q4*1000*AQ35 -> -26.019509 | AQ42: =+AR42*$AQ$4+AP42 -> 8926.657 | AR42: =+((AL42*24*AM42/100*$AC$37)*AN42*AO42)/10000 -> 9267.7811 | AS42: =+AQ42-AQ41 -> 99.712909 | AV42: RMoSel, % | AW42: =+AW41 -> 8494.565 | AX42: =+AX41 -> 92.32423 | AY42: =+AY41 -> 0.019288224 | AZ42: =+AZ41 -> 89.806766 | BA42: =+BA43 -> 89.800033 | BB42: =+((AW42*24*AX42/100*$AV$36)*AY42*AZ42*BA42)/1000000 -> 29.278302 | BC42: =+BB42-BB41 -> 0.60765103 | BE42: RMoSel, % | BF42: =+BF44 -> 8494.565 | BG42: =+BG44 -> 92.32423 | BH42: =+BH44 -> 0.019288224 | BI42: =+BI44 -> 89.806766 | BJ42: =+BJ44 -> 89.800033 | BK42: =+BK37 -> 73.248003 | BL42: =+BM42*$BK$4+BK42 -> 102.37991 | BM42: =+((BF42*24*BG42/100*$BE$36)*BH42*BI42*BJ42)/1000000 -> 29.278302 | BN42: =+BL42-BL41 -> 0.60461277
A43: Conc Mo Producido | B43: ton | C43: ='ST Original'!AC39 -> 1615.8935 | D43: ='ST Original'!#REF! -> #REF! | E43: =+C43-D43 -> #REF! | F43: =+E43/D43 -> #REF! | H43: Conc Mo Producido | I43: ton | J43: =C43 -> 1615.8935 | K43: ='ST Original'!#REF! -> #REF! | L43: =+J43-K43 -> #REF! | M43: =+L43/K43 -> #REF! | O43: Conc Mo Producido | P43: ton | Q43: =+'R+P'!$Y$47 -> 2526.0767 | R43: =C43 -> 1615.8935 | S43: =+Q43-R43 -> 910.18323 | T43: =+S43/R43 -> 0.56326932 | V43: Conc Mo Producido | W43: ton | X43: =Real!W40 -> 1701.5102 | Y43: ='ST Original'!$FW$39 -> 905.60737 | Z43: =+X43-Y43 -> 795.90285 | AA43: =+Z43/Y43 -> 0.87886083 | AC43: R + P | AD43: =+Q29 -> 8494.565 | AE43: =+Q32 -> 92.32423 | AF43: =+Q34 -> 0.51875622 | AG43: =+Q35 -> 90.397219 | AH43: =+((AD43*24*AE43/100*$AC$37)*AF43*AG43)/10000 -> 9267.7811 | AI43: =SUM(AI38:AI42) -> 9267.7811 | AK43: R + P | AL43: =+AD43 -> 8494.565 | AM43: =+AE43 -> 92.32423 | AN43: =+AF43 -> 0.51875622 | AO43: =+AG43 -> 90.397219 | AP43: =+AP42 -> -26.019509 | AQ43: =+AR43*$AQ$4+AP43 -> 8926.657 | AR43: =+((AL43*24*AM43/100*$AC$37)*AN43*AO43)/10000 -> 9267.7811 | AS43: =SUM(AS37:AS42) -> 8926.657 | AV43: Real | AW43: =+AD43 -> 8494.565 | AX43: =+AE43 -> 92.32423 | AY43: =+Q39/10000 -> 0.019288224 | AZ43: =+Q41 -> 89.806766 | BA43: =+Q42 -> 89.800033 | BB43: =+((AW43*24*AX43/100*$AV$36)*AY43*AZ43*BA43)/1000000 -> 29.278302 | BC43: =SUM(BC37:BC42) -> 29.278302 | BE43: Inv | BF43: =+BF44 -> 8494.565 | BG43: =+BG44 -> 92.32423 | BH43: =+BH44 -> 0.019288224 | BI43: =+BI44 -> 89.806766 | BJ43: =+BJ44 -> 89.800033 | BK43: =+Q6*1000 -> 92.866388 | BL43: =+BM43*$BK$4+BK43 -> 121.9983 | BM43: =+((BF43*24*BG43/100*$BE$36)*BH43*BI43*BJ43)/1000000 -> 29.278302 | BN43: =+BL43-BL42 -> 19.618384
A44: Ley Conc. Mo | B44: % | C44: ='ST Original'!AA39 -> 50 | D44: ='ST Original'!#REF! -> #REF! | E44: =+C44-D44 -> #REF! | F44: =+E44/D44 -> #REF! | H44: Ley Conc. Mo | I44: % | J44: ='ST Original'!AA37 -> 50 | K44: ='ST Original'!#REF! -> #REF! | L44: =+J44-K44 -> #REF! | M44: =+L44/K44 -> #REF! | O44: Ley Conc. Mo | P44: % | Q44: ='R+P'!$W$47 -> 48.603538 | R44: =C44 -> 50 | S44: =+Q44-R44 -> -1.3964622 | T44: =+S44/R44 -> -0.027929244 | V44: Ley Conc. Mo | W44: % | X44: =Real!V40 -> 29.112025 | Y44: =C44 -> 50 | Z44: =+X44-Y44 -> -20.887975 | AA44: =+Z44/Y44 -> -0.41775949 | BE44: Real | BF44: =+AD43 -> 8494.565 | BG44: =+AE43 -> 92.32423 | BH44: =+Q39/10000 -> 0.019288224 | BI44: =+Q41 -> 89.806766 | BJ44: =+Q42 -> 89.800033 | BK44: =+BK43 -> 92.866388 | BL44: =+BM44*$BK$4+BK44 -> 121.9983 | BM44: =+((BF44*24*BG44/100*$BE$36)*BH44*BI44*BJ44)/1000000 -> 29.278302 | BN44: =SUM(BN37:BN43) -> 121.9983
A46: As Alim. | B46: ppm | C46: ='ST Original'!BI39 -> 27.445147 | D46: ='ST Original'!#REF! -> #REF! | E46: =+C46-D46 -> #REF! | F46: =+E46/D46 -> #REF! | H46: As Alim. | I46: ppm | J46: ='ST Original'!#REF! -> #REF! | K46: ='ST Original'!#REF! -> #REF! | L46: =+J46-K46 -> #REF! | M46: =+L46/K46 -> #REF! | O46: As Alim. | P46: ppm | Q46: ='R+P'!BA47 -> 20.726944 | R46: =C46 -> 27.445147 | S46: =+Q46-R46 -> -6.7182024 | T46: =+S46/R46 -> -0.24478654 | V46: As Alim. | W46: ppm | X46: =Real!AE40 -> 18.100498 | Y46: ='ST Original'!$GG$39 -> 28.042765 | Z46: =+X46-Y46 -> -9.9422669 | AA46: =+Z46/Y46 -> -0.35453946
A47: As Conc. | B47: ppm | C47: ='ST Original'!BJ39 -> 1264.0914 | D47: ='ST Original'!#REF! -> #REF! | E47: =+C47-D47 -> #REF! | F47: =+E47/D47 -> #REF! | H47: As Conc. | I47: ppm | J47: ='ST Original'!#REF! -> #REF! | K47: ='ST Original'!#REF! -> #REF! | L47: =+J47-K47 -> #REF! | M47: =+L47/K47 -> #REF! | O47: As Conc. | P47: ppm | Q47: ='R+P'!BB47 -> 978.90256 | R47: =C47 -> 1264.0914 | S47: =+Q47-R47 -> -285.18884 | T47: =+S47/R47 -> -0.22560777 | V47: As Conc. | W47: ppm | X47: =Real!AF40 -> 887.39033 | Y47: ='ST Original'!$GH$39 -> 1261.9244 | Z47: =+X47-Y47 -> -374.5341 | AA47: =+Z47/Y47 -> -0.29679598
A50: COMPARACION REAL y SHORT TERM ORIGINAL VS BUDGET | H50: COMPARACION REAL y SHORT TERM ORIGINAL VS FORECAST | O50: COMPARACION REAL y PROYECCION VS BUDGET | V50: COMPARACION REAL y PROYECCION VS FORECAST
A51: PARA EL MES | B51: =C2 -> #REF! | E51: VARIACION | H51: PARA EL MES | I51: =C2 -> #REF! | L51: VARIACION | O51: PARA EL MES | P51: =C2 -> #REF! | S51: VARIACION | V51: PARA EL MES | W51: =C2 -> #REF! | Z51: VARIACION
B52: UNIDAD | C52: R+S.T. | D52: B | E52: Q | F52: % | I52: UNIDAD | J52: R+S.T. | K52: F | L52: Q | M52: % | P52: UNIDAD | Q52: R+P | R52: B | S52: Q | T52: % | W52: UNIDAD | X52: R+P | Y52: F | Z52: Q | AA52: %
A53: Cu Fino Eq. Producido | B53: Kton | C53: ='Real+S.T.'!AD48/1000 -> 29.151257 | D53: =D11 -> 22.933613 | E53: =+C53-D53 -> 6.2176444 | F53: =+E53/D53 -> 0.27111491 | H53: Cu Fino Eq. Producido | I53: Kton | J53: =C53 -> 29.151257 | K53: =K11 -> #REF! | L53: =+J53-K53 -> #REF! | M53: =+L53/K53 -> #REF! | O53: Cu Fino Eq. Producido | P53: Kton | Q53: =Q11 -> 29.993232 | R53: =D11 -> 22.933613 | S53: =+Q53-R53 -> 7.0596189 | T53: =+S53/R53 -> 0.30782846 | V53: Cu Fino Eq. Producido | W53: Kton | X53: =Q53 -> 29.993232 | Y53: =K53 -> #REF! | Z53: =+X53-Y53 -> #REF! | AA53: =+Z53/Y53 -> #REF!
A54: Cu Fino Eq. Filtrado (Ppto) | B54: Kton | C54: =C57+C61*Factores!$D$9 -> 30.599953 | D54: =D24 -> 0 | E54: =+C54-D54 -> 30.599953 | F54: =+E54/D54 -> #DIV/0! | H54: Cu Fino Eq. Filtrado (Ppto) | I54: Kton | J54: =C54 -> 30.599953 | K54: =K24 -> 0 | L54: =+J54-K54 -> 30.599953 | M54: =+L54/K54 -> #DIV/0! | O54: Cu Fino Eq. Filtrado (Bdgt) | P54: Kton | Q54: =Q24 -> 194.44 | R54: =D24 -> 0 | S54: =+Q54-R54 -> 194.44 | T54: =+S54/R54 -> #DIV/0! | V54: Cu Fino Eq. Filtrado (Bdgt) | W54: Kton | X54: =Q54 -> 194.44 | Y54: =K54 -> 0 | Z54: =+X54-Y54 -> 194.44 | AA54: =+Z54/Y54 -> #DIV/0!
A55: Cu Fino Eq. Filtrado (Real) | B55: Kton | C55: =C58+C62*Factores!$F$9 -> 30.599953 | D55: =D58+D62*Factores!$F$9 -> 33.406194 | E55: =+C55-D55 -> -2.8062406 | F55: =+E55/D55 -> -0.084003602 | H55: Cu Fino Eq. Filtrado (Real) | I55: Kton | J55: =J58+J62*Factores!$F$9 -> 30.599953 | K55: =K58+K62*Factores!$F$9 -> #REF! | L55: =+J55-K55 -> #REF! | M55: =+L55/K55 -> #REF! | O55: Cu Fino Eq. Filtrado (Real) | P55: Kton | Q55: =Q58+Q62*Factores!$F$9 -> 29.291621 | R55: =R58+R62*Factores!$F$9 -> 33.406194 | S55: =+Q55-R55 -> -4.1145723 | T55: =+S55/R55 -> -0.12316795 | V55: Cu Fino Eq. Filtrado (Real) | W55: Kton | X55: =X58+X62*Factores!$F$9 -> 29.291621 | Y55: =Y58+Y62*Factores!$F$9 -> #REF! | Z55: =+X55-Y55 -> #REF! | AA55: =+Z55/Y55 -> #REF!
A56: Cu Fino Producido | B56: Kton | C56: ='Real+S.T.'!O48/1000 -> 27.752623 | D56: =D14 -> 22.933613 | E56: =+C56-D56 -> 4.8190096 | F56: =+E56/D56 -> 0.21012867 | H56: Cu Fino Producido | I56: Kton | J56: =C56 -> 27.752623 | K56: =K14 -> #REF! | L56: =+J56-K56 -> #REF! | M56: =+L56/K56 -> #REF! | O56: Cu Fino Producido | P56: Kton | Q56: =Q14 -> 27.36202 | R56: =D14 -> 22.933613 | S56: =+Q56-R56 -> 4.4284072 | T56: =+S56/R56 -> 0.19309679 | V56: Cu Fino Producido | W56: Kton | X56: =Q56 -> 27.36202 | Y56: =K56 -> #REF! | Z56: =+X56-Y56 -> #REF! | AA56: =+Z56/Y56 -> #REF!
A57: Cu Fino Filtrado Pagable (Ppto) | B57: Kton | C57: ='Real+S.T.'!AI39/1000*Factores!$D$7 -> 27.714024 | D57: =D15 -> 31.316639 | E57: =+C57-D57 -> -3.6026147 | F57: =+E57/D57 -> -0.11503836 | H57: Cu Fino Filtrado Pagable (Ppto) | I57: Kton | J57: =C57 -> 27.714024 | K57: =K15 -> #REF! | L57: =+J57-K57 -> #REF! | M57: =+L57/K57 -> #REF! | O57: Cu Fino Filtrado Pagable (Bdgt) | P57: Kton | Q57: =Q15 -> 26.405692 | R57: =D15 -> 31.316639 | S57: =+Q57-R57 -> -4.9109465 | T57: =+S57/R57 -> -0.15681589 | V57: Cu Fino Filtrado Pagable (Bdgt) | W57: Kton | X57: =Q57 -> 26.405692 | Y57: =K57 -> #REF! | Z57: =+X57-Y57 -> #REF! | AA57: =+Z57/Y57 -> #REF!
A58: Cu Fino Filtrado Pagable (Real) | B58: Kton | C58: =C57/Factores!$D$7*Factores!$F$7 -> 27.714024 | D58: =D57/Factores!$D$7*Factores!$F$7 -> 31.316639 | E58: =+C58-D58 -> -3.6026147 | F58: =+E58/D58 -> -0.11503836 | H58: Cu Fino Filtrado Pagable (Real) | I58: Kton | J58: =J57/Factores!$D$7*Factores!$F$7 -> 27.714024 | K58: =K57/Factores!$D$7*Factores!$F$7 -> #REF! | L58: =+J58-K58 -> #REF! | M58: =+L58/K58 -> #REF! | O58: Cu Fino Filtrado Pagable (Real) | P58: Kton | Q58: =Q57/Factores!$D$7*Factores!$F$7 -> 26.405692 | R58: =R57/Factores!$D$7*Factores!$F$7 -> 31.316639 | S58: =+Q58-R58 -> -4.9109465 | T58: =+S58/R58 -> -0.15681589 | V58: Cu Fino Filtrado Pagable (Real) | W58: Kton | X58: =X57/Factores!$D$7*Factores!$F$7 -> 26.405692 | Y58: =Y57/Factores!$D$7*Factores!$F$7 -> #REF! | Z58: =+X58-Y58 -> #REF! | AA58: =+Z58/Y58 -> #REF!
A59: Delta Inventario Cu Fino | B59: Kton | C59: =C56-C57/Factores!D7 -> -1.0561339 | H59: Delta Inventario Cu Fino | I59: Kton | J59: =C59 -> -1.0561339 | M59: =+L59/K59 -> #DIV/0! | O59: Delta Inventario Cu Fino | P59: Kton | Q59: =Q17 -> -0.086724087 | V59: Delta Inventario Cu Fino | W59: Kton | X59: =Q59 -> -0.086724087
A60: Mo Fino Producido | B60: Kton | C60: ='Real+S.T.'!X39/1000 -> 0.85048716 | D60: =D18 -> 0.49377314 | E60: =+C60-D60 -> 0.35671402 | F60: =+E60/D60 -> 0.72242491 | H60: Mo Fino Producido | I60: Kton | J60: =C60 -> 0.85048716 | K60: =K18 -> #REF! | L60: =+J60-K60 -> #REF! | M60: =+L60/K60 -> #REF! | O60: Mo Fino Producido | P60: Kton | Q60: =Q18 -> 0.90762735 | R60: =D18 -> 0.49377314 | S60: =+Q60-R60 -> 0.41385421 | T60: =+S60/R60 -> 0.83814646 | V60: Mo Fino Producido | W60: Kton | X60: =Q60 -> 0.90762735 | Y60: =K60 -> #REF! | Z60: =+X60-Y60 -> #REF! | AA60: =+Z60/Y60 -> #REF!
A61: Mo Fino Envasado Pagable (Ppto) | B61: Kton | C61: =+'Real+S.T.'!Z39/1000*Factores!$D$8 -> 0.99549127 | D61: =D19 -> 0.72078476 | E61: =+C61-D61 -> 0.2747065 | F61: =+E61/D61 -> 0.38112141 | H61: Mo Fino Envasado Pagable (Ppto) | I61: Kton | J61: =C61 -> 0.99549127 | K61: =K19 -> #REF! | L61: =+J61-K61 -> #REF! | M61: =+L61/K61 -> #REF! | O61: Mo Fino Envasado Pagable (Bdgt) | P61: Kton | Q61: =Q19 -> 0.99549127 | R61: =D19 -> 0.72078476 | S61: =+Q61-R61 -> 0.2747065 | T61: =+S61/R61 -> 0.38112141 | V61: Mo Fino Envasado Pagable (Bdgt) | W61: Kton | X61: =Q61 -> 0.99549127 | Y61: =K61 -> #REF! | Z61: =+X61-Y61 -> #REF! | AA61: =+Z61/Y61 -> #REF!
A62: Mo Fino Envasado Pagable (Real) | B62: Kton | C62: =C61/Factores!$D$8*Factores!$F$8 -> 0.99549127 | D62: =D61/Factores!$D$8*Factores!$F$8 -> 0.72078476 | E62: =+C62-D62 -> 0.2747065 | F62: =+E62/D62 -> 0.38112141 | H62: Mo Fino Envasado Pagable (Real) | I62: Kton | J62: =J61/Factores!$D$8*Factores!$F$8 -> 0.99549127 | K62: =K61/Factores!$D$8*Factores!$F$8 -> #REF! | L62: =+J62-K62 -> #REF! | M62: =+L62/K62 -> #REF! | O62: Mo Fino Envasado Pagable (Real) | P62: Kton | Q62: =Q61/Factores!$D$8*Factores!$F$8 -> 0.99549127 | R62: =R61/Factores!$D$8*Factores!$F$8 -> 0.72078476 | S62: =+Q62-R62 -> 0.2747065 | T62: =+S62/R62 -> 0.38112141 | V62: Mo Fino Envasado Pagable (Real) | W62: Kton | X62: =X61/Factores!$D$8*Factores!$F$8 -> 0.99549127 | Y62: =Y61/Factores!$D$8*Factores!$F$8 -> #REF! | Z62: =+X62-Y62 -> #REF! | AA62: =+Z62/Y62 -> #REF! | AC62: ='TP sin BM'!D2 -> 16.5
A63: Delta Inventario Mo Fino | B63: Kton | C63: =C60-C61/Factores!D8 -> -0.15000658 | H63: Delta Inventario Mo Fino | I63: Kton | J63: =C63 -> -0.15000658 | M63: =+L63/K63 -> #DIV/0! | O63: Delta Inventario Mo Fino | P63: Kton | Q63: =Q21 -> -0.092866388 | V63: Delta Inventario Mo Fino | W63: Kton | X63: =Q63 -> -0.092866388
AC64: CUMPLIMIENTO REAL vs ST ACUM. MES | AJ64: CUMPLIMIENTO REAL vs BUDGET ACUM. AÑO
A65: Extracción | B65: Kton | C65: ='Real+S.T.'!CP48 -> #REF! | D65: =D26 -> #REF! | E65: =+C65-D65 -> #REF! | F65: =+E65/D65 -> #REF! | H65: Extracción | I65: Kton | J65: =C65 -> #REF! | K65: =K26 -> #REF! | L65: =+J65-K65 -> #REF! | M65: =+L65/K65 -> #REF! | O65: Extracción | P65: Kton | Q65: =Q26 -> #REF! | R65: =D65 -> #REF! | S65: =+Q65-R65 -> #REF! | T65: =+S65/R65 -> #REF! | V65: Extracción | W65: Kton | X65: =Q65 -> #REF! | Y65: =K65 -> #REF! | Z65: =+X65-Y65 -> #REF! | AA65: =+Z65/Y65 -> #REF! | AJ65: ,
A66: Tonelaje Procesado | B66: Kton | C66: ='Real+S.T.'!F48 -> 5842.4355 | D66: =D27 -> #REF! | E66: =+C66-D66 -> #REF! | F66: =+E66/D66 -> #REF! | H66: Tonelaje Procesado | I66: Kton | J66: =C66 -> 5842.4355 | K66: =K27 -> #REF! | L66: =+J66-K66 -> #REF! | M66: =+L66/K66 -> #REF! | O66: Tonelaje Procesado | P66: Kton | Q66: =Q27 -> 5834.851 | R66: =D66 -> #REF! | S66: =+Q66-R66 -> #REF! | T66: =+S66/R66 -> #REF! | V66: Tonelaje Procesado | W66: Kton | X66: =Q66 -> 5834.851 | Y66: =K66 -> #REF! | Z66: =+X66-Y66 -> #REF! | AA66: =+Z66/Y66 -> #REF! | AE66: REAL | AF66: ST | AG66: Delta | AH66: % Desv. | AL66: REAL | AM66: BUDGET | AN66: Delta | AO66: % Desv.
A67: Toneladas por día | B67: Ktpd | C67: =C66/COUNT('Real+S.T.'!B8:B38) -> 188.46566 | D67: =D28 -> #REF! | E67: =+C67-D67 -> #REF! | F67: =+E67/D67 -> #REF! | H67: Toneladas por día | I67: Ktpd | J67: =C67 -> 188.46566 | K67: =K28 -> #REF! | L67: =+J67-K67 -> #REF! | M67: =+L67/K67 -> #REF! | O67: Toneladas por día | P67: Ktpd | Q67: =Q28 -> 188.221 | R67: =D67 -> #REF! | S67: =+Q67-R67 -> #REF! | T67: =+S67/R67 -> #REF! | V67: Toneladas por día | W67: Ktpd | X67: =Q67 -> 188.221 | Y67: =K67 -> #REF! | Z67: =+X67-Y67 -> #REF! | AA67: =+Z67/Y67 -> #REF! | AC67: Extracción Mina | AD67: ktms | AE67: =Real!AW40/1000 -> 7028.6855 | AF67: =Real!#REF!/1000 -> #REF! | AG67: =+AE67-AF67 -> #REF! | AH67: =+(AE67-AF67)/AF67 -> #REF! | AJ67: Extracción Mina | AK67: ktms | AL67: ='R+RP+B'!#REF! -> #REF! | AM67: =BDGT!#REF! -> #REF! | AN67: =+AL67-AM67 -> #REF! | AO67: =+(AL67-AM67)/AM67 -> #REF!
A68: Rendimiento | B68: Tph | C68: ='Real+S.T.'!F48*1000/(24*COUNT('Real+S.T.'!B8:B38)*C70%) -> 8484.7125 | D68: =D29 -> #REF! | E68: =+C68-D68 -> #REF! | F68: =+E68/D68 -> #REF! | H68: Rendimiento | I68: Tph | J68: =C68 -> 8484.7125 | K68: =K29 | L68: =+J68-K68 -> #VALUE! | M68: =+L68/K68 -> #VALUE! | O68: Rendimiento | P68: Tph | Q68: =Q29 -> 8494.565 | R68: =D68 -> #REF! | S68: =+Q68-R68 -> #REF! | T68: =+S68/R68 -> #REF! | V68: Rendimiento | W68: Tph | X68: =Q68 -> 8494.565 | Y68: =K68 | Z68: =+X68-Y68 -> #VALUE! | AA68: =+Z68/Y68 -> #VALUE! | AC68: Tratamiento | AD68: ktms | AE68: =X27 -> 2919.0798 | AF68: =Y27 -> 2933.8431 | AG68: =+AE68-AF68 -> -14.763304 | AH68: =+(AE68-AF68)/AF68 -> -0.0050320699 | AJ68: Tratamiento | AK68: ktms | AL68: =Q183 -> 12013.913 | AM68: =R183 -> 0 | AN68: =+AL68-AM68 -> 12013.913 | AO68: =+(AL68-AM68)/AM68 -> #DIV/0!
A69: Mineral Duro | B69: % | C69: ='Real+S.T.'!CM39 -> 68.318784 | D69: =D30 -> #REF! | E69: =+C69-D69 -> #REF! | F69: =+E69/D69 -> #REF! | H69: Mineral Duro | I69: % | J69: =C69 -> 68.318784 | K69: =K30 -> #REF! | L69: =+J69-K69 -> #REF! | M69: =+L69/K69 -> #REF! | O69: Mineral Duro | P69: % | Q69: =Q30 -> 67.341178 | R69: =D69 -> #REF! | S69: =+R69-Q69 -> #REF! | T69: =+S69/R69 -> #REF! | V69: Mineral Duro | W69: % | X69: =Q69 -> 67.341178 | Y69: =K69 -> #REF! | Z69: =+Y69-X69 -> #REF! | AA69: =+Z69/Y69 -> #REF! | AC69: CM | AD69: % | AE69: =X32 -> 88.117328 | AF69: =Y32 -> 88.216548 | AG69: =+AE69-AF69 -> -0.099220776 | AH69: =+(AE69-AF69)/AF69 -> -0.0011247411 | AJ69: CM | AK69: % | AL69: =Q187 -> 78.63325 | AM69: =R187 -> 0 | AN69: =+AL69-AM69 -> 78.63325 | AO69: =+(AL69-AM69)/AM69 -> #DIV/0!
A70: Coeficiente de Marcha | B70: % | C70: ='Real+S.T.'!G48 -> 92.551584 | D70: =D32 -> #REF! | E70: =+C70-D70 -> #REF! | F70: =+E70/D70 -> #REF! | H70: Coeficiente de Marcha | I70: % | J70: =C70 -> 92.551584 | K70: =K32 -> #REF! | L70: =+J70-K70 -> #REF! | M70: =+L70/K70 -> #REF! | O70: Coeficiente de Marcha | P70: % | Q70: =Q32 -> 92.32423 | R70: =D70 -> #REF! | S70: =+Q70-R70 -> #REF! | T70: =+S70/R70 -> #REF! | V70: Coeficiente de Marcha | W70: % | X70: =Q70 -> 92.32423 | Y70: =K70 -> #REF! | Z70: =+X70-Y70 -> #REF! | AA70: =+Z70/Y70 -> #REF! | AC70: Rendimiento | AD70: tph | AE70: =+Real!AK5 -> 8365.4531 | AF70: ='ST Original'!$FI$39 -> 8414.2412 | AG70: =+AE70-AF70 -> -48.788062 | AH70: =+(AE70-AF70)/AF70 -> -0.0057982724 | AJ70: Rendimiento | AK70: tph | AL70: =Q185 -> 8376.3229 | AM70: =R185 -> #REF! | AN70: =+AL70-AM70 -> #REF! | AO70: =+(AL70-AM70)/AM70 -> #REF!
AC71: AxB | AD71: % | AE71: =X33 -> 37.942958 | AF71: =Y33 -> 36.900097 | AG71: =-AE71+AF71 -> -1.0428608 | AH71: =-(AE71-AF71)/AF71 -> -0.028261735 | AJ71: Dureza Mineral | AK71: % | AL71: =Q186 -> 0 | AM71: =R186 -> #REF! | AN71: =-AL71+AM71 -> #REF! | AO71: =-(AL71-AM71)/AM71 -> #REF!
A72: Ley Alim. Cu | B72: % | C72: ='Real+S.T.'!I48 -> 0.52521338 | D72: =D34 -> #REF! | E72: =+C72-D72 -> #REF! | F72: =+E72/D72 -> #REF! | H72: Ley Alim. Cu | I72: % | J72: =C72 -> 0.52521338 | K72: =K34 -> #REF! | L72: =+J72-K72 -> #REF! | M72: =+L72/K72 -> #REF! | O72: Ley Alim. Cu | P72: % | Q72: =Q34 -> 0.51875622 | R72: =D72 -> #REF! | S72: =+Q72-R72 -> #REF! | T72: =+S72/R72 -> #REF! | V72: Ley Alim. Cu | W72: % | X72: =Q72 -> 0.51875622 | Y72: =K72 -> #REF! | Z72: =+X72-Y72 -> #REF! | AA72: =+Z72/Y72 -> #REF! | AC72: F80 | AD72: In | AE72: =X31 -> 4.6902586 | AF72: =Y31 -> 4.1675369 | AG72: =-AE72+AF72 -> -0.5227217 | AH72: =-(AE72-AF72)/AF72 -> -0.12542701 | AJ72: F80 | AK72: In | AL72: =+'R+RP+B'!AE20 -> 4.8102222 | AM72: =+BDGT!Y19 -> #REF! | AN72: =-AL72+AM72 -> #REF! | AO72: =-(AL72-AM72)/AM72 -> #REF!
A73: Rec. Cu | B73: % | C73: ='Real+S.T.'!J48 -> 90.442868 | D73: =D35 -> #REF! | E73: =+C73-D73 -> #REF! | F73: =+E73/D73 -> #REF! | H73: Rec. Cu | I73: % | J73: =C73 -> 90.442868 | K73: =K35 -> #REF! | L73: =+J73-K73 -> #REF! | M73: =+L73/K73 -> #REF! | O73: Rec. Cu | P73: % | Q73: =Q35 -> 90.397219 | R73: =D73 -> #REF! | S73: =+Q73-R73 -> #REF! | T73: =+S73/R73 -> #REF! | V73: Rec. Cu | W73: % | X73: =Q73 -> 90.397219 | Y73: =K73 -> #REF! | Z73: =+X73-Y73 -> #REF! | AA73: =+Z73/Y73 -> #REF! | AC73: Ley Cu Mineral | AD73: % | AE73: =X34 -> 0.49046726 | AF73: =Y34 -> 0.51107742 | AG73: =+AE73-AF73 -> -0.020610154 | AH73: =+(AE73-AF73)/AF73 -> -0.040326872 | AJ73: Ley Cu Mineral | AK73: % | AL73: =Q189 -> 0.50415579 | AM73: =R189 -> #REF! | AN73: =+AL73-AM73 -> #REF! | AO73: =+(AL73-AM73)/AM73 -> #REF!
A74: Conc Cu Producido | B74: Kton | C74: ='Real+S.T.'!M48/1000 -> 104.47782 | D74: =D36 -> #REF! | E74: =+C74-D74 -> #REF! | F74: =+E74/D74 -> #REF! | H74: Conc Cu Producido | I74: Kton | J74: =C74 -> 104.47782 | K74: =K36 -> #REF! | L74: =+J74-K74 -> #REF! | M74: =+L74/K74 -> #REF! | O74: Conc Cu Producido | P74: Kton | Q74: =Q36 -> 103.61851 | R74: =D74 -> #REF! | S74: =+Q74-R74 -> #REF! | T74: =+S74/R74 -> #REF! | V74: Conc Cu Producido | W74: Kton | X74: =Q74 -> 103.61851 | Y74: =K74 -> #REF! | Z74: =+X74-Y74 -> #REF! | AA74: =+Z74/Y74 -> #REF! | AC74: Ley Mo Mineral | AD74: ppm | AE74: =X39 -> 209.05586 | AF74: =Y39 -> 190.92613 | AG74: =+AE74-AF74 -> 18.129727 | AH74: =+(AE74-AF74)/AF74 -> 0.09495676 | AJ74: Ley Mo Mineral | AK74: ppm | AL74: =Q194 -> 196.54499 | AM74: =R194 -> #REF! | AN74: =+AL74-AM74 -> #REF! | AO74: =+(AL74-AM74)/AM74 -> #REF!
A75: Ley Conc. Cu | B75: % | C75: ='Real+S.T.'!K48 -> 26.563173 | D75: =D37 -> 26.777705 | E75: =+C75-D75 -> -0.2145325 | F75: =+E75/D75 -> -0.0080116089 | H75: Ley Conc. Cu | I75: % | J75: =C75 -> 26.563173 | K75: =K37 -> #REF! | L75: =+J75-K75 -> #REF! | M75: =+L75/K75 -> #REF! | O75: Ley Conc. Cu | P75: % | Q75: =Q37 -> 26.406498 | R75: =D75 -> 26.777705 | S75: =+Q75-R75 -> -0.37120691 | T75: =+S75/R75 -> -0.013862536 | V75: Ley Conc. Cu | W75: % | X75: =Q75 -> 26.406498 | Y75: =K75 -> #REF! | Z75: =+X75-Y75 -> #REF! | AA75: =+Z75/Y75 -> #REF! | AC75: Recup Cu | AD75: % | AE75: =X35 -> 90.621182 | AF75: =Y35 -> 90.302073 | AG75: =+AE75-AF75 -> 0.31910823 | AH75: =+(AE75-AF75)/AF75 -> 0.0035337863 | AJ75: Recup Cu | AK75: % | AL75: =Q190 -> 90.586122 | AM75: =R190 -> #REF! | AN75: =+AL75-AM75 -> #REF! | AO75: =+(AL75-AM75)/AM75 -> #REF!
AC76: Ley Cu Concol | AD76: % | AE76: =X37 -> 25.931627 | AF76: =Y37 -> 26.389507 | AG76: =+AE76-AF76 -> -0.45788027 | AH76: =+(AE76-AF76)/AF76 -> -0.017350846 | AJ76: Ley Cu Concol | AK76: % | AL76: =Q192 -> 26.706672 | AM76: =R192 -> #REF! | AN76: =+AL76-AM76 -> #REF! | AO76: =+(AL76-AM76)/AM76 -> #REF!
A77: Ley Alim. Mo | B77: ppm | C77: ='Real+S.T.'!P48 -> 180.19464 | D77: =D39 -> #REF! | E77: =+C77-D77 -> #REF! | F77: =+E77/D77 -> #REF! | H77: Ley Alim. Mo | I77: ppm | J77: =C77 -> 180.19464 | K77: =K39 -> #REF! | L77: =+J77-K77 -> #REF! | M77: =+L77/K77 -> #REF! | O77: Ley Alim. Mo | P77: ppm | Q77: =Q39 -> 192.88224 | R77: =D77 -> #REF! | S77: =+Q77-R77 -> #REF! | T77: =+S77/R77 -> #REF! | V77: Ley Alim. Mo | W77: ppm | X77: =Q77 -> 192.88224 | Y77: =K77 -> #REF! | Z77: =+X77-Y77 -> #REF! | AA77: =+Z77/Y77 -> #REF! | AC77: Recup Mo Colectiva | AD77: % | AE77: =X41 -> 89.313167 | AF77: =Y41 -> 92.043617 | AG77: =+AE77-AF77 -> -2.7304503 | AH77: =+(AE77-AF77)/AF77 -> -0.029664744 | AJ77: Recup Mo Colectiva | AK77: % | AL77: =Q196 -> 90.297335 | AM77: =R196 -> #REF! | AN77: =+AL77-AM77 -> #REF! | AO77: =+(AL77-AM77)/AM77 -> #REF!
A78: Rec. Mo Global | B78: % | C78: ='Real+S.T.'!S48 -> 80.78523 | D78: =D40 -> #REF! | E78: =+C78-D78 -> #REF! | F78: =+E78/D78 -> #REF! | H78: Rec. Mo Global | I78: % | J78: =C78 -> 80.78523 | K78: =K40 -> #REF! | L78: =+J78-K78 -> #REF! | M78: =+L78/K78 -> #REF! | O78: Rec. Mo Global | P78: % | Q78: =Q40 -> 80.646505 | R78: =D78 -> #REF! | S78: =+Q78-R78 -> #REF! | T78: =+S78/R78 -> #REF! | V78: Rec. Mo Global | W78: % | X78: =Q78 -> 80.646505 | Y78: =K78 -> #REF! | Z78: =+X78-Y78 -> #REF! | AA78: =+Z78/Y78 -> #REF! | AC78: Recup Mo Selectiva | AD78: % | AE78: =X42 -> 90.883109 | AF78: =Y42 -> 87.824161 | AG78: =+AE78-AF78 -> 3.0589481 | AH78: =+(AE78-AF78)/AF78 -> 0.034830371 | AJ78: Recup Mo Selectiva | AK78: % | AL78: =Q197 -> 88.625801 | AM78: =R197 -> #REF! | AN78: =+AL78-AM78 -> #REF! | AO78: =+(AL78-AM78)/AM78 -> #REF!
A79: Rec. Mo Colectiva | B79: % | C79: ='Real+S.T.'!Q48 -> 90.070561 | D79: =D41 -> #REF! | E79: =+C79-D79 -> #REF! | F79: =+E79/D79 -> #REF! | H79: Rec. Mo Colectiva | I79: % | J79: =C79 -> 90.070561 | K79: =K41 -> #REF! | L79: =+J79-K79 -> #REF! | M79: =+L79/K79 -> #REF! | O79: Rec. Mo Colectiva | P79: % | Q79: =Q41 -> 89.806766 | R79: =D79 -> #REF! | S79: =+Q79-R79 -> #REF! | T79: =+S79/R79 -> #REF! | V79: Rec. Mo Colectiva | W79: % | X79: =Q79 -> 89.806766 | Y79: =K79 -> #REF! | Z79: =+X79-Y79 -> #REF! | AA79: =+Z79/Y79 -> #REF! | AC79: Finos Cu Producidos | AD79: tmf | AE79: =X14*1000 -> 12974.353 | AF79: =Y14*1000 -> 13540.082 | AG79: =+AE79-AF79 -> -565.72901 | AH79: =+(AE79-AF79)/AF79 -> -0.0417818 | AJ79: Finos Cu Producidos | AK79: tmf | AL79: =Q170*1000 -> 54860.16 | AM79: =R170*1000 -> #REF! | AN79: =+AL79-AM79 -> #REF! | AO79: =+(AL79-AM79)/AM79 -> #REF!
A80: Rec. Mo Selectiva | B80: % | C80: ='Real+S.T.'!R48 -> 89.691048 | D80: =D42 -> #REF! | E80: =+C80-D80 -> #REF! | F80: =+E80/D80 -> #REF! | H80: Rec. Mo Selectiva | I80: % | J80: =C80 -> 89.691048 | K80: =K42 -> #REF! | L80: =+J80-K80 -> #REF! | M80: =+L80/K80 -> #REF! | O80: Rec. Mo Selectiva | P80: % | Q80: =Q42 -> 89.800033 | R80: =D80 -> #REF! | S80: =+Q80-R80 -> #REF! | T80: =+S80/R80 -> #REF! | V80: Rec. Mo Selectiva | W80: % | X80: =Q80 -> 89.800033 | Y80: =K80 -> #REF! | Z80: =+X80-Y80 -> #REF! | AA80: =+Z80/Y80 -> #REF! | AC80: Finos Mo Producido | AD80: tmf | AE80: =X18*1000 -> 495.34409 | AF80: =Y18*1000 -> 452.80369 | AG80: =+AE80-AF80 -> 42.540401 | AH80: =+(AE80-AF80)/AF80 -> 0.093948884 | AJ80: Finos Mo Producido | AK80: tmf | AL80: =Q174*1000 -> 0 | AM80: =R174*1000 -> #REF! | AN80: =+AL80-AM80 -> #REF! | AO80: =+(AL80-AM80)/AM80 -> #REF!
A81: Conc Mo Producido | B81: ton | C81: ='Real+S.T.'!V39 -> 2411.7964 | D81: =D43 -> #REF! | E81: =+C81-D81 -> #REF! | F81: =+E81/D81 -> #REF! | H81: Conc Mo Producido | I81: ton | J81: =C81 -> 2411.7964 | K81: =K43 -> #REF! | L81: =+J81-K81 -> #REF! | M81: =+L81/K81 -> #REF! | O81: Conc Mo Producido | P81: ton | Q81: =Q43 -> 2526.0767 | R81: =D81 -> #REF! | S81: =+Q81-R81 -> #REF! | T81: =+S81/R81 -> #REF! | V81: Conc Mo Producido | W81: ton | X81: =Q81 -> 2526.0767 | Y81: =K81 -> #REF! | Z81: =+X81-Y81 -> #REF! | AA81: =+Z81/Y81 -> #REF! | AC81: Finos Cu Filt. Pagable | AD81: tmf | AE81: =X15*1000 -> 12598.464 | AF81: =Y16*1000 -> 12114.235 | AG81: =+AE81-AF81 -> 484.22847 | AH81: =+(AE81-AF81)/AF81 -> 0.039971856 | AJ81: Finos Cu Filt. Pagable | AK81: tmf | AL81: =Q171*1000 -> 52317.338 | AM81: =R171*1000 -> #REF! | AN81: =+AL81-AM81 -> #REF! | AO81: =+(AL81-AM81)/AM81 -> #REF!
A82: Ley Conc. Mo | B82: % | C82: ='Real+S.T.'!T39 -> 48.605351 | D82: =D44 -> #REF! | E82: =+C82-D82 -> #REF! | F82: =+E82/D82 -> #REF! | H82: Ley Conc. Mo | I82: % | J82: =C82 -> 48.605351 | K82: =K44 -> #REF! | L82: =+J82-K82 -> #REF! | M82: =+L82/K82 -> #REF! | O82: Ley Conc. Mo | P82: % | Q82: =Q44 -> 48.603538 | R82: =D82 -> #REF! | S82: =+Q82-R82 -> #REF! | T82: =+S82/R82 -> #REF! | V82: Ley Conc. Mo | W82: % | X82: =Q82 -> 48.603538 | Y82: =K82 -> #REF! | Z82: =+X82-Y82 -> #REF! | AA82: =+Z82/Y82 -> #REF! | AC82: Finos Mo Env. Pagable | AD82: tmf | AE82: =X19*1000 -> 565.60301 | AF82: =Y19*1000 -> 446.90052 | AG82: =+AE82-AF82 -> 118.70248 | AH82: =+(AE82-AF82)/AF82 -> 0.26561276 | AJ82: Finos Mo Env. Pagable | AK82: tmf | AL82: =Q175*1000 -> 1758.9287 | AM82: =R175*1000 -> #DIV/0! | AN82: =+AL82-AM82 -> #DIV/0! | AO82: =+(AL82-AM82)/AM82 -> #DIV/0!
A84: As Alim. | B84: ppm | C84: ='Real+S.T.'!AU39 -> 22.476141 | D84: =D46 -> #REF! | E84: =+C84-D84 -> #REF! | F84: =+E84/D84 -> #REF! | H84: As Alim. | I84: ppm | J84: =C84 -> 22.476141 | K84: =K46 -> #REF! | L84: =+J84-K84 -> #REF! | M84: =+L84/K84 -> #REF! | O84: As Alim. | P84: ppm | Q84: =Q46 -> 20.726944 | R84: =D84 -> #REF! | S84: =+R84-Q84 -> #REF! | T84: =+S84/R84 -> #REF! | V84: As Alim. | W84: ppm | X84: =Q84 -> 20.726944 | Y84: =K84 -> #REF! | Z84: =+Y84-X84 -> #REF! | AA84: =+Z84/Y84 -> #REF!
A85: As Conc. | B85: ppm | C85: ='Real+S.T.'!AV39 -> 1062.708 | D85: =D47 -> #REF! | E85: =+C85-D85 -> #REF! | F85: =+E85/D85 -> #REF! | H85: As Conc. | I85: ppm | J85: =C85 -> 1062.708 | K85: =K47 -> #REF! | L85: =+J85-K85 -> #REF! | M85: =+L85/K85 -> #REF! | O85: As Conc. | P85: ppm | Q85: =Q47 -> 978.90256 | R85: =D85 -> #REF! | S85: =+R85-Q85 -> #REF! | T85: =+S85/R85 -> #REF! | V85: As Conc. | W85: ppm | X85: =Q85 -> 978.90256 | Y85: =K85 -> #REF! | Z85: =+Y85-X85 -> #REF! | AA85: =+Z85/Y85 -> #REF! | AF85: =+AE79*0.9644 -> 12512.466 | AJ85: DELTA INVENTARIO MES | AL85: REAL | AM85: S.T.
AE86: =+AF85-AE81 -> -85.997504 | AF86: En planta como inventario, no pagables en puerto | AJ86: Cu Fino Producido | AL86: =+'R+RP+B'!M10*1000 -> 35774.53 | AM86: =+'ST Original'!V37 -> 26747.419
AC87: =AE68*AE73*AE75/10000 -> 12.974353 | AD87: =AE68*AF73*AE75/10000 -> 13.519555 | AJ87: Cu Fino Filtrado | AL87: =+#REF!/0.966 -> #REF! | AM87: =+#REF!/0.966 -> #REF!
A88: COMPARACION REAL y SHORT TERM ORIGINAL VS BUDGET | H88: COMPARACION REAL y SHORT TERM ORIGINAL VS FORECAST | O88: COMPARACION REAL y PROYECCION VS BUDGET | V88: COMPARACION REAL y PROYECCION VS FORECAST | AD88: =AE68*AE73*AF75/10000 -> 12.928666 | AJ88: Delta Inventario Cu | AL88: =+AL87-AL86 -> #REF! | AM88: =+AM87-AM86 -> #REF! | AN88: =+AL88-AM88 -> #REF!
A89: ACUMULADO HASTA | B89: =C2 -> #REF! | E89: VARIACION | H89: ACUMULADO HASTA | I89: =C2 -> #REF! | L89: VARIACION | O89: ACUMULADO HASTA | P89: Ene | S89: VARIACION | V89: ACUMULADO HASTA | W89: =C2 -> #REF! | Z89: VARIACION | AD89: =AF68*AE73*AE75/10000 -> 13.039971 | AJ89: CASCADA FIN DE MES CUFFP ST, DATOS BM
B90: UNIDAD | C90: R+S.T. | D90: B | E90: Q | F90: % | I90: UNIDAD | J90: R+S.T. | K90: F | L90: Q | M90: % | P90: UNIDAD | Q90: R+P | R90: B | S90: Q | T90: % | W90: UNIDAD | X90: R+P | Y90: F | Z90: Q | AA90: %
A91: Cu Fino Eq. Producido | B91: Kton | C91: ='R+RS+B'!U13 -> 76.146069 | D91: =D94+D98/Factores!F9 -> 69.454455 | E91: =+C91-D91 -> 6.6916144 | F91: =+E91/D91 -> 0.096345358 | H91: Cu Fino Eq. Producido | I91: Kton | J91: =C91 -> 76.146069 | K91: ='BDGT ORI'!U13 -> 0 | L91: =+J91-K91 -> 76.146069 | M91: =+L91/K91 -> #DIV/0! | O91: Cu Fino Eq. Producido | P91: Kton | Q91: ='R+RP+B'!U8 -> 75.921116 | R91: =D91 -> 69.454455 | S91: =+Q91-R91 -> 6.4666614 | T91: =+S91/R91 -> 0.093106502 | U91: l | V91: Cu Fino Eq. Producido | W91: Kton | X91: =Q91 -> 75.921116 | Y91: =K91 -> 0 | Z91: =+X91-Y91 -> 75.921116 | AA91: =+Z91/Y91 -> #DIV/0!
A92: Cu Fino Eq. Filtrado (Ppto) | B92: Kton | C92: ='R+RS+B'!U14 -> 73.706321 | D92: =D95+D99*Factores!D9 -> 78.402771 | E92: =+C92-D92 -> -4.6964505 | F92: =+E92/D92 -> -0.059901588 | H92: Cu Fino Eq. Filtrado (Ppto) | I92: Kton | J92: =C92 -> 73.706321 | K92: =K95+K99*Factores!D9 -> 80.712015 | L92: =+J92-K92 -> -7.0056941 | M92: =+L92/K92 -> -0.086798653 | O92: Cu Fino Eq. Filtrado (Bdgt) | P92: Kton | Q92: ='R+RP+B'!U9 -> 72.376956 | R92: =D92 -> 78.402771 | S92: =+Q92-R92 -> -6.025815 | T92: =+S92/R92 -> -0.076857168 | U92: l | V92: Cu Fino Eq. Filtrado (Bdgt) | W92: Kton | X92: =Q92 -> 72.376956 | Y92: =K92 -> 80.712015 | Z92: =+X92-Y92 -> -8.3350586 | AA92: =+Z92/Y92 -> -0.10326912 | AE92: Rendimiento | AF92: CM % | AG92: Ley Cu | AH92: Rec Cu | AI92: CuFFP-CuFP | AJ92: TMF | AK92: DIF
A93: Cu Fino Eq. Filtrado (Real) | B93: Kton | C93: =C96+C100*Factores!$F$9 -> 73.706321 | D93: =D96+D100*Factores!$F$9 -> 78.402771 | E93: =+C93-D93 -> -4.6964505 | F93: =+E93/D93 -> -0.059901588 | H93: Cu Fino Eq. Filtrado (Real) | I93: Kton | J93: =J96+J100*Factores!$F$9 -> 73.706321 | K93: =K96+K100*Factores!$F$9 -> 80.712015 | L93: =+J93-K93 -> -7.0056941 | M93: =+L93/K93 -> -0.086798653 | O93: Cu Fino Eq. Filtrado (Real) | P93: Kton | Q93: =Q96+Q100*Factores!$F$9 -> 72.469946 | R93: =R96+R100*Factores!$F$9 -> 78.402771 | S93: =+Q93-R93 -> -5.9328248 | T93: =+S93/R93 -> -0.075671111 | V93: Cu Fino Eq. Filtrado (Real) | W93: Kton | X93: =X96+X100*Factores!$F$9 -> 72.469946 | Y93: =Y96+Y100*Factores!$F$9 -> 80.712015 | Z93: =+X93-Y93 -> -8.2420685 | AA93: =+Z93/Y93 -> -0.102117 | AC93: PM | AE93: =AF70 -> 8414.2412 | AF93: =AF69 -> 88.216548 | AG93: =AF73 -> 0.51107742 | AH93: =AF75 -> 90.302073 | AI93: =AF81-AF79 -> -1425.847 | AJ93: =AE93*$AC$62*24*AF93/100*AG93/100*AH93/100+AI93 -> 12139.928 | AK93: =AJ93 -> 12139.928
A94: Cu Fino Producido | B94: Kton | C94: ='R+RS+B'!U15 -> 69.638429 | D94: =BDGT!T8 -> 68.589013 | E94: =+C94-D94 -> 1.0494163 | F94: =+E94/D94 -> 0.015300064 | H94: Cu Fino Producido | I94: Kton | J94: =C94 -> 69.638429 | K94: ='BDGT ORI'!U15 -> 75.347786 | L94: =+J94-K94 -> -5.7093573 | M94: =+L94/K94 -> -0.075773391 | O94: Cu Fino Producido | P94: Kton | Q94: ='R+RP+B'!U10 -> 69.247827 | R94: =D94 -> 68.589013 | S94: =+Q94-R94 -> 0.65881391 | T94: =+S94/R94 -> 0.0096052397 | U94: l | V94: Cu Fino Producido | W94: Kton | X94: =Q94 -> 69.247827 | Y94: =K94 -> 75.347786 | Z94: =+X94-Y94 -> -6.0999597 | AA94: =+Z94/Y94 -> -0.080957384 | AC94: Rendimiento | AE94: =AE70 -> 8365.4531 | AF94: =AF93 -> 88.216548 | AG94: =AG93 -> 0.51107742 | AH94: =AH93 -> 90.302073 | AI94: =AI93 -> -1425.847 | AJ94: =AE94*$AC$62*24*AF94/100*AG94/100*AH94/100+AI94 -> 12061.27 | AK94: =AJ94-AJ93 -> -78.65806
A95: Cu Fino Filtrado Pagable (Ppto) | B95: Kton | C95: ='R+RS+B'!U16 -> 67.36094 | D95: =BDGT!T7 -> 71.201972 | E95: =+C95-D95 -> -3.8410314 | F95: =+E95/D95 -> -0.053945576 | H95: Cu Fino Filtrado Pagable (Ppto) | I95: Kton | J95: =C95 -> 67.36094 | K95: =+'BDGT ORI'!U16 -> 72.785961 | L95: =+J95-K95 -> -5.425021 | M95: =+L95/K95 -> -0.074533893 | O95: Cu Fino Filtrado Pagable (Bdgt) | P95: Kton | Q95: ='R+RP+B'!U11 -> 66.124566 | R95: =D95 -> 71.201972 | S95: =+Q95-R95 -> -5.0774058 | T95: =+S95/R95 -> -0.071309904 | U95: l | V95: Cu Fino Filtrado Pagable (Bdgt) | W95: Kton | X95: =Q95 -> 66.124566 | Y95: =K95 -> 72.785961 | Z95: =+X95-Y95 -> -6.6613954 | AA95: =+Z95/Y95 -> -0.091520333 | AC95: CM % | AE95: =AE94 -> 8365.4531 | AF95: =AE69 -> 88.117328 | AG95: =AG93 -> 0.51107742 | AH95: =AH93 -> 90.302073 | AI95: =AI93 -> -1425.847 | AJ95: =AE95*$AC$62*24*AF95/100*AG95/100*AH95/100+AI95 -> 12046.101 | AK95: =AJ95-AJ94 -> -15.169515 | AL95: =SUM(AK94:AK95) -> -93.827574
A96: Cu Fino Filtrado Pagable (Real) | B96: Kton | C96: =C95/Factores!$D$7*Factores!$F$7 -> 67.36094 | D96: =D95/Factores!$D$7*Factores!$F$7 -> 71.201972 | E96: =+C96-D96 -> -3.8410314 | F96: =+E96/D96 -> -0.053945576 | H96: Cu Fino Filtrado Pagable (Real) | I96: Kton | J96: =J95/Factores!$D$7*Factores!$F$7 -> 67.36094 | K96: =K95/Factores!$D$7*Factores!$F$7 -> 72.785961 | L96: =+J96-K96 -> -5.425021 | M96: =+L96/K96 -> -0.074533893 | O96: Cu Fino Filtrado Pagable (Real) | P96: Kton | Q96: =Q95/Factores!$D$7*Factores!$F$7 -> 66.124566 | R96: =R95/Factores!$D$7*Factores!$F$7 -> 71.201972 | S96: =+Q96-R96 -> -5.0774058 | T96: =+S96/R96 -> -0.071309904 | V96: Cu Fino Filtrado Pagable (Real) | W96: Kton | X96: =X95/Factores!$D$7*Factores!$F$7 -> 66.124566 | Y96: =Y95/Factores!$D$7*Factores!$F$7 -> 72.785961 | Z96: =+X96-Y96 -> -6.6613954 | AA96: =+Z96/Y96 -> -0.091520333 | AC96: Ley Cu,% | AE96: =AE94 -> 8365.4531 | AF96: =AF95 -> 88.117328 | AG96: =AE73 -> 0.49046726 | AH96: =AH93 -> 90.302073 | AI96: =AI93 -> -1425.847 | AJ96: =AE96*$AC$62*24*AF96/100*AG96/100*AH96/100+AI96 -> 11502.819 | AK96: =AJ96-AJ95 -> -543.28151
A97: Delta Inventario Cu Fino | B97: Kton | C97: ='R+RS+B'!S62 -> -0.38333868 | H97: Delta Inventario Cu Fino | I97: Kton | J97: =C97 -> -0.38333868 | O97: Delta Inventario Cu Fino | P97: Kton | Q97: ='R+RP+B'!S59 -> 11.964239 | V97: Delta Inventario Cu Fino | W97: Kton | X97: =Q97 -> 11.964239 | AC97: RCu, % | AE97: =AE94 -> 8365.4531 | AF97: =AF95 -> 88.117328 | AG97: =AG96 -> 0.49046726 | AH97: =AE75 -> 90.621182 | AI97: =AI96 -> -1425.847 | AJ97: =AE97*$AC$62*24*AF97/100*AG97/100*AH97/100+AI97 -> 11548.506 | AK97: =AJ97-AJ96 -> 45.687144
A98: Mo Fino Producido | B98: Kton | C98: ='R+RS+B'!U17 -> 2.244788 | D98: =BDGT!T9 -> 2.5089172 | E98: =+C98-D98 -> -0.26412925 | F98: =+E98/D98 -> -0.10527619 | H98: Mo Fino Producido | I98: Kton | J98: =C98 -> 2.244788 | K98: ='BDGT ORI'!U17 -> 2.7478037 | L98: =+J98-K98 -> -0.50301569 | M98: =+L98/K98 -> -0.183061 | O98: Mo Fino Producido | P98: Kton | Q98: ='R+RP+B'!U12 -> 2.3019282 | R98: =D98 -> 2.5089172 | S98: =+Q98-R98 -> -0.20698906 | T98: =+S98/R98 -> -0.082501351 | U98: l | V98: Mo Fino Producido | W98: Kton | X98: =Q98 -> 2.3019282 | Y98: =K98 -> 2.7478037 | Z98: =+X98-Y98 -> -0.44587549 | AA98: =+Z98/Y98 -> -0.16226614 | AC98: Inventarios | AE98: =AE97 -> 8365.4531 | AF98: =AF96 -> 88.117328 | AG98: =AG96 -> 0.49046726 | AH98: =AH97 -> 90.621182 | AI98: =AE81-AE79 -> -375.88947 | AJ98: =AE98*$AC$62*24*AF98/100*AG98/100*AH98/100+AI98 -> 12598.464 | AK98: =AJ98-AJ97 -> 1049.9575
A99: Mo Fino Envasado Pagable (Ppto) | B99: Kton | C99: ='R+RS+B'!U18 -> 2.1888169 | D99: =BDGT!T10*Factores!$D$8 -> 2.4838908 | E99: =+C99-D99 -> -0.29507384 | F99: =+E99/D99 -> -0.11879501 | H99: Mo Fino Envasado Pagable (Ppto) | I99: Kton | J99: =C99 -> 2.1888169 | K99: ='BDGT ORI'!U18 -> 2.7340646 | L99: =+J99-K99 -> -0.5452477 | M99: =+L99/K99 -> -0.19942751 | O99: Mo Fino Envasado Pagable (Bdgt) | P99: Kton | Q99: ='R+RP+B'!U13 -> 2.1888169 | R99: =D99 -> 2.4838908 | S99: =+Q99-R99 -> -0.29507384 | T99: =+S99/R99 -> -0.11879501 | U99: l | V99: Mo Fino Envasado Pagable (Bdgt) | W99: Kton | X99: =Q99 -> 2.1888169 | Y99: =K99 -> 2.7340646 | Z99: =+X99-Y99 -> -0.5452477 | AA99: =+Z99/Y99 -> -0.19942751 | AC99: R+P | AE99: =AE98 -> 8365.4531 | AF99: =AF98 -> 88.117328 | AG99: =AG98 -> 0.49046726 | AH99: =AH98 -> 90.621182 | AI99: =AI98 -> -375.88947 | AJ99: =AE99*$AC$62*24*AF99/100*AG99/100*AH99/100+AI99 -> 12598.464 | AK99: =AJ98 -> 12598.464 | AL99: =SUM(AK94:AK98) -> 458.53554
A100: Mo Fino Envasado Pagable (Real) | B100: Kton | C100: =C99/Factores!$D$8*Factores!$F$8 -> 2.1888169 | D100: =D99/Factores!$D$8*Factores!$F$8 -> 2.4838908 | E100: =+C100-D100 -> -0.29507384 | F100: =+E100/D100 -> -0.11879501 | H100: Mo Fino Envasado Pagable (Real) | I100: Kton | J100: =J99/Factores!$D$8*Factores!$F$8 -> 2.1888169 | K100: =K99/Factores!$D$8*Factores!$F$8 -> 2.7340646 | L100: =+J100-K100 -> -0.5452477 | M100: =+L100/K100 -> -0.19942751 | O100: Mo Fino Envasado Pagable (Real) | P100: Kton | Q100: =Q99/Factores!$D$8*Factores!$F$8 -> 2.1888169 | R100: =R99/Factores!$D$8*Factores!$F$8 -> 2.4838908 | S100: =+Q100-R100 -> -0.29507384 | T100: =+S100/R100 -> -0.11879501 | V100: Mo Fino Envasado Pagable (Real) | W100: Kton | X100: =X99/Factores!$D$8*Factores!$F$8 -> 2.1888169 | Y100: =Y99/Factores!$D$8*Factores!$F$8 -> 2.7340646 | Z100: =+X100-Y100 -> -0.5452477 | AA100: =+Z100/Y100 -> -0.19942751
A101: Delta Inventario Mo Fino | B101: Kton | C101: ='R+RS+B'!S65 -> 0.08304853 | H101: Delta Inventario Mo Fino | I101: Kton | J101: =C101 -> 0.08304853 | O101: Delta Inventario Mo Fino | P101: Kton | Q101: ='R+RP+B'!S62 -> 0.14018872 | S101: =+Q101-R101 -> 0.14018872 | V101: Delta Inventario Mo Fino | W101: Kton | X101: =Q101 -> 0.14018872
A103: Extracción | B103: Kton | C103: ='R+RS+B'!U11 -> #REF! | D103: =BDGT!#REF! -> #REF! | E103: =+C103-D103 -> #REF! | F103: =+E103/D103 -> #REF! | H103: Extracción | I103: Kton | J103: =C103 -> #REF! | K103: ='BDGT ORI'!U11 -> 0 | L103: =+J103-K103 -> #REF! | M103: =+L103/K103 -> #REF! | O103: Extracción | P103: Kton | Q103: ='R+RP+B'!#REF! -> #REF! | R103: =D103 -> #REF! | S103: =+Q103-R103 -> #REF! | T103: =+S103/R103 -> #REF! | U103: l | V103: Extracción | W103: Kton | X103: =Q103 -> #REF! | Y103: =K103 -> 0 | Z103: =+X103-Y103 -> #REF! | AA103: =+Z103/Y103 -> #REF!
A104: Tonelaje Procesado | B104: Kton | C104: ='R+RS+B'!U20 -> 14937.268 | D104: =BDGT!T24 -> 0 | E104: =+C104-D104 -> 14937.268 | F104: =+E104/D104 -> #DIV/0! | H104: Tonelaje Procesado | I104: Kton | J104: =C104 -> 14937.268 | K104: ='BDGT ORI'!U20 -> 15946.36 | L104: =+J104-K104 -> -1009.092 | M104: =+L104/K104 -> -0.063280395 | O104: Tonelaje Procesado | P104: Kton | Q104: ='R+RP+B'!U15 -> 14929.684 | R104: =D104 -> 0 | S104: =+Q104-R104 -> 14929.684 | T104: =+S104/R104 -> #DIV/0! | U104: l | V104: Tonelaje Procesado | W104: Kton | X104: =Q104 -> 14929.684 | Y104: =K104 -> 15946.36 | Z104: =+X104-Y104 -> -1016.6764 | AA104: =+Z104/Y104 -> -0.063756017
A105: Toneladas por día | B105: Ktpd | C105: ='R+RS+B'!U21 -> 165.96965 | D105: =BDGT!T13 -> 168.77709 | E105: =+C105-D105 -> -2.8074451 | F105: =+E105/D105 -> -0.016634041 | H105: Toneladas por día | I105: Ktpd | J105: =C105 -> 165.96965 | K105: ='BDGT ORI'!U21 -> 175.23473 | L105: =+J105-K105 -> -9.2650806 | M105: =+L105/K105 -> -0.0528724 | O105: Toneladas por día | P105: Ktpd | Q105: ='R+RP+B'!U16 -> 165.88538 | R105: =D105 -> 168.77709 | S105: =+Q105-R105 -> -2.8917166 | T105: =+S105/R105 -> -0.017133348 | U105: l | V105: Toneladas por día | W105: Ktpd | X105: =Q105 -> 165.88538 | Y105: =K105 -> 175.23473 | Z105: =+X105-Y105 -> -9.349352 | AA105: =+Z105/Y105 -> -0.053353306
A106: Rendimiento | B106: Tph | C106: ='R+RS+B'!U22 -> 8420.9426 | D106: =BDGT!T14 -> 8151.9777 | E106: =+C106-D106 -> 268.96486 | F106: =+E106/D106 -> 0.032993816 | H106: Rendimiento | I106: Tph | J106: =C106 -> 8420.9426 | K106: ='BDGT ORI'!U22 -> 8685.5195 | L106: =+J106-K106 -> -264.57694 | M106: =+L106/K106 -> -0.030461843 | O106: Rendimiento | P106: Tph | Q106: ='R+RP+B'!U17 -> 8426.8957 | R106: =D106 -> 8151.9777 | S106: =+Q106-R106 -> 274.91798 | T106: =+S106/R106 -> 0.033724083 | U106: l | V106: Rendimiento | W106: Tph | X106: =Q106 -> 8426.8957 | Y106: =K106 -> 8685.5195 | Z106: =+X106-Y106 -> -258.62381 | AA106: =+Z106/Y106 -> -0.029776436
...

Sheet Acumulados
B1: 1000 | T1: 1000 | AY1: Inv. Final: | AZ1: 2968 | BA1: Tmf
D2: 30.5 | E2: 28 | F2: 31 | G2: 30 | H2: 31 | I2: 30 | J2: 31 | K2: 31 | L2: 30 | M2: 31 | N2: 31 | O2: 30 | P2: 31.5 | Q2: =SUM(D2:M2) -> 303.5 | R2: =+SUM(D2:P2) -> 396 | T2: 31 | U2: 28 | V2: 31 | W2: 30 | X2: 31 | Y2: 30 | Z2: 31 | AA2: 31 | AB2: 30 | AC2: 31 | AD2: 30 | AE2: 31 | AF2: =SUM(T2:AC4) -> 304 | AG2: =SUM(T2:AE4) -> 365
D3: =(D7-D8/0.9644)*1000 -> 431.13712 | E3: =(E7-E8/0.9644)*1000 -> 426.92697 | F3: =(F7-F8/0.9644)*1000 -> -281.44259 | G3: =(G7-G8/0.9644)*1000 -> 270.63574 | H3: =(H7-H8/0.9644)*1000 -> -588.20834 | I3: =(I7-I8/0.9644)*1000 -> 66.597659 | Q3: =(Q7-Q8/0.9644)*1000 -> 325.64656 | R3: =(R7-R8/0.9644)*1000 -> 792.21365 | T3: =(T7-T8/0.966)*1000 -> 2.8158809e-08 | U3: =(U7-U8/0.966)*1000 -> -1.6353141e-08 | V3: =(V7-V8/0.966)*1000 -> 1.5941026e-08 | W3: =(W7-W8/0.966)*1000 -> -3.932854e-09 | X3: =(X7-X8/0.966)*1000 -> -1.8015811e-08 | Y3: =(Y7-Y8/0.966)*1000 -> 4.3485215e-09 | AF3: =(AF7-AF8/0.966)*1000 -> 1.014655e-08 | AG3: =(AG7-AG8/0.966)*1000 -> 7.9296569e-08 | AQ3: ENERO | AS3: Rendimiento | AT3: CM % | AU3: Ley Cu | AV3: Rec Cu | AW3: CuFFP-CuFP | AX3: TMF | AY3: DIF
D4: =(D7*0.9644-D8)*1000 -> 415.78863 | E4: =(E7*0.9644-E8)*1000 -> 411.72837 | F4: =(F7*0.9644-F8)*1000 -> -271.42323 | G4: =(G7*0.9644-G8)*1000 -> 261.00111 | H4: =(H7*0.9644-H8)*1000 -> -567.26812 | I4: =(I7*0.9644-I8)*1000 -> 64.226783 | Q4: =(Q7*0.9644-Q8)*1000 -> 314.05354 | R4: =(R7*0.9644-R8)*1000 -> 764.01085 | T4: =(T7*0.966-T8)*1000 -> 2.7203129e-08 | U4: =(U7*0.966-U8)*1000 -> -1.5798918e-08 | V4: =(V7*0.966-V8)*1000 -> 1.5397461e-08 | W4: =(W7*0.966-W8)*1000 -> -3.7978509e-09 | X4: =(X7*0.966-X8)*1000 -> -1.7401192e-08 | Y4: =(Y7*0.966-Y8)*1000 -> 4.2028603e-09 | AF4: =(AF7*0.966-AF8)*1000 -> 9.8054898e-09 | AG4: =(AG7*0.966-AG8)*1000 -> 7.6624929e-08 | AQ4: BDGT Ajustado | AS4: =T14 -> 8278.1672 | AT4: =T18 -> 91.052835 | AU4: =T20 -> 0.47560795 | AV4: =T21 -> 89.520023 | AW4: =(T8-T7)*1000 -> -811.79957 | AX4: =AS4*AT4*24*30.5/100*AU4/100*AV4/100+AW4 -> 22679.554 | AY4: =AX4 -> 22679.554
D5: REAL | E5: REAL | F5: REAL | G5: REAL | H5: REAL | I5: REAL | J5: R+P | K5: R+P | M5: PM | Q5: Real | R5: R+P | T5: BD | U5: BD | V5: BD | W5: BD | X5: BD | Y5: BD | Z5: BD | AA5: R+P | AC5: PM | AI5: REAL | AL5: R+P
C6: Unidad | D6: BM Ene | E6: BM Feb | F6: BM Mar | G6: BM Abr | H6: BM May | I6: BM Jun | J6: BM Jul | K6: BM Ago | L6: BM Sep | M6: BM Sep | N6: BM Oct | O6: BM Nov | P6: R+P Dic | Q6: Acum. H1 | R6: Acum a Dic | T6: BD Ene | U6: BD Feb | V6: BD Mar | W6: BD Abr | X6: BD May | Y6: BD Jun | Z6: BD Jul | AA6: BD Ago | AB6: BD Sept | AC6: BD Oct | AD6: BD Nov | AE6: BD Dic | AF6: BD H1 | AG6: BD a Dic | AI6: DIF H1 | AJ6: % | AL6: DIF a Dic | AM6: % | AQ6: Rendimiento | AS6: =+$D$14 -> 8148.8879 | AT6: =AT4 -> 91.052835 | AU6: =AU4 -> 0.47560795 | AV6: =AV4 -> 89.520023 | AW6: =AW4 -> -811.79957 | AX6: =AS6*AT6*24*30.5/100*AU6/100*AV6/100+AW6 -> 22312.692 | AY6: =AX6-AX4 -> -366.86227
B7: Cu Fino Producido | C7: Kton | D7: 23.95399 | E7: 22.519131 | F7: 26.579021 | G7: 24.938046 | H7: 24.998531 | I7: 25.805466 | J7: 25.099591 | K7: 26.794658 | L7: 24.981376 | M7: 27.084518 | Q7: =SUM(D7:I7) -> 148.79418 | R7: =+SUM(D7:N7) -> 252.75433 | T7: 23.876458 | U7: 22.751614 | V7: 26.459281 | W7: 26.49665 | X7: 30.074574 | Y7: 29.481818 | Z7: 23.330845 | AA7: 25.162032 | AB7: 28.714162 | AC7: 29.087249 | AD7: 30.090002 | AF7: =SUM(T7:Y7) -> 159.14039 | AG7: =+SUM(T7:AE7) -> 295.52468 | AI7: =Q7-AF7 -> -10.34621 | AJ7: =AI7/AF7 -> -0.065013099 | AL7: =R7-AG7 -> -42.770356 | AM7: =AL7/AG7 -> -0.14472685 | AQ7: CM % | AS7: =AS6 -> 8148.8879 | AT7: =+$D$18 -> 88.463115 | AU7: =AU4 -> 0.47560795 | AV7: =AV4 -> 89.520023 | AW7: =AW4 -> -811.79957 | AX7: =AS7*AT7*24*30.5/100*AU7/100*AV7/100+AW7 -> 21654.986 | AY7: =AX7-AX6 -> -657.70573
B8: Cu Fino Filtrado Pagable | C8: Kton | D8: 22.685439 | E8: 21.305722 | F8: 25.904231 | G8: 23.789251 | H8: 24.675851 | I8: 24.822565 | J8: 24.240236 | K8: 22.126648 | L8: 26.613589 | M8: 26.828731 | Q8: =SUM(D8:I8) -> 143.18306 | R8: =+SUM(D8:N8) -> 242.99226 | T8: 23.064658 | U8: 21.978059 | V8: 25.559665 | W8: 25.595764 | X8: 29.052039 | Y8: 28.479436 | Z8: 22.537596 | AA8: 24.306523 | AB8: 27.73788 | AC8: 28.098282 | AD8: 29.066942 | AF8: =SUM(T8:Y8) -> 153.72962 | AG8: =+SUM(T8:AE8) -> 285.47684 | AI8: =Q8-AF8 -> -10.546563 | AJ8: =AI8/AF8 -> -0.068604627 | AL8: =R8-AG8 -> -42.484582 | AM8: =AL8/AG8 -> -0.14881971 | AO8: =G8-W8 -> -1.8065135 | AQ8: Ley Cu,% | AS8: =AS6 -> 8148.8879 | AT8: =AT7 -> 88.463115 | AU8: =+$D$20 -> 0.5130814 | AV8: =AV4 -> 89.520023 | AW8: =AW4 -> -811.79957 | AX8: =AS8*AT8*24*30.5/100*AU8/100*AV8/100+AW8 -> 23425.158 | AY8: =AX8-AX7 -> 1770.1721
B9: Mo Fino Producido | C9: Kton | D9: 0.6877459 | E9: 0.7682988 | F9: 0.7919837 | G9: 0.9899452 | H9: 1.2376732 | I9: 1.191114 | J9: 0.8455234 | K9: 1.0873835 | L9: 1.1182268 | M9: 1.3382371 | Q9: =SUM(D9:I9) -> 5.6667608 | R9: =+SUM(D9:N9) -> 10.056132 | T9: 0.8398606 | U9: 0.9127278 | V9: 0.9952153 | W9: 1.1689092 | X9: 1.1986114 | Y9: 1.2198837 | Z9: 0.824863 | AA9: 1.0567662 | AB9: 1.3598521 | AC9: 1.0812537 | AD9: 1.283036 | AF9: =SUM(T9:Y9) -> 6.335208 | AG9: =+SUM(T9:AE9) -> 11.940979 | AI9: =Q9-AF9 -> -0.6684472 | AJ9: =AI9/AF9 -> -0.10551306 | AL9: =R9-AG9 -> -1.8848474 | AM9: =AL9/AG9 -> -0.15784697 | AQ9: RCu, % | AS9: =AS6 -> 8148.8879 | AT9: =AT7 -> 88.463115 | AU9: =AU8 -> 0.5130814 | AV9: =+$D$21 -> 88.474775 | AW9: =AW4 -> -811.79957 | AX9: =AS9*AT9*24*30.5/100*AU9/100*AV9/100+AW9 -> 23142.164 | AY9: =AX9-AX8 -> -282.99418
B10: Mo Fino Envasado Pagable | C10: Kton | D10: 0.5593703 | E10: 0.7106961 | F10: 0.9812003 | G10: 1.0258433 | H10: 1.2090692 | I10: 1.2382653 | J10: 0.9370735 | K10: 0.9557617 | L10: 1.1409695 | M10: 1.1591302 | Q10: =SUM(D10:I10) -> 5.7244445 | R10: =+SUM(D10:N10) -> 9.9173794 | T10: 0.8356613 | U10: 0.9081641 | V10: 0.9902392 | W10: 1.1630647 | X10: 1.1926184 | Y10: 1.2137843 | Z10: 0.8207387 | AA10: 1.0514823 | AB10: 1.3530528 | AC10: 1.0758475 | AD10: 1.2766208 | AF10: =SUM(T10:Y10) -> 6.303532 | AG10: =+SUM(T10:AE10) -> 11.881274 | AI10: =Q10-AF10 -> -0.5790875 | AJ10: =AI10/AF10 -> -0.091867147 | AL10: =R10-AG10 -> -1.9638947 | AM10: =AL10/AG10 -> -0.16529328 | AQ10: Inventarios | AS10: =AS6 -> 8148.8879 | AT10: =AT7 -> 88.463115 | AU10: =AU8 -> 0.5130814 | AV10: =AV9 -> 88.474775 | AW10: =+($D$8-$D$7)*1000 -> -1268.5507 | AX10: =AS10*AT10*24*30.5/100*AU10/100*AV10/100+AW10 -> 22685.413 | AY10: =AX10-AX9 -> -456.7511
AQ11: Real | AS11: =AS6 -> 8148.8879 | AT11: =AT7 -> 88.463115 | AU11: =AU8 -> 0.5130814 | AV11: =AV9 -> 88.474775 | AW11: =AW10 -> -1268.5507 | AY11: =+SUM(AY4:AY10) -> 22685.413 | AZ11: =AY11-AY4 -> 5.8588405
B12: Tonelaje Procesado | C12: Kton | D12: 5276.8123 | E12: 4993.564 | F12: 5347.4708 | G12: 4979.3775 | H12: 5484.1979 | I12: 5118.1204 | J12: 4931.705 | K12: 5062.2333 | L12: 5101.3371 | M12: 5607.0996 | Q12: =SUM(D12:I12) -> 31199.543 | R12: =+SUM(D12:N12) -> 51901.918 | T12: 5607.9044 | U12: 5222.8705 | V12: 5115.5852 | W12: 5879.0851 | X12: 6219.2205 | Y12: 6022.8239 | Z12: 5113.1375 | AA12: 5314.0765 | AB12: 5878.2009 | AC12: 6213.1358 | AD12: 5781.6331 | AF12: =SUM(T12:Y12) -> 34067.49 | AG12: =+SUM(T12:AE12) -> 62367.674 | AI12: =Q12-AF12 -> -2867.9469 | AJ12: =AI12/AF12 -> -0.084184274 | AL12: =R12-AG12 -> -10465.756 | AM12: =AL12/AG12 -> -0.16780738 | AO12: =AP12-V12 -> 726.88744 | AP12: 5842.4727
B13: Toneladas por día | C13: Ktpd | D13: 170.21975 | E13: 178.34157 | F13: 172.49906 | G13: 165.97925 | H13: 176.90961 | I13: 170.60401 | J13: 159.08726 | K13: 163.29785 | L13: 169.48333 | M13: 180.87418 | Q13: =Q12/Q2 -> 102.79915 | R13: =R12/R2 -> 131.06545 | T13: 180.90014 | U13: 186.53109 | V13: 165.01888 | W13: 195.9695 | X13: 200.62002 | Y13: 200.7608 | Z13: 164.93992 | AA13: 171.42182 | AB13: 195.94003 | AC13: 200.42374 | AF13: =AF12/AF2 -> 112.06411 | AG13: =AG12/AG2 -> 170.87034 | AI13: =Q13-AF13 -> -9.2649583 | AJ13: =AI13/AF13 -> -0.082675517 | AL13: =R13-AG13 -> -39.804889 | AM13: =AL13/AG13 -> -0.23295377
B14: Rendimiento Global | C14: Tph | D14: 8148.8879 | E14: 8332.3276 | F14: 7997.1747 | G14: 8365.8896 | H14: 8204.964 | I14: 8016.3524 | J14: 8528.3777 | K14: 8383.8182 | L14: 7630.7967 | M14: 8036.6071 | Q14: =Q12*1000/(AF2*24*Q18/100) -> 8114.535 | R14: =R12*1000/(R2*24*R18/100) -> 8121.1153 | T14: 8278.1672 | U14: 8684.4809 | V14: 8745.2728 | W14: 8512.0482 | X14: 8702.6606 | Y14: 8750.6559 | Z14: 8432.7098 | AA14: 9072.7109 | AB14: 8628.0742 | AC14: 8684.6607 | AD14: 8236.0167 | AF14: =AF12*1000/(AF2*24*AF18/100) -> 8608.6106 | AG14: =AG12*1000/(R2*24*AG18/100) -> 9543.3215 | AI14: =Q14-AF14 -> -494.07564 | AJ14: =AI14/AF14 -> -0.057393191 | AL14: =R14-AG14 -> -1422.2062 | AM14: =AL14/AG14 -> -0.14902633
B15: AxB | C15: - | D15: 37.515527 | E15: 38.069277 | F15: 38.252026 | G15: 37.687322 | H15: 37.421213 | I15: 37.398726 | J15: 37.600247 | K15: 38.806704 | L15: 36.448042 | M15: 37.569619 | Q15: =SUMPRODUCT(D12:I12,D15:I15)/Q$12 -> 37.722068 | R15: =SUMPRODUCT($D$12:$M$12,D15:M15)/$R$12 -> 37.674591 | T15: 37.25541 | U15: 35.921331 | V15: 36.784395 | W15: 35.513843 | X15: 36.439688 | Y15: 35.694447 | Z15: 36.664253 | AA15: 36.916859 | AB15: 35.950088 | AC15: 37.69751 | AF15: =SUMPRODUCT(T12:Y12,T15:Y15)/AF$12 -> 36.254731 | AG15: =SUMPRODUCT($T$12:$AD$12,T15:AD15)/$AG$12 -> 33.09884 | AI15: =Q15-AF15 -> 1.4673369 | AJ15: =AI15/AF15 -> 0.040472977 | AL15: =R15-AG15 -> 4.5757513 | AM15: =AL15/AG15 -> 0.13824506 | AY15: Inv. Final: | AZ15: 3375.9215 | BA15: Tmf
B16: RQD | C16: - | D16: 78.042419 | E16: 80.745704 | F16: 81.84674 | G16: ='[18]TP sin BM'!F14 -> 85.465536 | H16: 85.465536 | I16: ='TP sin BM'!G14 -> 82.923534 | J16: 81.726664 | K16: 84.998951 | L16: 4.1336908 | M16: ='PM vs OL y BD'!D14 -> 82.923534 | Q16: =SUMPRODUCT(D$12:H$12,D16:H16)/Q$12 -> 68.814219 | R16: =SUMPRODUCT($D$12:$I$12,D16:I16)/$R$12 -> 49.543156 | T16: 80.669353 | U16: 86.227462 | V16: 86.384367 | W16: 89.675422 | X16: 89.877307 | Y16: 88.961175 | AF16: =SUMPRODUCT(T$12:X$12,T16:X16)/AF$12 -> 71.35318 | AG16: =SUMPRODUCT($D$12:$I$12,T16:Y16)/$R$12 -> 52.270592 | AI16: =Q16-AF16 -> -2.5389608 | AJ16: =AI16/AF16 -> -0.035583009 | AL16: =R16-AG16 -> -2.7274365 | AM16: =AL16/AG16 -> -0.052179177 | AQ16: FEBRERO | AS16: Rendimiento | AT16: CM % | AU16: Ley Cu | AV16: Rec Cu | AW16: CuFFP-CuFP | AX16: TMF | AY16: DIF
B17: F80 | C17: In | D17: 4.1622031 | E17: 4.25 | F17: 4.1451512 | G17: 4.21 | H17: 4.1 | I17: 4.27 | J17: 3.93 | K17: 4.04 | L17: 4.15 | M17: 4.1603619 | Q17: =SUMPRODUCT(D$12:I$12,D17:I17)/Q$12 -> 4.1877104 | R17: =SUMPRODUCT($D$12:$M$12,D17:M17)/$R$12 -> 4.142155 | T17: 4.0515644 | U17: 4.0481779 | V17: 4.0564913 | W17: 4.0004374 | X17: 4.029893 | Y17: 3.9363241 | Z17: 4.0151167 | AA17: 3.9721027 | AB17: 4.0573849 | AC17: 3.9664332 | AD17: 3.9527435 | AF17: =SUMPRODUCT(T$12:Y$12,T17:Y17)/AF$12 -> 4.0186323 | AG17: =SUMPRODUCT($T$12:$AD$12,T17:AD17)/$AG$12 -> 4.0067238 | AI17: =Q17-AF17 -> 0.16907814 | AJ17: =AI17/AF17 -> 0.042073553 | AL17: =R17-AG17 -> 0.13543119 | AM17: =AL17/AG17 -> 0.033800981 | AQ17: BDGT Ajustado | AS17: =U14 -> 8684.4809 | AT17: =U18 -> 89.494455 | AU17: =U20 -> 0.4844022 | AV17: =U21 -> 89.928394 | AW17: =(U8-U7)*1000 -> -773.55487 | AX17: =AS17*AT17*24*28/100*AU17/100*AV17/100+AW17 -> 21978.059 | AY17: =AX17 -> 21978.059
B18: CM Global | C18: % | D18: 88.463115 | E18: 93.369271 | F18: 89.875 | G18: 82.552011 | H18: 89.83871 | I18: 88.675 | J18: 77.724462 | K18: 81.157258 | L18: 92.543488 | M18: 93.776193 | Q18: =SUMPRODUCT(D2:I2,D18:I18)/AF2 -> 52.698684 | R18: =(D2*24*D18+E2*24*E18+F2*24*F18+G2*24*G18+H2*24*H18+I2*24*I18+J2*24*J18+K2*24*K18+M2*24*M18+L2*L18*24+N2*24*N18)/(R2*24) -> 67.245202 | T18: 91.052835 | U18: 89.494455 | V18: 78.622894 | W18: 95.927511 | X18: 96.053008 | Y18: 95.593214 | Z18: 81.49808 | AA18: 78.725928 | AB18: 94.623292 | AC18: 96.157919 | AD18: 97.499147 | AF18: =SUMPRODUCT(T2:Y2,T18:Y18)/AF2 -> 54.24032 | AG18: =(D2*24*T18+U2*24*U18+V2*24*V18+W2*24*W18+X2*24*X18+Y2*24*Y18+Z2*24*Z18+AA2*24*AA18+AC2*24*AC18+AB2*24*AB18)/(R2*24) -> 68.762802 | AI18: =Q18-AF18 -> -1.5416363 | AJ18: =AI18/AF18 -> -0.028422331 | AL18: =R18-AG18 -> -1.5175999 | AM18: =AL18/AG18 -> -0.022070071 | AO18: =AO12*F20*F21/10000*1000 -> 3615.0991 | AP18: =AO18*0.9644 -> 3486.4016 | AQ18: Rendimiento | AS18: =+$E$14 -> 8332.3276 | AT18: =AT17 -> 89.494455 | AU18: =AU17 -> 0.4844022 | AV18: =AV17 -> 89.928394 | AW18: =AW17 -> -773.55487 | AX18: =AS18*AT18*24*28/100*AU18/100*AV18/100+AW18 -> 21055.487 | AY18: =AX18-AX17 -> -922.57144
AO19: Aporte flujo cero | AQ19: CM % | AS19: =AS18 -> 8332.3276 | AT19: =+$E$18 -> 93.369271 | AU19: =AU17 -> 0.4844022 | AV19: =AV17 -> 89.928394 | AW19: =AW17 -> -773.55487 | AX19: =AS19*AT19*24*28/100*AU19/100*AV19/100+AW19 -> 22000.613 | AY19: =AX19-AX18 -> 945.12583
B20: Ley Alim. Cu | C20: % | D20: 0.5130814 | E20: 0.5236813 | F20: 0.5518866 | G20: 0.5593653 | H20: 0.5117386 | I20: 0.5527667 | J20: 0.5629039 | K20: 0.5796008 | L20: 0.5364302 | M20: 0.53164717 | Q20: =SUMPRODUCT(D$12:I$12,D20:I20)/Q$12 -> 0.53508993 | R20: =SUMPRODUCT($D$12:$M$12,D20:M20)/$R$12 -> 0.54183395 | T20: 0.47560795 | U20: 0.4844022 | V20: 0.57638134 | W20: 0.49662714 | X20: 0.53934664 | Y20: 0.54510952 | Z20: 0.50293145 | AA20: 0.5307765 | AB20: 0.54398213 | AC20: 0.52332063 | AD20: 0.58348174 | AF20: =SUMPRODUCT(T$12:Y$12,T20:Y20)/AF$12 -> 0.5196388 | AG20: =SUMPRODUCT($T$12:$AD$12,T20:AD20)/$AG$12 -> 0.52779762 | AI20: =Q20-AF20 -> 0.015451127 | AJ20: =AI20/AF20 -> 0.029734359 | AL20: =R20-AG20 -> 0.014036333 | AM20: =AL20/AG20 -> 0.026594157 | AQ20: Ley Cu,% | AS20: =AS18 -> 8332.3276 | AT20: =AT19 -> 93.369271 | AU20: =+$E$20 -> 0.5236813 | AV20: =AV17 -> 89.928394 | AW20: =AW17 -> -773.55487 | AX20: =AS20*AT20*24*28/100*AU20/100*AV20/100+AW20 -> 23847.32 | AY20: =AX20-AX19 -> 1846.7067
B21: Rec. Cu | C21: % | D21: 88.474775 | E21: 86.11153 | F21: 90.116266 | G21: 89.308562 | H21: 89.057102 | I21: 91.0301 | J21: 90.257233 | K21: 91.257921 | L21: 91.270096 | M21: 90.857196 | Q21: =Q7/(Q12*Q20/100)*100 -> 89.127342 | R21: =R7/(R12*R20/100)*100 -> 89.877085 | T21: 89.520023 | U21: 89.928394 | V21: 89.737258 | W21: 90.750864 | X21: 89.659343 | Y21: 89.798757 | Z21: 90.726507 | AA21: 89.208497 | AB21: 89.798087 | AC21: 89.45898 | AD21: =+AD7/(AD12*AD20%)*100 -> 89.195802 | AF21: =AF7/(AF12*AF20/100)*100 -> 89.89566 | AG21: =AG7/(AG12*AG20/100)*100 -> 89.777351 | AI21: =Q21-AF21 -> -0.76831883 | AJ21: =AI21/AF21 -> -0.0085467845 | AL21: =R21-AG21 -> 0.099733533 | AM21: =AL21/AG21 -> 0.0011108986 | AQ21: RCu, % | AS21: =AS18 -> 8332.3276 | AT21: =AT19 -> 93.369271 | AU21: =AU20 -> 0.5236813 | AV21: =+$E$21 -> 86.11153 | AW21: =AW17 -> -773.55487 | AX21: =AS21*AT21*24*28/100*AU21/100*AV21/100+AW21 -> 22802.327 | AY21: =AX21-AX20 -> -1044.9929
B22: Conc Cu Producido | C22: Kton | D22: 90.493144 | E22: 83.847982 | F22: 99.042431 | G22: 89.566273 | H22: 93.007885 | I22: 89.551669 | J22: 92.499418 | K22: 95.244432 | L22: 91.600563 | M22: 96.822295 | Q22: =SUM(D22:I22) -> 545.50938 | R22: =+SUM(D22:N22) -> 921.67609 | T22: 89.110927 | U22: 84.171301 | V22: 90.892581 | W22: 92.263072 | X22: 101.86319 | Y22: 103.56013 | Z22: 76.758648 | AA22: 81.551769 | AB22: 94.318199 | AC22: 97.434661 | AD22: =+AD7/AD23% -> 98.533999 | AF22: =SUM(T22:Y22) -> 561.8612 | AG22: =+SUM(T22:AE22) -> 1010.4585 | AI22: =Q22-AF22 -> -16.351817 | AJ22: =AI22/AF22 -> -0.029102948 | AL22: =R22-AG22 -> -88.782386 | AM22: =AL22/AG22 -> -0.087863468 | AQ22: Inventarios | AS22: =AS18 -> 8332.3276 | AT22: =AT19 -> 93.369271 | AU22: =AU20 -> 0.5236813 | AV22: =AV21 -> 86.11153 | AW22: =+($E$8-$E$7)*1000 -> -1213.4094 | AX22: =AS22*AT22*24*28/100*AU22/100*AV22/100+AW22 -> 22362.473 | AY22: =AX22-AX21 -> -439.85457
B23: Ley Conc. Cu | C23: % | D23: 26.470502 | E23: 26.857094 | F23: 26.835994 | G23: 27.779301 | H23: 26.877862 | I23: 28.76172 | J23: 27.082185 | K23: 28.097974 | L23: 27.272077 | M23: 27.973431 | Q23: =Q7/Q22*100 -> 27.276192 | R23: =R7/R22*100 -> 27.423336 | T23: 26.794085 | U23: 27.030132 | V23: 29.110496 | W23: 28.718587 | X23: 29.524478 | Y23: 28.468308 | Z23: 30.39507 | AA23: 30.85406 | AB23: 30.443925 | AC23: 29.853081 | AD23: 30.537685 | AF23: =AF7/AF22*100 -> 28.323791 | AG23: =AG7/AG22*100 -> 29.246594 | AI23: =Q23-AF23 -> -1.0475999 | AJ23: =AI23/AF23 -> -0.036986569 | AL23: =R23-AG23 -> -1.823258 | AM23: =AL23/AG23 -> -0.062340865 | AQ23: Real | AS23: =AS18 -> 8332.3276 | AT23: =AT19 -> 93.369271 | AU23: =AU20 -> 0.5236813 | AV23: =AV21 -> 86.11153 | AW23: =AW22 -> -1213.4094 | AY23: =+SUM(AY17:AY22) -> 22362.473 | AZ23: =AY23-AY17 -> 384.41364
B25: Ley Alim. Mo | C25: ppm | D25: 174.76501 | E25: 199.16807 | F25: 196.46034 | G25: 241.18259 | H25: 263.90326 | I25: 280.52512 | J25: 209.4622 | K25: 256.88781 | L25: 273.14672 | M25: 282.80736 | Q25: =SUMPRODUCT(D$12:I$12,D25:I25)/Q$12 -> 226.00731 | R25: =SUMPRODUCT($D$12:$N$12,D25:N25)/$R$12 -> 238.21661 | T25: 179.78398 | U25: 209.52561 | V25: 231.98672 | W25: 236.94845 | X25: 229.03083 | Y25: 240.44486 | Z25: 194.46641 | AA25: 235.97812 | AB25: 278.22511 | AC25: 208.13685 | AD25: 267.45959 | AF25: =SUMPRODUCT(T$12:Y$12,T25:Y25)/AF$12 -> 221.762 | AG25: =SUMPRODUCT($T$12:$AD$12,T25:AD25)/$AG$12 -> 228.93611 | AI25: =Q25-AF25 -> 4.2453123 | AJ25: =AI25/AF25 -> 0.019143552 | AL25: =R25-AG25 -> 9.2805015 | AM25: =AL25/AG25 -> 0.040537517
B26: Rec. Mo Global | C26: % | D26: 74.576476 | E26: 77.250234 | F26: 75.386387 | G26: 82.430917 | H26: 85.516143 | I26: 82.960449 | J26: 81.850793 | K26: 83.617485 | L26: 80.250897 | M26: 84.392546 | Q26: =Q9/(Q12*Q25)*100000000 -> 80.364484 | R26: =R9/(R12*R25)*100000000 -> 81.33463 | T26: 83.302041 | U26: 83.405539 | V26: 83.860718 | W26: 83.910666 | X26: 84.148913 | Y26: 84.236979 | Z26: 82.956376 | AA26: 84.271235 | AB26: 84.407831 | AC26: 83.611843 | AD26: =+AD9/(AD12*AD25*10^-8) -> 82.971728 | AF26: =AF9/(AF12*AF25)*100000000 -> 83.855898 | AG26: =AG9/(AG12*AG25)*100000000 -> 83.630768 | AI26: =Q26-AF26 -> -3.4914143 | AJ26: =AI26/AF26 -> -0.041635882 | AL26: =R26-AG26 -> -2.2961383 | AM26: =AL26/AG26 -> -0.027455664
B27: Conc Mo Producido | C27: ton | D27: 1.0760145 | E27: 1.3516964 | F27: 1.9218213 | G27: 1.9635255 | H27: 2.2737817 | I27: 2.2828355 | J27: 1.7455797 | K27: 1.8177446 | L27: 2.1524625 | M27: 2.5823875 | Q27: =SUM(D27:I27) -> 10.869675 | R27: =+SUM(D27:N27) -> 19.167849 | T27: 1.5552975 | U27: 1.6902366 | V27: 1.8429912 | W27: 2.1646466 | X27: 2.2196507 | Y27: 2.2590439 | Z27: 1.5275241 | AA27: 1.9569744 | AB27: 2.5148056 | AC27: 2.0023217 | AF27: =SUM(T27:Y27) -> 11.731867 | AG27: =+SUM(T27:AE27) -> 19.733492 | AI27: =Q27-AF27 -> -0.8621917 | AJ27: =AI27/AF27 -> -0.073491434 | AL27: =R27-AG27 -> -0.56564313 | AM27: =AL27/AG27 -> -0.028664117
B28: As Alim. | C28: ppm | D28: 26.762132 | E28: 62.305812 | F28: 70.909227 | G28: ='[18]TP sin BM'!F26 -> 29.442452 | H28: ='[18]TP sin BM'!F26 -> 29.442452 | I28: 33.650043 | Q28: =SUMPRODUCT(D$12:H$12,D28:H28)/Q$12 -> 36.526341 | R28: =SUMPRODUCT($D$12:$I$12,D28:I28)/$R$12 -> 25.275176 | T28: 37.982096 | U28: 26.012162 | V28: 39.398148 | W28: 19.755106 | X28: 34.418888 | Y28: 37.982096 | AF28: =SUMPRODUCT(T$12:X$12,T28:X28)/AF$12 -> 25.848788 | AG28: =SUMPRODUCT($T$12:$Y$12,T28:Y28)/$AG$12 -> 17.787465 | AI28: =Q28-AF28 -> 10.677554 | AJ28: =AI28/AF28 -> 0.41307754 | AL28: =R28-AG28 -> 7.4877116 | AM28: =AL28/AG28 -> 0.42095441 | AY28: Inv. Final: | AZ28: 3105
B29: As Conc. | C29: ppm | D29: 1684.0909 | E29: 2118.3123 | F29: 1608.4598 | G29: ='[18]TP sin BM'!F27 -> 1304.1798 | H29: ='[18]TP sin BM'!F27 -> 1304.1798 | I29: 1346.0017 | Q29: =SUMPRODUCT(D$22:H$22,D29:H29)/Q$22 -> 1333.4879 | R29: =SUMPRODUCT($D$22:$I$22,D29:I29)/$R$22 -> 920.02699 | T29: 1521.919 | U29: 1040.4865 | V29: 1575.9259 | W29: 780.83285 | X29: 1376.6955 | Y29: 1519.2838 | AF29: =SUMPRODUCT(T$22:X$22,T29:X29)/AF$22 -> 1029.9969 | AG29: =SUMPRODUCT($T$22:$Y$22,T29:Y29)/$AG$22 -> 728.43423 | AI29: =Q29-AF29 -> 303.491 | AJ29: =AI29/AF29 -> 0.29465234 | AL29: =R29-AG29 -> 191.59275 | AM29: =AL29/AG29 -> 0.26301997 | AQ29: MARZO | AS29: Rendimiento | AT29: CM % | AU29: Ley Cu | AV29: Rec Cu | AW29: CuFFP-CuFP | AX29: TMF | AY29: DIF
B31: Pagabilidad | D31: =D8/D32 -> 0.96229821 | E31: =E8/E32 -> 0.96358083 | F31: =F8/F32 -> 0.96420839 | G31: =G8/G32 -> 0.9635875 | H31: =H8/H32 -> 0.96293895 | I31: =I8/I32 -> 0.9649746 | J31: =J8/J32 -> 0.96528417 | K31: 0.9644 | L31: 0.9644 | M31: 0.9644 | N31: 0.9644 | Q31: =Q8/Q32 -> 0.9636225 | R31: =R8/R32 -> 0.96402975 | T31: 0.966 | U31: 0.966 | V31: 0.966 | W31: 0.966 | X31: 0.966 | Y31: 0.966 | Z31: 0.966 | AA31: 0.966 | AB31: 0.966 | AC31: 0.966 | AD31: 0.966 | AE31: 0.966 | AF31: =AF8/AF32 -> 0.966 | AG31: =AG8/AG32 -> 0.966 | AQ31: BDGT Ajustado | AS31: =V14 -> 8745.2728 | AT31: =V18 -> 78.622894 | AU31: =V20 -> 0.57638134 | AV31: =V21 -> 89.737258 | AW31: =(V8-V7)*1000 -> -899.61556 | AX31: =AS31*AT31*24*$V$2/100*AU31/100*AV31/100+AW31 -> 25559.665 | AY31: =AX31 -> 25559.665
B32: Cu Filtrado | D32: 23.57423 | E32: 22.110986 | F32: 26.865801 | G32: 24.68821 | H32: 25.625562 | I32: 25.723542 | J32: 25.112021 | K32: =K8/K31 -> 22.943435 | L32: =L8/L31 -> 27.596007 | M32: =M8/M31 -> 27.81909 | N32: =N8/N31 -> 0 | Q32: =SUM(D32:I32) -> 148.58833 | R32: =SUM(D32:M32) -> 252.05888 | T32: =T8/T31 -> 23.876458 | U32: =U8/U31 -> 22.751614 | V32: =V8/V31 -> 26.459281 | W32: =W8/W31 -> 26.49665 | X32: =X8/X31 -> 30.074574 | Y32: =Y8/Y31 -> 29.481818 | Z32: =Z8/Z31 -> 23.330845 | AA32: =AA8/AA31 -> 25.162032 | ... AE32: =AE8/AE31 -> 0 | AF32: =SUM(T32:Y32) -> 159.14039 | AG32: =+SUM(T32:AE32) -> 295.52468 | AQ32: Rendimiento | AS32: =+$F$14 -> 7997.1747 | AT32: =AT31 -> 78.622894 | AU32: =AU31 -> 0.57638134 | AV32: =AV31 -> 89.737258 | AW32: =AW31 -> -899.61556 | AX32: =AS32*AT32*24*$V$2/100*AU32/100*AV32/100+AW32 -> 23296.255 | AY32: =AX32-AX31 -> -2263.41
AQ33: CM % | AS33: =AS32 -> 7997.1747 | AT33: =+$F$18 -> 89.875 | AU33: =AU31 -> 0.57638134 | AV33: =AV31 -> 89.737258 | AW33: =AW31 -> -899.61556 | AX33: =AS33*AT33*24*$V$2/100*AU33/100*AV33/100+AW33 -> 26759.044 | AY33: =AX33-AX32 -> 3462.789
L34: =+L17*25.4 -> 105.41 | AQ34: Ley Cu,% | AS34: =AS32 -> 7997.1747 | AT34: =AT33 -> 89.875 | AU34: =+$F$20 -> 0.5518866 | AV34: =AV31 -> 89.737258 | AW34: =AW31 -> -899.61556 | AX34: =AS34*AT34*24*$V$2/100*AU34/100*AV34/100+AW34 -> 25583.622 | AY34: =AX34-AX33 -> -1175.4228
AQ35: RCu, % | AS35: =AS32 -> 7997.1747 | AT35: =AT33 -> 89.875 | AU35: =AU34 -> 0.5518866 | AV35: =+$F$21 -> 90.116266 | AW35: =AW31 -> -899.61556 | AX35: =AS35*AT35*24*$V$2/100*AU35/100*AV35/100+AW35 -> 25695.474 | AY35: =AX35-AX34 -> 111.85269
C36: Rend | D36: CM | E36: Ley | F36: Rec | G36: Inv | H36: Pag | I36: Fino | J36: DIF | AQ36: Inventarios | AS36: =AS32 -> 7997.1747 | AT36: =AT33 -> 89.875 | AU36: =AU34 -> 0.5518866 | AV36: =AV35 -> 90.116266 | AW36: =+($F$8-$F$7)*1000 -> -674.78991 | AX36: =AS36*AT36*24*$V$2/100*AU36/100*AV36/100+AW36 -> 25920.3 | AY36: =AX36-AX35 -> 224.82564
B37: BDGT H1 | C37: =AF14 -> 8608.6106 | D37: =AF18 -> 54.24032 | E37: =AF20 -> 0.5196388 | F37: =AF21 -> 89.89566 | G37: =(AF8/$AF$31-AF7)*1000 -> -1.0174972e-08 | H37: =AF31 -> 0.966 | I37: =(C37*$AF$2*24*D37/100*E37/100*F37/100+G37)*H37 -> 153729.62 | J37: =I37 -> 153729.62 | AA37: =(C37*$AF$2*24*D37/100)/1000 -> 34067.49 | AG37: TMS | AO37: Real | AQ37: =AS32 -> 7997.1747 | AR37: =AT33 -> 89.875 | AS37: =AU34 -> 0.5518866 | AT37: =AV35 -> 90.116266 | AU37: =AW36 -> -674.78991 | AW37: =+SUM(AY31:AY36) -> 25920.3 | AX37: =AW37-AY31 -> 360.63446
B38: Rendimiento | C38: =Q14 -> 8114.535 | D38: =D37 -> 54.24032 | E38: =E37 -> 0.5196388 | F38: =F37 -> 89.89566 | G38: =G37 -> -1.0174972e-08 | H38: =H37 -> 0.966 | I38: =(C38*$AF$2*24*D38/100*E38/100*F38/100+G38)*H38 -> 144906.59 | J38: =I38-I37 -> -8823.0336 | AA38: =(C38*$AF$2*24*D38/100)/1000 -> 32112.248 | AG38: =AA38-AA37 -> -1955.242 | AH38: Rendimiento
B39: CM | C39: =C38 -> 8114.535 | D39: =Q18 -> 52.698684 | E39: =E38 -> 0.5196388 | F39: =F38 -> 89.89566 | G39: =G38 -> -1.0174972e-08 | H39: =H38 -> 0.966 | I39: =(C39*$AF$2*24*D39/100*E39/100*F39/100+G39)*H39 -> 140788 | J39: =I39-I38 -> -4118.583 | K39: =J39+J38 -> -12941.617 | AA39: =(C39*$AF$2*24*D39/100)/1000 -> 31199.543 | AG39: =AA39-AA38 -> -912.70494 | AH39: CM
B40: Ley | C40: =C39 -> 8114.535 | D40: =D39 -> 52.698684 | E40: =Q20 -> 0.53508993 | F40: =F39 -> 89.89566 | G40: =G39 -> -1.0174972e-08 | H40: =H39 -> 0.966 | I40: =(C40*$AF$2*24*D40/100*E40/100*F40/100+G40)*H40 -> 144974.25 | J40: =I40-I39 -> 4186.2411
B41: Rec Cu | C41: =C40 -> 8114.535 | D41: =D40 -> 52.698684 | E41: =E40 -> 0.53508993 | F41: =Q21 -> 89.127342 | G41: =G40 -> -1.0174972e-08 | H41: =H40 -> 0.966 | I41: =(C41*$AF$2*24*D41/100*E41/100*F41/100+G41)*H41 -> 143735.18 | J41: =I41-I40 -> -1239.0636
B42: Inv. | C42: =C41 -> 8114.535 | D42: =D41 -> 52.698684 | E42: =E40 -> 0.53508993 | F42: =F41 -> 89.127342 | G42: =(Q8/Q31-Q7)*1000 -> -205.85478 | H42: =H41 -> 0.966 | I42: =(C42*$AF$2*24*D42/100*E42/100*F42/100+G42)*H42 -> 143536.33 | J42: =I42-I41 -> -198.85572
B43: Pagabilidad | C43: =C42 -> 8114.535 | D43: =D42 -> 52.698684 | E43: =E41 -> 0.53508993 | F43: =F42 -> 89.127342 | G43: =G42 -> -205.85478 | H43: =Q31 -> 0.9636225 | I43: =(C43*$AF$2*24*D43/100*E43/100*F43/100+G43)*H43 -> 143183.06 | J43: =I43-I42 -> -353.26852
B44: Real H1 | C44: =C43 -> 8114.535 | D44: =D43 -> 52.698684 | E44: =E42 -> 0.53508993 | F44: =F43 -> 89.127342 | G44: =G42 -> -205.85478 | H44: =H43 -> 0.9636225 | I44: =(C44*$AF$2*24*D44/100*E44/100*F44/100+G44)*H44 -> 143183.06 | J44: =I44 -> 143183.06
J46: =J44-J37 -> -10546.563
J47: =J46/J37 -> -0.068604627
C55: Unidad | D55: BM Ene | E55: BM Feb | F55: BM Mar | G55: BM Abr | H55: BM May | I55: BM Jun | J55: R+P Jul | K55: Acum. H1 | Q55: Acum a Julio | S55: BD Ene | T55: BD Feb | U55: BD Mar | V55: BD Abr | W55: BD May | X55: BD Jun | Y55: BD Jul | Z55: BD H1 | AA55: BD a Julio | AG55: DIF H1 | AH55: % | AJ55: DIF a Julio | AK55: %
B56: Fino Mo Producido | C56: ktons | D56: 0.6877459 | E56: 0.7682988 | F56: 0.7919837 | G56: 0.9899452 | H56: 1.2376732 | I56: 1.191114 | J56: 0.92782648 | K56: =SUM(D56:I56) -> 5.6667608 | Q56: =SUM(D56:J56) -> 6.5945873 | S56: 0.83986064 | T56: 0.91272777 | U56: 0.99521526 | V56: 1.1689092 | W56: 1.1986114 | X56: 1.2198837 | Y56: 0.82486301 | Z56: =SUM(S56:X56) -> 6.335208 | AA56: =SUM(S56:Y56) -> 7.160071 | AG56: =K56-Z56 -> -0.66844724 | AH56: =AG56/Z56 -> -0.10551307 | AJ56: =Q56-AA56 -> -0.56548376 | AK56: =AJ56/AA56 -> -0.078977396
B57: Onzas de Oro Producidas | C57: oz | D57: 3.9962795 | E57: 3.615752 | F57: 4.9296788 | G57: 5.2189639 | H57: 4.8311143 | I57: 5.4226484 | J57: 5.0281812 | K57: =SUM(D57:I57) -> 28.014437 | Q57: =SUM(D57:J57) -> 33.042618 | S57: 4.4584173 | T57: 3.8181149 | U57: 4.8931964 | V57: 4.6932379 | W57: 5.7308184 | X57: 4.5636577 | Y57: 5.849605 | Z57: =SUM(S57:X57) -> 28.157443 | AA57: =SUM(S57:Y57) -> 34.007048 | AG57: =K57-Z57 -> -0.14300587 | AH57: =AG57/Z57 -> -0.0050787946 | AJ57: =Q57-AA57 -> -0.96442964 | AK57: =AJ57/AA57 -> -0.028359699
B58: Onzas de Plata Producidas | C58: koz | D58: 152.81578 | E58: 166.86104 | F58: 201.96013 | G58: 197.90573 | H58: 187.39818 | I58: 210.71566 | J58: 229.34197 | K58: =SUM(D58:I58) -> 1117.6565 | Q58: =SUM(D58:J58) -> 1346.9985 | S58: 176.54719 | T58: 160.28534 | U58: 202.12331 | V58: 207.54693 | W58: 225.03616 | X58: 208.00539 | Y58: 210.17745 | Z58: =SUM(S58:X58) -> 1179.5443 | AA58: =SUM(S58:Y58) -> 1389.7218 | AG58: =K58-Z58 -> -61.887815 | AH58: =AG58/Z58 -> -0.052467562 | AJ58: =Q58-AA58 -> -42.723303 | AK58: =AJ58/AA58 -> -0.030742342

Sheet TP sin BM
C1: Días: | D1: =D2/30 -> 0.55 | F1: Inv. Final Proy | Z1: $Q | AA1: $P | AB1: =0.5/28 -> 0.017857143 | AD1: =F16*28*24/100+474.5 -> 1094.9188
A2: Sin BM | D2: =+COUNT(Real!C9:C39)-0.5 -> 16.5 | E2: =+DAY(EOMONTH('ST Original'!B8,0))-D2 -> 14.5 | F2: ='R+P'!AP38 -> 2600
G3: R+P vs PM | J3: R+P v/s Budget | M3: R+P vs OL 0+12 | Q3: R+P Acum. v/s OL 0+12 Acum | W3: R+P Acum. v/s Budget Acum. | AA3: MTD | AB3: Proy PM | AE3: Plan Mensual Versus Budget
A4: Enero | C4: Unidad | D4: Real | E4: Proyección | F4: R + P Mar | G4: PM Mar | H4: Q | I4: Δ% | J4: B | K4: Q | L4: Δ% | M4: OL | N4: Q | O4: Δ% | P4: R+P Acum. | Q4: OL | R4: Q | S4: Δ% | W4: B | X4: Q | Y4: Δ% | AA4: Real (PM) | AB4: (Proyección PM)
A5: 23.95399 | B5: Cu Fino Producido | C5: Kton | D5: =Real!P40/1000 -> 12.974353 | E5: ='R+P'!Q132/1000 -> 14.387667 | F5: =+'Comparacion (Sin BM)'!Q14 -> 27.36202 | G5: =+'Comparacion (Sin BM)'!R14 -> 28.318352 | H5: =F5-G5 -> -0.95633141 | I5: =H5/G5 -> -0.03377073 | J5: =+BDGT!$G$7 -> 29.514271 | K5: =+F5-J5 -> -2.1522506 | L5: =+K5/J5 -> -0.072922369 | M5: =+'0+12'!$G$15 -> 28.86486 | N5: =F5-M5 -> -1.5028395 | O5: =N5/M5 -> -0.052064675 | P5: =+'Comparacion (Sin BM)'!Q94 -> 69.247827 | Q5: =+'0+12'!$T$15 -> 70.975674 | R5: =P5-Q5 -> -1.7278477 | S5: =R5/Q5 -> -0.024344224 | W5: =BDGT!$T$7 -> 71.201972 | X5: =P5-W5 -> -1.9541453 | Y5: =X5/W5 -> -0.027445101 | AA5: =+'Comparacion (Sin BM)'!AF79/1000 -> 13.540082 | AB5: =+'ST Original'!HM39/1000 -> 14.778269
A6: 22.734987 | B6: Cu Fino Filtrado Pagable | C6: Kton | D6: =Real!AQ40*Factores!F7/1000 -> 12.598464 | E6: ='R+P'!AO133/1000 -> 13.841675 | F6: =+'R+P'!AO39*Factores!D24/1000 -> 26.405692 | G6: =+'Comparacion (Sin BM)'!R15 -> 27.229795 | H6: =F6-G6 -> -0.82410323 | I6: =H6/G6 -> -0.03026476 | J6: =+BDGT!$G$8 -> 28.422385 | K6: =+F6-J6 -> -2.0166927 | L6: =+K6/J6 -> -0.070954379 | M6: =+'0+12'!$G$16 -> 28.232331 | N6: =F6-M6 -> -1.8266393 | O6: =N6/M6 -> -0.064700265 | P6: =+'Comparacion (Sin BM)'!Q95 -> 66.124566 | Q6: =+'0+12'!$T$16 -> 67.898281 | R6: =P6-Q6 -> -1.7737148 | S6: =R6/Q6 -> -0.026123118 | W6: =BDGT!$T$8 -> 68.589013 | X6: =P6-W6 -> -2.4644466 | Y6: =X6/W6 -> -0.035930632 | AA6: =+'Comparacion (Sin BM)'!AF81/1000 -> 12.114235 | AB6: =+'ST Original'!IC39*0.96/1000 -> 15.084135
A7: 0.68774587 | B7: Mo Fino Producido | C7: Kton | D7: =Real!Y40/1000 -> 0.49534409 | E7: ='R+P'!AA132/1000 -> 0.41228326 | F7: =+'Comparacion (Sin BM)'!Q18 -> 0.90762735 | G7: =+'Comparacion (Sin BM)'!R18 -> 0.80794675 | H7: =F7-G7 -> 0.099680594 | I7: =H7/G7 -> 0.1233752 | J7: =+BDGT!$G$9 -> 1.0603706 | K7: =+F7-J7 -> -0.15274327 | L7: =+K7/J7 -> -0.14404706 | M7: =+'0+12'!$G$17 -> 1.0136224 | N7: =F7-M7 -> -0.10599505 | O7: =N7/M7 -> -0.10457055 | P7: =+'Comparacion (Sin BM)'!Q98 -> 2.3019282 | Q7: =+'0+12'!$T$17 -> 2.4060426 | R7: =P7-Q7 -> -0.10411448 | S7: =R7/Q7 -> -0.043272083 | W7: =BDGT!$T$9 -> 2.5089172 | X7: =P7-W7 -> -0.20698906 | Y7: =X7/W7 -> -0.082501351 | AA7: =+'Comparacion (Sin BM)'!AF80/1000 -> 0.45280369 | AB7: =+'ST Original'!HV39/1000 -> 0.35514307
A8: 0.56381979 | B8: Mo Fino Envasado Pagable | C8: Kton | D8: =Real!AA40/1000*0.995 -> 0.56560301 | E8: ='R+P'!AC132/1000*0.995 -> 0.42988826 | F8: =+'Comparacion (Sin BM)'!Q20 -> 0.99549127 | G8: =+'Comparacion (Sin BM)'!R20 -> 0.87678878 | H8: =F8-G8 -> 0.11870248 | I8: =H8/G8 -> 0.13538321 | J8: =+BDGT!$G$10 -> 1.0550688 | K8: =+F8-J8 -> -0.059577501 | L8: =+K8/J8 -> -0.056467884 | M8: =+'0+12'!$G$18 -> 1.0085543 | N8: =F8-M8 -> -0.013063018 | O8: =N8/M8 -> -0.012952221 | P8: =+'Comparacion (Sin BM)'!Q100 -> 2.1888169 | Q8: =+'0+12'!$T$18 -> 2.3877799 | R8: =P8-Q8 -> -0.19896292 | S8: =R8/Q8 -> -0.083325488 | W8: =BDGT!$T$10 -> 2.4963726 | X8: =P8-W8 -> -0.3075557 | Y8: =X8/W8 -> -0.12320104 | AA8: =+'Comparacion (Sin BM)'!AF82/1000 -> 0.44690052 | AB8: =+'ST Original'!HX39/1000 -> 0.4320485
A10: 5276.8123 | B10: Tonelaje Procesado | C10: Kton | D10: =Real!E40/1000 -> 2919.0798 | E10: ='R+P'!E132/1000 -> 2915.7712 | F10: =+'Comparacion (Sin BM)'!Q27 -> 5834.851 | G10: =+'Comparacion (Sin BM)'!R27 -> 5857.1988 | H10: =F10-G10 -> -22.347735 | I10: =H10/G10 -> -0.0038154305 | J10: =+BDGT!$G$12 -> 5835.7551 | K10: =+F10-J10 -> -0.90403301 | L10: =+K10/J10 -> -0.00015491277 | M10: =+'0+12'!$G$20 -> 5652.5027 | N10: =F10-M10 -> 182.34839 | O10: =N10/M10 -> 0.032259761 | P10: =+'R+RP+B'!U15 -> 14929.684 | Q10: =+'0+12'!$T$20 -> 14823.126 | R10: =P10-Q10 -> 106.55757 | S10: =R10/Q10 -> 0.0071886033 | W10: =BDGT!$T$12 -> 15189.938 | X10: =P10-W10 -> -260.25449 | Y10: =X10/W10 -> -0.017133348 | AA10: =+'Comparacion (Sin BM)'!AF68 -> 2933.8431 | AB10: =+'ST Original'!HD39/1000 -> 2923.3556
A11: 173.01024 | B11: Toneladas por día | C11: Ktpd | D11: =D10/D2 -> 176.91393 | E11: =E10/E2 -> 201.08767 | F11: =+F10/31 -> 188.221 | G11: =+G10/31 -> 188.9419 | H11: =F11-G11 -> -0.72089467 | I11: =H11/G11 -> -0.0038154305 | J11: =+BDGT!$G$13 -> 188.25016 | K11: =+F11-J11 -> -0.029162355 | L11: =+K11/J11 -> -0.00015491277 | M11: =+'0+12'!$G$21 -> 182.3388 | N11: =F11-M11 -> 5.882206 | O11: =N11/M11 -> 0.032259761 | P11: ='Comparacion (Sin BM)'!Q105 -> 165.88538 | Q11: =+'0+12'!$T$21 -> 165.62152 | R11: =P11-Q11 -> 0.26385348 | S11: =R11/Q11 -> 0.001593111 | W11: =+BDGT!$T$13 -> 168.77709 | X11: =P11-W11 -> -2.8917166 | Y11: =X11/W11 -> -0.017133348 | AA11: =+AA10/D2 -> 177.80867 | AB11: =+AB10/E2 -> 201.61073
A12: 8149.1748 | B12: Rendimiento Global | C12: Tph | D12: =IFERROR(D10*1000/(24*(Real!$E$41)*'TP sin BM'!D16/100),0) -> 8365.4531 | E12: =E10*1000/(24*E2*'TP sin BM'!E16/100) -> 8549.4495 | F12: =+F10*1000/(F16%*24*31) -> 8494.565 | G12: =+G10*1000/(G16%*24*31) -> 8497.054 | H12: =F12-G12 -> -2.4889809 | I12: =H12/G12 -> -0.00029292281 | J12: =+BDGT!$G$14 -> 8256.2174 | K12: =+F12-J12 -> 238.34756 | L12: =+K12/J12 -> 0.028868857 | M12: ='0+12'!$G$22 -> 8052.7228 | N12: =+F12-M12 -> 441.8422 | O12: =+N12/M12 -> 0.054868671 | P12: =+P10*1000/(P16%*24*90) -> 8424.7006 | Q12: =+'0+12'!$T$22 -> 8223.3351 | R12: =P12-Q12 -> 201.36548 | S12: =R12/Q12 -> 0.024487082 | W12: =+BDGT!$T$14 -> 8151.9777 | X12: =P12-W12 -> 272.72286 | Y12: =X12/W12 -> 0.03345481 | AA12: =+'Comparacion (Sin BM)'!AF70 -> 8414.2412 | AB12: =+'ST Original'!HF39 -> 8576.3314
A13: 37.515527 | B13: AxB | C13: - | D13: =IFERROR(Real!AU40,0) -> 37.942958 | E13: ='R+P'!BE132 -> 38.005298 | F13: =+'Comparacion (Sin BM)'!Q33 -> 37.97411 | G13: =+'Comparacion (Sin BM)'!R33 -> 37.368349 | H13: =F13-G13 -> 0.6057616 | I13: =H13/G13 -> 0.016210553 | J13: =+BDGT!$G$18 -> 37.853336 | K13: =+F13-J13 -> 0.12077419 | L13: =+K13/J13 -> 0.0031905825 | M13: =+'0+12'!$G$24 -> 38.199063 | N13: =F13-M13 -> -0.22495251 | O13: =N13/M13 -> -0.0058889536 | P13: =+'Comparacion (Sin BM)'!Q114 -> 37.84201 | Q13: =+'0+12'!$T$24 -> 37.648151 | R13: =P13-Q13 -> 0.19385921 | S13: =R13/Q13 -> 0.0051492359 | W13: =+BDGT!$T$18 -> 38.202371 | X13: =P13-W13 -> -0.36036129 | Y13: =X13/W13 -> -0.009432956 | AA13: =+'Comparacion (Sin BM)'!AF71 -> 36.900097
A14: 78.664564 | B14: RQD | C14: - | D14: =IFERROR(Real!AC40,0) -> 75.419101 | E14: ='R+P'!AW132 -> 85.051372 | F14: =+'R+P'!AW39 -> 80.339422 | G14: =+'ST Original'!AU39 -> 82.923534 | H14: =G14-F14 -> 2.5841121 | I14: =H14/G14 -> 0.031162589 | J14: =+BDGT!$G$57 -> 81.009536 | K14: =+F14-J14 -> -0.6701141 | L14: =+K14/J14 -> -0.0082720397 | M14: =+'0+12'!$G$65 -> 82.367317 | N14: =F14-M14 -> -2.0278952 | O14: =N14/M14 -> -0.024620143 | P14: =+'R+RP+B'!U53 -> 82.461031 | Q14: =+'0+12'!$T$65 -> 84.107514 | R14: =P14-Q14 -> -1.646483 | S14: =R14/Q14 -> -0.019575932 | W14: =BDGT!T57 -> 82.672478 | X14: =P14-W14 -> -0.21144734 | Y14: =X14/W14 -> -0.0025576509
A15: 4.1622031 | B15: F80 | C15: In | D15: =IFERROR(Real!AS40,0) -> 4.6902586 | E15: ='R+P'!BD132 -> 4.1994294 | F15: =+'R+P'!BD39 -> 4.4644232 | G15: =+'ST Original'!AX39 -> 4.2028666 | H15: =-F15+G15 -> -0.26155667 | I15: =H15/G15 -> -0.062232922 | J15: =+BDGT!$G$19 -> 4.1504745 | K15: =J15-F15 -> -0.31394871 | L15: =K15/J15 -> -0.075641641 | M15: =+'0+12'!$G$64 -> 4.1562992 | N15: =M15-F15 -> -0.30812401 | O15: =N15/M15 -> -0.074134222 | P15: =+'Comparacion (Sin BM)'!Q109 -> 4.6985318 | Q15: =+'0+12'!$T$64 -> 4.2460434 | R15: =Q15-P15 -> -0.4524884 | S15: =R15/Q15 -> -0.10656707 | W15: =+BDGT!$T$19 -> 4.1523939 | X15: =W15-P15 -> -0.54613798 | Y15: =X15/W15 -> -0.13152365 | AA15: =+'Comparacion (Sin BM)'!AF72 -> 4.1675369
A16: 88.46 | B16: CM Global | C16: % | D16: =IFERROR(Real!J40,0) -> 88.117328 | E16: ='R+P'!J132 -> 98.00225 | F16: =+'Comparacion (Sin BM)'!Q32 -> 92.32423 | G16: =+'ST Original'!CB39 -> 92.650689 | H16: =F16-G16 -> -0.32645839 | I16: =H16/G16 -> -0.0035235398 | J16: =+BDGT!$G$20*100 -> 95.068132 | K16: =+F16-J16 -> -2.7439022 | L16: =+K16/J16 -> -0.028862482 | M16: =+'0+12'!$G$25*100 -> 94.409795 | N16: =F16-M16 -> -2.0855646 | O16: =N16/M16 -> -0.022090554 | P16: ='Comparacion (Sin BM)'!Q108 -> 82.043161 | Q16: =+'0+12'!$T$25*100 -> 83.915863 | R16: =P16-Q16 -> -1.8727026 | S16: =R16/Q16 -> -0.022316431 | W16: =+BDGT!$T$20 -> 86.3258 | X16: =P16-W16 -> -4.282639 | Y16: =X16/W16 -> -0.049610186 | AA16: =+'Comparacion (Sin BM)'!AF69 -> 88.216548 | AB16: =+'ST Original'!HE39 -> 97.936038
B17: Horas Disponibles | C17: Hrs | D17: =+D18*D16/100 -> 348.56697 | E17: =+E18*E16/100 -> 340.62782 | F17: =+F18*F16/100 -> 619.95721 | G17: =+G18*G16/100 -> 688.85787 | H17: =F17-G17 -> -68.900664 | I17: =H17/G17 -> -0.1000216 | J17: =+BDGT!$G$22 -> 706.83156 | K17: =F17-J17 -> -86.874359 | L17: =K17/J17 -> -0.12290673 | P17: =+P18*P16/100 -> 1210.5468 | W17: =+BDGT!T22 -> 1863.3439 | X17: =P17-W17 -> -652.7971 | Y17: =X17/W17 -> -0.35033634
B18: Horas Totales | C18: =+C17 -> Hrs | D18: =+(D2-$AB$1)*24 -> 395.57143 | E18: =+(E2-$AB$1)*24 -> 347.57143 | F18: =28*24-0.5 -> 671.5 | G18: =+'PM vs OL y BD'!D18 -> 743.5 | H18: =F18-G18 -> -72 | I18: =H18/G18 -> -0.096839274 | J18: =+BDGT!$G$27 -> 743.5 | K18: =G18-J18 -> 0 | L18: =K18/J18 -> 0 | P18: =+'R+RP+B'!F23+G18 -> 1475.5 | W18: =+BDGT!T27 -> 2158.5 | X18: =P18-W18 -> -683 | Y18: =X18/W18 -> -0.31642344
A20: 0.51308141 | B20: Ley Alim. Cu | C20: % | D20: =IFERROR(Real!K40,0) -> 0.49046726 | E20: ='R+P'!L132 -> 0.54707727 | F20: =+'Comparacion (Sin BM)'!Q34 -> 0.51875622 | G20: =+'Comparacion (Sin BM)'!R34 -> 0.53544933 | H20: =F20-G20 -> -0.016693109 | I20: =H20/G20 -> -0.03117589 | J20: =+BDGT!$G$29 -> 0.56048277 | K20: =+F20-J20 -> -0.04172655 | L20: =+K20/J20 -> -0.074447517 | M20: =+'0+12'!$G$33 -> 0.56467653 | N20: =F20-M20 -> -0.045920315 | O20: =N20/M20 -> -0.08132145 | P20: ='Comparacion (Sin BM)'!Q110 -> 0.51253836 | Q20: =+'0+12'!$T$33 -> 0.53035654 | R20: =P20-Q20 -> -0.017818176 | S20: =R20/Q20 -> -0.033596598 | W20: =+BDGT!$T$29 -> 0.52083856 | X20: =P20-W20 -> -0.0083001949 | Y20: =X20/W20 -> -0.015936214 | AA20: =+'Comparacion (Sin BM)'!AF73 -> 0.51107742 | AB20: =+'ST Original'!HH39 -> 0.55990867 | AF20: Tratamiento | AG20: Ley Cu | AH20: Rec Cu | AI20: TMF | AJ20: dif | AM20: TPH | AN20: CM | AO20: Ley Cu | AP20: Rec Cu | AQ20: TMF | AR20: dif | AS20: =+'TP sin BM'!E2 -> 14.5
A21: 88.474869 | B21: Rec. Cu | C21: % | D21: =IFERROR(Real!L40,0) -> 90.621182 | E21: ='R+P'!M132 -> 90.196204 | F21: =+'Comparacion (Sin BM)'!Q35 -> 90.397219 | G21: =+'Comparacion (Sin BM)'!R35 -> 90.294153 | H21: =F21-G21 -> 0.10306589 | I21: =H21/G21 -> 0.0011414459 | J21: =+BDGT!$G$30 -> 90.234525 | K21: =+F21-J21 -> 0.1626943 | L21: =+K21/J21 -> 0.0018030161 | M21: =+'0+12'!$G$34 -> 90.433416 | N21: =F21-M21 -> -0.036197114 | O21: =N21/M21 -> -0.0004002626 | P21: ='Comparacion (Sin BM)'!Q111 -> 90.504839 | Q21: =+'0+12'!$T$34 -> 90.282129 | R21: =P21-Q21 -> 0.2227105 | S21: =R21/Q21 -> 0.0024668282 | W21: =+BDGT!$T$30 -> 89.998005 | X21: =P21-W21 -> 0.50683434 | Y21: =X21/W21 -> 0.0056316175 | AA21: =+'Comparacion (Sin BM)'!AF75 -> 90.302073 | AB21: =+'ST Original'!HI39 -> 90.286898 | AE21: OL 6+6 | AF21: =+$M$10 -> 5652.5027 | AG21: =+$M$20 -> 0.56467653 | AH21: =+$M$21 -> 90.433416 | AI21: =+AF21*AG21*AH21/10 -> 28864.86 | AJ21: =+AI21 -> 28864.86 | AL21: BDGT | AM21: =#REF! -> #REF! | AN21: =+#REF! -> #REF! | AO21: =+#REF! -> #REF! | AP21: =+#REF! -> #REF! | AQ21: =+#REF!*#REF!*#REF!/10 -> #REF! | AR21: =+AQ21 -> #REF!
A22: 90.493144 | B22: Conc Cu Producido | C22: Kton | D22: =IFERROR(Real!N40/1000,0) -> 50.032932 | E22: ='R+P'!O132/1000 -> 53.585579 | F22: =+'Comparacion (Sin BM)'!Q36 -> 103.61851 | G22: =+'Comparacion (Sin BM)'!R36 -> 105.75347 | H22: =F22-G22 -> -2.1349564 | I22: =H22/G22 -> -0.020188051 | J22: =+BDGT!$G$32 -> 105.71507 | K22: =+F22-J22 -> -2.0965614 | L22: =+K22/J22 -> -0.01983219 | M22: =+'0+12'!$G$35 -> 102.13916 | N22: =F22-M22 -> 1.4793516 | O22: =N22/M22 -> 0.014483687 | P22: ='Comparacion (Sin BM)'!Q112 -> 259.00301 | Q22: =+'0+12'!$T$35 -> 262.54123 | R22: =P22-Q22 -> -3.538219 | S22: =R22/Q22 -> -0.013476813 | W22: =+BDGT!$T$32 -> 254.52677 | X22: =P22-W22 -> 4.4762356 | Y22: =X22/W22 -> 0.017586502 | AA22: =+'ST Original'!FN39/1000 -> 51.308583 | AB22: =+'ST Original'!HL39/1000 -> 54.444884 | AE22: Tratamiento | AF22: =G10 -> 5857.1988 | AG22: =AG21 -> 0.56467653 | AH22: =AH21 -> 90.433416 | AI22: =+AF22*AG22*AH22/10 -> 29910.153 | AJ22: =+AI22-AI21 -> 1045.2936 | AL22: Rendimiento | AM22: =G12 -> 8497.054 | AN22: =+AN21 -> #REF! | AO22: =+AO21 -> #REF! | AP22: =+AP21 -> #REF! | AQ22: =+(AM22*AN22*24*$AS$20/1000000)*AO22*AP22 -> #REF! | AR22: =+AQ22-AQ21 -> #REF!
A23: 26.470502 | B23: Ley Conc. Cu | C23: % | D23: =IFERROR(Real!M40,0) -> 25.931627 | E23: ='R+P'!N132 -> 26.849886 | F23: =+'Comparacion (Sin BM)'!Q37 -> 26.406498 | G23: =+'Comparacion (Sin BM)'!R37 -> 26.777705 | H23: =F23-G23 -> -0.37120691 | I23: =H23/G23 -> -0.013862536 | J23: =+BDGT!$G$33 -> 27.918697 | K23: =+F23-J23 -> -1.5121988 | L23: =+K23/J23 -> -0.054164377 | M23: =+'0+12'!$G$36 -> 28.260327 | N23: =F23-M23 -> -1.8538282 | O23: =N23/M23 -> -0.065598257 | P23: ='Comparacion (Sin BM)'!Q113 -> 26.736302 | Q23: =+'0+12'!$T$36 -> 27.034106 | R23: =P23-Q23 -> -0.29780419 | S23: =R23/Q23 -> -0.01101587 | W23: =+BDGT!$T$33 -> 27.974256 | X23: =P23-W23 -> -1.2379543 | Y23: =X23/W23 -> -0.044253342 | AA23: =+'Comparacion (Sin BM)'!AF76 -> 26.389507 | AB23: =+'ST Original'!HJ39 -> 27.143541 | AE23: Ley Cu,% | AF23: =AF22 -> 5857.1988 | AG23: =G20 -> 0.53544933 | AH23: =AH21 -> 90.433416 | AI23: =+AF23*AG23*AH23/10 -> 28362.028 | AJ23: =+AI23-AI22 -> -1548.1256 | AL23: C.M. | AM23: =AM22 -> 8497.054 | AN23: =G16 -> 92.650689 | AO23: =+AO22 -> #REF! | AP23: =+AP22 -> #REF! | AQ23: =+(AM23*AN23*24*$AS$20/1000000)*AO23*AP23 -> #REF! | AR23: =+AQ23-AQ22 -> #REF!
AE24: RCu, % | AF24: =AF22 -> 5857.1988 | AG24: =AG23 -> 0.53544933 | AH24: =G21 -> 90.294153 | AI24: =+AF24*AG24*AH24/10 -> 28318.352 | AJ24: =+AI24-AI23 -> -43.676125 | AL24: Ley Cu,% | AM24: =AM22 -> 8497.054 | AN24: =AN23 -> 92.650689 | AO24: =G20 -> 0.53544933 | AP24: =+AP23 -> #REF! | AQ24: =+(AM24*AN24*24*$AS$20/1000000)*AO24*AP24 -> #REF! | AR24: =+AQ24-AQ23 -> #REF!
A25: 174.76501 | B25: Ley Alim. Mo | C25: ppm | D25: =IFERROR(Real!R40,0) -> 209.05586 | E25: ='R+P'!S132 -> 176.69027 | F25: =+'Comparacion (Sin BM)'!Q39 -> 192.88224 | G25: =+'Comparacion (Sin BM)'!R39 -> 171.18629 | H25: =F25-G25 -> 21.695952 | I25: =H25/G25 -> 0.12673884 | J25: =+BDGT!$G$35 -> 216.46397 | K25: =+F25-J25 -> -23.581723 | L25: =+K25/J25 -> -0.10894064 | M25: =+'0+12'!$G$38 -> 213.48422 | N25: =F25-M25 -> -20.601981 | O25: =N25/M25 -> -0.096503529 | P25: ='Comparacion (Sin BM)'!Q115 -> 192.66736 | Q25: =+'0+12'!$T$38 -> 195.69438 | R25: =P25-Q25 -> -3.0270206 | S25: =R25/Q25 -> -0.015468102 | W25: =+BDGT!$T$35 -> 197.52628 | X25: =P25-W25 -> -4.8589203 | Y25: =X25/W25 -> -0.024598855 | AA25: =+'Comparacion (Sin BM)'!AF74 -> 190.92613 | AB25: =+'ST Original'!HO39 -> 151.37563 | AE25: PM | AF25: =AF22 -> 5857.1988 | AG25: =AG23 -> 0.53544933 | AH25: =AH24 -> 90.294153 | AI25: =+AF25*AG25*AH25/10 -> 28318.352 | AJ25: =+SUM(AJ21:AJ24) -> 28318.352 | AL25: RCu, % | AM25: =AM22 -> 8497.054 | AN25: =AN23 -> 92.650689 | AO25: =AO24 -> 0.53544933 | AP25: =G21 -> 90.294153 | AQ25: =+(AM25*AN25*24*$AS$20/1000000)*AO25*AP25 -> 13245.681 | AR25: =+AQ25-AQ24 -> #REF!
A26: 74.576476 | B26: Rec. Mo Global | C26: % | D26: =IFERROR(Real!U40,0) -> 81.170583 | E26: ='R+P'!V132 -> 80.025725 | F26: =+'Comparacion (Sin BM)'!Q40 -> 80.646505 | G26: =+'Comparacion (Sin BM)'!R40 -> 80.579357 | H26: =F26-G26 -> 0.067148601 | I26: =H26/G26 -> 0.00083332262 | J26: =+BDGT!$G$36 -> 83.94117 | K26: =+F26-J26 -> -3.2946651 | L26: =+K26/J26 -> -0.039249692 | M26: =+'0+12'!$G$39 -> 83.998134 | N26: =F26-M26 -> -3.3516283 | O26: =N26/M26 -> -0.039901224 | P26: ='Comparacion (Sin BM)'!Q116 -> 80.026351 | Q26: =+'0+12'!$T$39 -> 82.944036 | R26: =P26-Q26 -> -2.9176847 | S26: =R26/Q26 -> -0.035176546 | W26: =+BDGT!$T$36 -> 83.619091 | X26: =P26-W26 -> -3.59274 | Y26: =X26/W26 -> -0.042965547 | AA26: =+'ST Original'!FU39 -> 80.836534 | AB26: =+'ST Original'!HR39 -> 80.253822 | AI26: =SUM(AJ22:AJ24) -> -546.50813 | AL26: PM | AM26: =AM22 -> 8497.054 | AN26: =AN23 -> 92.650689 | AO26: =AO24 -> 0.53544933 | AP26: =AP25 -> 90.294153 | AQ26: =+(AM26*AN26*24*$AS$20/1000000)*AO26*AP26 -> 13245.681 | AR26: =SUM(AR21:AR25) -> #REF!
A27: 1323.5879 | B27: Rec. Mo Colectiva | C27: % | F27: =+'Comparacion (Sin BM)'!Q41 -> 89.806766 | G27: ='Comparacion (Sin BM)'!R41 -> 91.633787 | H27: =F27-G27 -> -1.8270206 | I27: =H27/G27 -> -0.019938285 | J27: =BDGT!$G$37 -> 93.8379 | K27: =+F27-J27 -> -4.0311342 | L27: =K27/J27 -> -0.042958487 | M27: =+J27 -> 93.8379 | N27: =+G27-M27 -> -2.2041136 | O27: =N27/M27 -> -0.023488522 | P27: ='Comparacion (Sin BM)'!Q117 -> 90.314191 | W27: =BDGT!$F$37 -> 94.176552 | X27: =P27-W27 -> -3.8623613 | Y27: =X27/W27 -> -0.041011921
B28: Rec. Mo Selectiva | C28: % | F28: =+'Comparacion (Sin BM)'!Q42 -> 89.800033 | G28: ='Comparacion (Sin BM)'!R42 -> 87.936295 | H28: =F28-G28 -> 1.863738 | I28: =H28/G28 -> 0.021194183 | J28: =BDGT!$G$38 -> 89.453377 | K28: =+F28-J28 -> 0.34665602 | L28: =K28/J28 -> 0.0038752704 | M28: =+J28 -> 89.453377 | N28: =+G28-M28 -> -1.5170819 | O28: =N28/M28 -> -0.016959471 | P28: ='Comparacion (Sin BM)'!Q118 -> 88.630655 | W28: =BDGT!$T$38 -> 89.277431 | X28: =P28-W28 -> -0.64677519 | Y28: =X28/W28 -> -0.0072445543
A29: 26.762132 | B29: Conc Mo Producido | C29: ton | D29: =Real!W40 -> 1701.5102 | E29: ='R+P'!X132 -> 824.56652 | F29: =+'Comparacion (Sin BM)'!Q43 -> 2526.0767 | G29: =+'Comparacion (Sin BM)'!R43 -> 1615.8935 | H29: =F29-G29 -> 910.18323 | I29: =H29/G29 -> 0.56326932 | J29: =BDGT!$G$39*1000 -> 1963.6493 | K29: =+F29-J29 -> 562.42744 | L29: =K29/J29 -> 0.2864195 | M29: =+'0+12'!$G$42*1000 -> 1877.0785 | N29: =F29-M29 -> 648.99823 | O29: =N29/M29 -> 0.34574911 | P29: ='Comparacion (Sin BM)'!$Q$119 -> 4717.8739 | Q29: ='0+12'!$T$42*1000 -> 4455.6345 | R29: =P29-Q29 -> 262.23937 | S29: =R29/Q29 -> 0.058855674 | W29: =BDGT!$T$39*1000 -> 4646.143 | X29: =P29-W29 -> 71.730885 | Y29: =X29/W29 -> 0.015438803 | AA29: =+'ST Original'!FW39 -> 905.60737 | AB29: =+'ST Original'!HT39 -> 710.28614
A30: 1684.0909
B31: As Alim. | C31: ppm | D31: =IFERROR(Real!AE40,0) -> 18.100498 | E31: ='R+P'!BA132 -> 23.35637 | F31: =+'Comparacion (Sin BM)'!Q46 -> 20.726944 | G31: =+'Comparacion (Sin BM)'!R46 -> 27.445147 | H31: =F31-G31 -> -6.7182024 | I31: =H31/G31 -> -0.24478654 | J31: =BDGT!$G$54 -> 34.290586 | K31: =+F31-J31 -> -13.563642 | L31: =K31/J31 -> -0.39555002 | M31: =+'0+12'!$G$57 -> 31.625552 | N31: =F31-M31 -> -10.898607 | O31: =N31/M31 -> -0.34461398 | P31: =+'Comparacion (Sin BM)'!Q122 -> 11.311253 | Q31: =+'0+12'!$T$57 -> 27.290095 | R31: =P31-Q31 -> -15.978843 | S31: =R31/Q31 -> -0.58551802 | W31: =BDGT!$T$54 -> 29.280537 | X31: =P31-W31 -> -17.969284 | Y31: =X31/W31 -> -0.61369381 | AA31: =+'ST Original'!GG39 -> 28.042765
B32: As Conc. | C32: ppm | D32: =IFERROR(Real!AF40,0) -> 887.39033 | E32: ='R+P'!BB132 -> 1064.3477 | F32: =+'Comparacion (Sin BM)'!Q47 -> 978.90256 | G32: =+'Comparacion (Sin BM)'!R47 -> 1264.0914 | H32: =F32-G32 -> -285.18884 | I32: =H32/G32 -> -0.22560777 | J32: =BDGT!$G$55 -> 1371.3752 | K32: =+F32-J32 -> -392.47265 | L32: =K32/J32 -> -0.28618911 | M32: =+'0+12'!$G$58 -> 1415.2434 | N32: =F32-M32 -> -436.34087 | O32: =N32/M32 -> -0.30831507 | P32: =+'Comparacion (Sin BM)'!Q123 -> 631.80418 | Q32: =+'0+12'!$T$58 -> 1275.7294 | R32: =P32-Q32 -> -643.92523 | S32: =R32/Q32 -> -0.50475063 | W32: =BDGT!$T$55 -> 1181.6241 | X32: =P32-W32 -> -549.8199 | Y32: =X32/W32 -> -0.46530864 | AA32: =+'ST Original'!GH39 -> 1261.9244
B33: Rendimiento (L1L2L3) | C33: Tph | F33: =+'R+P'!BF39 -> 6716.4507 | G33: =+'ST Original'!BR39 -> 6726.6134 | H33: =F33-G33 -> -10.162756 | I33: =H33/G33 -> -0.0015108281 | J33: =+BDGT!H15 -> 6700.0482 | K33: =+G33-J33 -> 26.565209 | L33: =+K33/J33 -> 0.003964928 | P33: ='Comparacion (Sin BM)'!Q106 -> 8426.8957 | Q33: =+BDGT!$T$13 -> 168.77709 | R33: =P33-Q33 -> 8258.1186 | S33: =R33/Q33 -> 48.929144 | U33: =P33-T33 -> 8426.8957
B34: Rendimiento (L4) | C34: Tph | F34: =+'R+P'!BG39 -> 1895.7866 | G34: =+'ST Original'!BS39 -> 1748.4423 | H34: =F34-G34 -> 147.34426 | I34: =H34/G34 -> 0.084271729 | J34: =+BDGT!N16 -> 1812 | K34: =+G34-J34 -> -63.557656 | L34: =+K34/J34 -> -0.035075969 | P34: ='Comparacion (Sin BM)'!Q106 -> 8426.8957 | Q34: =+BDGT!$T$13 -> 168.77709 | R34: =P34-Q34 -> 8258.1186 | S34: =R34/Q34 -> 48.929144 | U34: =P34-T34 -> 8426.8957
B35: Mineral Duro | C35: % | F35: =+'Comparacion (Sin BM)'!Q30 -> 67.341178 | G35: =+'Comparacion (Sin BM)'!R30 -> 73.985882 | H35: =F35-G35 -> -6.6447044 | I35: =H35/G35 -> -0.089810437 | J35: =+BDGT!$E$17 -> 0 | K35: =+G35-J35 -> 73.985882 | L35: =+K35/J35 -> #DIV/0! | M35: =+'BDGT ORI'!M23 -> 36.10178 | N35: =+G35-M35 -> 37.884103 | O35: =N35/M35 -> 1.0493694 | P35: ='Comparacion (Sin BM)'!Q107 -> 0 | Q35: =+BDGT!$T$17 -> 0 | R35: =P35-Q35 -> 0 | S35: =R35/Q35 -> #DIV/0! | T35: =+'0+12'!$T$23 -> 0 | U35: =P35-T35 -> 0 | V35: =U35/T35 -> #DIV/0!
B36: CM (L1L2L3) | C36: % | F36: ='R+P'!H39 -> 100.68924 | G36: =+'ST Original'!H39 -> 93.142816 | H36: =F36-G36 -> 7.5464218 | I36: =H36/G36 -> 0.081019902 | U36: =P36-T36 -> 0
B37: CM (L4) | C37: % | F37: =+'ST Original'!I39 -> 98.723713 | G37: =+'ST Original'!I39 -> 98.723713 | H37: =F37-G37 -> 0 | I37: =H37/G37 -> 0 | U37: =P37-T37 -> 0
D39: =+D5*0.9644-D6 -> -0.085997504 | F39: =F6/0.9644-F5 -> 0.018415308 | G39: =G6/0.96-G5 -> 0.046018429 | J39: =J6/0.9644-J5 -> -0.042698113
B40: =2600*0.91 -> 2366 | D40: =D39/(D23/100) -> -0.33163173 | F40: =F39/(F23/100) -> 0.06973779 | G40: =G39/(G23/100) -> 0.17185352 | J40: =J39/(J23/100) -> -0.15293734
B41: 605
A42: 1 | B42: Waterfall CuFFP / Real + Proy. vs PM (Cierre de mes)
C43: CM % | D43: TPH | E43: Ley Cu | F43: Rec Cu | G43: Inv. | H43: Cu Fino | I43: DIF | J43: CuFFP | AC43: Rec Cu | AD43: TMF | AE43: dif | AH43: TPH | AI43: CM | AJ43: Ley Cu | AK43: Rec Cu | AL43: TMF | AM43: dif
B44: PM | C44: =+G16 -> 92.650689 | D44: =+G12 -> 8497.054 | E44: =+G20 -> 0.53544933 | F44: =+G21 -> 90.294153 | G44: =+(G6-G5*$C51)*1000 -> -12.459012 | H44: =+C44*24*D44*E44*F44*($D$2+$E$2)/1000000 -> 28318.352 | I44: =H44 -> 28318.352 | J44: =+G6*1000 -> 27229.795 | AC44: =+#REF! -> #REF! | AD44: =+X46*Y46*AC44/10 -> #REF! | AE44: =+AD44 -> #REF! | AG44: OL 6+6 | AH44: =M12 -> 8052.7228 | AI44: =M16 -> 94.409795 | AJ44: =M20 -> 0.56467653 | AK44: =M21 -> 90.433416 | AL44: =+(AH44*AI44*24*$AS$20/1000000)*AJ44*AK44 -> 13510.385 | AM44: =+AL44 -> 13510.385 | AN44: 31 | AO44: días/mes
B45: CM % | C45: =+F16 -> 92.32423 | D45: =D44 -> 8497.054 | E45: =E44 -> 0.53544933 | F45: =F44 -> 90.294153 | G45: =+G44 -> -12.459012 | H45: =+C45*24*D45*E45*F45*($D$2+$E$2)/1000000 -> 28218.571 | I45: =H45-H44 -> -99.78084 | J45: =+I45*$C$51 -> -95.989168 | AB45: 15 | AC45: =AC44 -> #REF! | AD45: =+X47*Y47*AC45/10 -> #REF! | AE45: =+AD45-AD44 -> #REF! | AG45: Rendimiento | AH45: =F12 -> 8494.565 | AI45: =+AI44 -> 94.409795 | AJ45: =+$AJ$44 -> 0.56467653 | AK45: =+$AK$44 -> 90.433416 | AL45: =+(AH45*AI45*24*$AS$20/1000000)*AJ45*AK45 -> 14251.682 | AM45: =+AL45-AL44 -> 741.29687
B46: TPH | C46: =C45 -> 92.32423 | D46: =+F12 -> 8494.565 | E46: =E44 -> 0.53544933 | F46: =F44 -> 90.294153 | G46: =G44 -> -12.459012 | H46: =+C46*24*D46*E46*F46*($D$2+$E$2)/1000000 -> 28210.305 | I46: =H46-H45 -> -8.2658632 | J46: =+I46*$C$51 -> -7.9517604 | AB46: =7+24*5 -> 127 | AC46: =AC44 -> #REF! | AD46: =+X48*Y48*AC46/10 -> #REF! | AE46: =+AD46-AD45 -> #REF! | AG46: C.M. | AH46: =AH45 -> 8494.565 | AI46: =F16 -> 92.32423 | AJ46: =+$AJ$44 -> 0.56467653 | AK46: =+$AK$44 -> 90.433416 | AL46: =+(AH46*AI46*24*$AS$20/1000000)*AJ46*AK46 -> 13936.854 | AM46: =+AL46-AL45 -> -314.82754
B47: Ley Cu,% | C47: =C45 -> 92.32423 | D47: =D46 -> 8494.565 | E47: =+F20 -> 0.51875622 | F47: =F44 -> 90.294153 | G47: =G44 -> -12.459012 | H47: =+C47*24*D47*E47*F47*($D$2+$E$2)/1000000 -> 27330.824 | I47: =H47-H46 -> -879.48136 | J47: =+I47*$C$51 -> -846.06107 | AC47: =F21 -> 90.397219 | AD47: =+X49*Y49*AC47/10 -> 0 | AE47: =+AD47-AD46 -> #REF! | AG47: Ley Cu,% | AH47: =AH45 -> 8494.565 | AI47: =AI46 -> 92.32423 | AJ47: =F20 -> 0.51875622 | AK47: =+$AK$44 -> 90.433416 | AL47: =+(AH47*AI47*24*$AS$20/1000000)*AJ47*AK47 -> 12803.489 | AM47: =+AL47-AL46 -> -1133.3652
B48: RCu, % | C48: =C45 -> 92.32423 | D48: =D46 -> 8494.565 | E48: =E47 -> 0.51875622 | F48: =+F21 -> 90.397219 | G48: =G44 -> -12.459012 | H48: =+C48*24*D48*E48*F48*($D$2+$E$2)/1000000 -> 27362.02 | I48: =H48-H47 -> 31.196656 | J48: =+I48*$C$51 -> 30.011184 | AC48: =AC47 -> 90.397219 | AD48: =+X50*Y50*AC48/10 -> 0 | AE48: =+SUM(AE44:AE47) -> #REF! | AG48: RCu, % | AH48: =AH45 -> 8494.565 | AI48: =AI46 -> 92.32423 | AJ48: =AJ47 -> 0.51875622 | AK48: =F21 -> 90.397219 | AL48: =+(AH48*AI48*24*$AS$20/1000000)*AJ48*AK48 -> 12798.364 | AM48: =+AL48-AL47 -> -5.1247578
B49: Inv. | C49: =C45 -> 92.32423 | D49: =D46 -> 8494.565 | E49: =E47 -> 0.51875622 | F49: =F48 -> 90.397219 | G49: =+(F6-F5*$C51)*1000 -> 83.428572 | H49: =C49*D49*24*31/100*E49/100*F49/100+G49 -> 27445.449 | I49: =H49-H48+G44 -> 70.96956 | J49: =+G49 -> 83.428572 | AG49: PM | AH49: =AH45 -> 8494.565 | AI49: =AI46 -> 92.32423 | AJ49: =AJ47 -> 0.51875622 | AK49: =AK48 -> 90.397219 | AL49: =+(AH49*AI49*24*$AS$20/1000000)*AJ49*AK49 -> 12798.364 | AM49: =SUM(AM44:AM48) -> 12798.364
B50: CuFFP Real | C50: =C45 -> 92.32423 | D50: =D46 -> 8494.565 | E50: =E47 -> 0.51875622 | F50: =F48 -> 90.397219 | G50: =G49 -> 83.428572 | H50: =+C50*24*D50*E50*F50*($D$2+$E$2)/1000000 -> 27362.02 | I50: =+SUM(I44:I49) -> 27432.99 | J50: =+SUM(J44:J49)-G44 -> 26405.692
B51: Pagabilidad ST | C51: =+'ST Original'!$AV$8 -> 0.962
G53: Ajuste Fino | H53: -9
A54: 2 | B54: Waterfall CuFFP / Real MTD vs PM (MTD)
C55: CM % | D55: TPH | E55: Ley Cu | F55: Rec Cu | G55: Inv. | H55: Cu Fino | I55: DIF | J55: CuFFP
B56: PM | C56: =+AA16 -> 88.216548 | D56: =+AA12 -> 8414.2412 | E56: =+AA20 -> 0.51107742 | F56: =+AA21 -> 90.302073 | G56: =+(AA$6-AA$5*$C$63)*1000 -> -911.32383 | H56: =+C56*24*D56*E56*F56*($D$2)/1000000+$H$53 -> 13556.775 | I56: =H56 -> 13556.775 | J56: =+AA6*1000 -> 12114.235 | AA56: =+J56 -> 12114.235
B57: CM % | C57: =+D16 -> 88.117328 | D57: =D56 -> 8414.2412 | E57: =E56 -> 0.51107742 | F57: =F56 -> 90.302073 | G57: =+G56 -> -911.32383 | H57: =+C57*24*D57*E57*F57*($D$2)/1000000 -> 13550.517 | I57: =H57-H56 -> -6.2579847 | J57: =+I57*$C$51 -> -6.0201813 | AA57: =+J57+J58 -> -81.604127
B58: TPH | C58: =C57 -> 88.117328 | D58: =+D12 -> 8365.4531 | E58: =E56 -> 0.51107742 | F58: =F56 -> 90.302073 | G58: =G56 -> -911.32383 | H58: =+C58*24*D58*E58*F58*($D$2)/1000000 -> 13471.948 | I58: =H58-H57 -> -78.56959 | J58: =+I58*$C$51 -> -75.583945 | AA58: =+J59 -> -522.63682
B59: Ley Cu,% | C59: =C57 -> 88.117328 | D59: =D58 -> 8365.4531 | E59: =+D20 -> 0.49046726 | F59: =F56 -> 90.302073 | G59: =G56 -> -911.32383 | H59: =+C59*24*D59*E59*F59*($D$2)/1000000 -> 12928.666 | I59: =H59-H58 -> -543.28151 | J59: =+I59*$C$51 -> -522.63682 | AA59: =+J60 -> 43.951032
B60: RCu, % | C60: =C57 -> 88.117328 | D60: =D58 -> 8365.4531 | E60: =E59 -> 0.49046726 | F60: =+D21 -> 90.621182 | G60: =G56 -> -911.32383 | H60: =+C60*24*D60*E60*F60*($D$2)/1000000 -> 12974.353 | I60: =H60-H59 -> 45.687144 | J60: =+I60*$C$51 -> 43.951032 | AA60: =+J61 -> 117.13595
B61: Inv. | C61: =C57 -> 88.117328 | D61: =D58 -> 8365.4531 | E61: =E59 -> 0.49046726 | F61: =F60 -> 90.621182 | G61: =+(D6-D5*$C63)*1000 -> 117.13595 | H61: =+C61*24*D61*E61*F61*($D$2)/1000000 -> 12974.353 | I61: =H61-H60+G56 -> -911.32383 | J61: =+G61 -> 117.13595
B62: CuFFP Real | C62: =C57 -> 88.117328 | D62: =D58 -> 8365.4531 | E62: =E59 -> 0.49046726 | F62: =F60 -> 90.621182 | G62: =G61 -> 117.13595 | H62: =+C62*24*D62*E62*F62*($D$2+$E$2)/1000000 -> 24376.058 | I62: =+SUM(I56:I61) -> 12063.029 | J62: =+SUM(J56:J61) -> 11671.081
B63: Pagabilidad ST | C63: =+'ST Original'!$AV$8 -> 0.962
AC64: Rec Cu | AD64: TMF | AE64: dif | AH64: TPH | AI64: CM | AJ64: Ley Cu | AK64: Rec Cu | AL64: TMF | AM64: dif
G65: Ajuste Fino | H65: -8 | AC65: =+$W$21 -> 89.998005 | AD65: =+X121*Y121*AC65/10 -> 0 | AE65: =+AD65 -> 0 | AG65: BD Acum. | AH65: =W12 -> 8151.9777 | AI65: =W16 -> 86.3258 | AJ65: =Y121 -> 0 | AK65: =AC65 -> 89.998005 | AL65: =+(AH65*AI65*24*$AN$65/1000000)*AJ65*AK65 -> 0 | AM65: =+AL65 -> 0 | AN65: =BDGT!T5 -> 90 | AO65: días/mes
A66: 3 | B66: Waterfall CuFFP / Proyección Resto del mes vs PM (Proyectado vs ST) | AC66: =AC65 -> 89.998005 | AD66: =+X122*Y122*AC66/10 -> 0 | AE66: =+AD66-AD65 -> 0 | AG66: Rendimiento | AH66: =P12 -> 8424.7006 | AI66: =+AI65 -> 86.3258 | AJ66: =AJ65 -> 0 | AK66: =AK65 -> 89.998005 | AL66: =+(AH66*AI66*24*$AN$65/1000000)*AJ66*AK66 -> 0 | AM66: =+AL66-AL65 -> 0
C67: CM % | D67: TPH | E67: Ley Cu | F67: Rec Cu | G67: Inv. | H67: Cu Fino | I67: DIF | J67: CuFFP | AC67: =AC65 -> 89.998005 | AD67: =+X123*Y123*AC67/10 -> 0 | AE67: =+AD67-AD66 -> 0 | AG67: C.M. | AH67: =AH66 -> 8424.7006 | AI67: =P16 -> 82.043161 | AJ67: =AJ65 -> 0 | AK67: =AK65 -> 89.998005 | AL67: =+(AH67*AI67*24*AN65/1000000)*AJ67*AK67 -> 0 | AM67: =+AL67-AL66 -> 0
B68: PM | C68: =+AB16 -> 97.936038 | D68: =+AB12 -> 8576.3314 | E68: =+AB20 -> 0.55990867 | F68: =+AB21 -> 90.286898 | G68: =+(AB$6-AB$5*$C$75)*1000 -> 867.43953 | H68: =+C68*24*D68*E68*F68*($D$2)/1000000+$H$65 -> 16806.393 | I68: =H68 -> 16806.393 | J68: =+AB6*1000 -> 15084.135 | AC68: =P21 -> 90.504839 | AD68: =+X124*Y124*AC68/10 -> 0 | AE68: =+AD68-AD67 -> 0 | AG68: Ley Cu,% | AH68: =AH66 -> 8424.7006 | AI68: =AI67 -> 82.043161 | AJ68: =P20 -> 0.51253836 | AK68: =AK65 -> 89.998005 | AL68: =+(AH68*AI68*24*AN65/1000000)*AJ68*AK68 -> 68866.795 | AM68: =+AL68-AL67 -> 68866.795
B69: CM % | C69: =+E16 -> 98.00225 | D69: =D68 -> 8576.3314 | E69: =E68 -> 0.55990867 | F69: =F68 -> 90.286898 | G69: =+G68 -> 867.43953 | H69: =+C69*24*D69*E69*F69*($D$2)/1000000 -> 16825.761 | I69: =H69-H68 -> 19.367797 | J69: =+I69*$C$51 -> 18.631821 | AC69: =AC68 -> 90.504839 | AD69: =+X125*Y125*AC69/10 -> 0 | AE69: =+SUM(AE65:AE68) -> 0 | AG69: RCu, % | AH69: =AH66 -> 8424.7006 | AI69: =AI67 -> 82.043161 | AJ69: =AJ68 -> 0.51253836 | AK69: =P21 -> 90.504839 | AL69: =+(AH69*AI69*24*AN65/1000000)*AJ69*AK69 -> 69254.626 | AM69: =+AL69-AL68 -> 387.83144
B70: TPH | C70: =C69 -> 98.00225 | D70: =+E12 -> 8549.4495 | E70: =E68 -> 0.55990867 | F70: =F68 -> 90.286898 | G70: =G68 -> 867.43953 | H70: =+C70*24*D70*E70*F70*($D$2)/1000000 -> 16773.022 | I70: =H70-H69 -> -52.739014 | J70: =+I70*$C$51 -> -50.734932 | AG70: Real + Proy. Acum. | AH70: =AH66 -> 8424.7006 | AI70: =AI67 -> 82.043161 | AJ70: =AJ68 -> 0.51253836 | AK70: =AK69 -> 90.504839 | AL70: =+(AH70*AI70*24*AN65/1000000)*AJ70*AK70 -> 69254.626 | AM70: =SUM(AM65:AM69) -> 69254.626
B71: Ley Cu,% | C71: =C69 -> 98.00225 | D71: =D70 -> 8549.4495 | E71: =+E20 -> 0.54707727 | F71: =F68 -> 90.286898 | G71: =G68 -> 867.43953 | H71: =+C71*24*D71*E71*F71*($D$2)/1000000 -> 16388.635 | I71: =H71-H70 -> -384.38648 | J71: =+I71*$C$51 -> -369.77979
B72: RCu, % | C72: =C69 -> 98.00225 | D72: =D70 -> 8549.4495 | E72: =E71 -> 0.54707727 | F72: =+E21 -> 90.196204 | G72: =G68 -> 867.43953 | H72: =+C72*24*D72*E72*F72*($D$2)/1000000 -> 16372.173 | I72: =H72-H71 -> -16.462548 | J72: =+I72*$C$51 -> -15.836971
B73: Inv. | C73: =C69 -> 98.00225 | D73: =D70 -> 8549.4495 | E73: =E71 -> 0.54707727 | F73: =F72 -> 90.196204 | G73: =+(E6-E5*$C75)*1000 -> 0.73892745 | H73: =+C73*24*D73*E73*F73*($D$2)/1000000 -> 16372.173 | I73: =H73-H72+G68 -> 867.43953 | J73: =+G73 -> 0.73892745
B74: CuFFP Real | C74: =C69 -> 98.00225 | D74: =D70 -> 8549.4495 | E74: =E71 -> 0.54707727 | F74: =F72 -> 90.196204 | G74: =G73 -> 0.73892745 | H74: =+C74*24*D74*E74*F74*($D$2+$E$2)/1000000 -> 30759.84 | I74: =+SUM(I68:I73) -> 17239.612 | J74: =+SUM(J68:J73)-G68 -> 13799.714
B75: Pagabilidad ST | C75: =+'ST Original'!$AV$8 -> 0.962
G77: Ajuste Fino | H77: -15
A78: 4 | B78: Waterfall CuFFP / R+P VS BDGT FEBRERO
C79: CM % | D79: TPH | E79: Ley Cu | F79: Rec Cu | G79: Inv. | H79: Cu Fino | I79: DIF | J79: CuFFP
B80: BDGT | C80: =+J16 -> 95.068132 | D80: =+J12 -> 8256.2174 | E80: =+J20 -> 0.56048277 | F80: =+J21 -> 90.234525 | G80: =+(J$6-J$5*$C$75)*1000 -> 29.65619 | H80: =+C80*24*D80*E80*F80*($D$2+$E$2)/1000000+$H$77 -> 29519.119 | I80: =H80 -> 29519.119 | J80: =+J6*1000 -> 28422.385
B81: CM % | C81: =+F16 -> 92.32423 | D81: =D80 -> 8256.2174 | E81: =E80 -> 0.56048277 | F81: =F80 -> 90.234525 | G81: =+G80 -> 29.65619 | H81: =+C81*24*D81*E81*F81*($D$2+$E$2)/1000000 -> 28681.691 | I81: =H81-H80 -> -837.42797 | J81: =+I81*$C$51 -> -805.60571
B82: TPH | C82: =C81 -> 92.32423 | D82: =+F12 -> 8494.565 | E82: =E80 -> 0.56048277 | F82: =F80 -> 90.234525 | G82: =G80 -> 29.65619 | H82: =+C82*24*D82*E82*F82*($D$2+$E$2)/1000000 -> 29509.699 | I82: =H82-H81 -> 828.00763 | J82: =+I82*$C$51 -> 796.54334
B83: Ley Cu,% | C83: =C81 -> 92.32423 | D83: =D82 -> 8494.565 | E83: =+F20 -> 0.51875622 | F83: =F80 -> 90.234525 | G83: =G80 -> 29.65619 | H83: =+C83*24*D83*E83*F83*($D$2+$E$2)/1000000 -> 27312.775 | I83: =H83-H82 -> -2196.9238 | J83: =+I83*$C$51 -> -2113.4407
B84: RCu, % | C84: =C81 -> 92.32423 | D84: =D82 -> 8494.565 | E84: =E83 -> 0.51875622 | F84: =+F21 -> 90.397219 | G84: =G80 -> 29.65619 | H84: =+C84*24*D84*E84*F84*($D$2+$E$2)/1000000 -> 27362.02 | I84: =H84-H83 -> 49.245374 | J84: =+I84*$C$51 -> 47.374049
B85: Inv. | C85: =C81 -> 92.32423 | D85: =D82 -> 8494.565 | E85: =E83 -> 0.51875622 | F85: =F84 -> 90.397219 | G85: =+(F6-F5*$C75)*1000 -> 83.428572 | H85: =+C85*24*D85*E85*F85*($D$2+$E$2)/1000000 -> 27362.02 | I85: =H85-H84+G80 -> 29.65619 | J85: =+G85 -> 83.428572
B86: CuFFP Real | C86: =C81 -> 92.32423 | D86: =D82 -> 8494.565 | E86: =E83 -> 0.51875622 | F86: =F84 -> 90.397219 | G86: =G85 -> 83.428572 | H86: =+C86*24*D86*E86*F86*($D$2+$E$2)/1000000 -> 27362.02 | I86: =+SUM(I80:I85) -> 27391.676 | J86: =+SUM(J80:J85)-G80 -> 26401.028
B87: Pagabilidad BDGT FEBRERO | C87: =+BDGT!F59 -> 0.964
C107: TPH | D107: CM | E107: Ley Cu | F107: Rec Cu | G107: TMF | H107: dif
B108: PM | C108: =G12 -> 8497.054 | D108: =G16 -> 92.650689 | E108: =G20 -> 0.53544933 | F108: =G21 -> 90.294153 | G108: =+(C108*D108*24*$AS$20/1000000)*E108*F108 -> 13245.681 | H108: =+G108 -> 13245.681
B109: Rendimiento | C109: =F12 -> 8494.565 | D109: =+D108 -> 92.650689 | E109: =E108 -> 0.53544933 | F109: =F108 -> 90.294153 | G109: =+(C109*D109*24*$AS$20/1000000)*E109*F109 -> 13241.801 | H109: =+G109-G108 -> -3.879962
B110: C.M. | C110: =C109 -> 8494.565 | D110: =F16 -> 92.32423 | E110: =E108 -> 0.53544933 | F110: =F108 -> 90.294153 | G110: =+(C110*D110*24*$AS$20/1000000)*E110*F110 -> 13195.143 | H110: =+G110-G109 -> -46.658012
B111: Ley Cu,% | C111: =C109 -> 8494.565 | D111: =D110 -> 92.32423 | E111: =F20 -> 0.51875622 | F111: =F108 -> 90.294153 | G111: =+(C111*D111*24*$AS$20/1000000)*E111*F111 -> 12783.772 | H111: =+G111-G110 -> -411.37031
B112: RCu, % | C112: =C109 -> 8494.565 | D112: =D110 -> 92.32423 | E112: =E111 -> 0.51875622 | F112: =F21 -> 90.397219 | G112: =+(C112*D112*24*$AS$20/1000000)*E112*F112 -> 12798.364 | H112: =+G112-G111 -> 14.591984
B113: Real + Proy. | C113: =C109 -> 8494.565 | D113: =D110 -> 92.32423 | E113: =E111 -> 0.51875622 | F113: =F112 -> 90.397219 | G113: =+(C113*D113*24*$AS$20/1000000)*E113*F113 -> 12798.364 | H113: =SUM(H108:H112) -> 12798.364
AG117: Rendimiento | AH117: CM % | AI117: Ley Cu | AJ117: Rec Cu | AK117: CuFFP-CuFP | AL117: TMF | AM117: DIF
AE118: OL 6+6 | AG118: =+M12 -> 8052.7228 | AH118: =+M16 -> 94.409795 | AI118: =+M20 -> 0.56467653 | AJ118: =+M21 -> 90.433416 | AK118: =+($M$6-$M$5)*1000 -> -632.52841 | AL118: =AG118*AH118*24*$AS$20/100*AI118/100*AJ118/100+AK118 -> 12877.857 | AM118: =AL118 -> 12877.857
AE119: Rendimiento | AG119: =+$G$12 -> 8497.054 | AH119: =AH118 -> 94.409795 | AI119: =AI118 -> 0.56467653 | AJ119: =AJ118 -> 90.433416 | AK119: =AK118 -> -632.52841 | AL119: =AG119*AH119*24*$AS$20/100*AI119/100*AJ119/100+AK119 -> 13623.329 | AM119: =AL119-AL118 -> 745.47274
AE120: CM % | AG120: =AG119 -> 8497.054 | AH120: =+$G$16 -> 92.650689 | AI120: =AI118 -> 0.56467653 | AJ120: =AJ118 -> 90.433416 | AK120: =AK118 -> -632.52841 | AL120: =AG120*AH120*24*$AS$20/100*AI120/100*AJ120/100+AK120 -> 13357.705 | AM120: =AL120-AL119 -> -265.62465
AE121: Ley Cu,% | AG121: =AG119 -> 8497.054 | AH121: =AH120 -> 92.650689 | AI121: =+$G$20 -> 0.53544933 | AJ121: =AJ118 -> 90.433416 | AK121: =AK118 -> -632.52841 | AL121: =AG121*AH121*24*$AS$20/100*AI121/100*AJ121/100+AK121 -> 12633.581 | AM121: =AL121-AL120 -> -724.12326
AE122: RCu, % | AG122: =AG119 -> 8497.054 | AH122: =AH120 -> 92.650689 | AI122: =AI121 -> 0.53544933 | AJ122: =+$G$21 -> 90.294153 | AK122: =AK118 -> -632.52841 | AL122: =AG122*AH122*24*$AS$20/100*AI122/100*AJ122/100+AK122 -> 12613.152 | AM122: =AL122-AL121 -> -20.429155
AE123: Inventarios | AG123: =AG119 -> 8497.054 | AH123: =AH120 -> 92.650689 | AI123: =AI121 -> 0.53544933 | AJ123: =AJ122 -> 90.294153 | AK123: =+($G$6-$G$5)*1000 -> -1088.5564 | AL123: =AG123*AH123*24*$AS$20/100*AI123/100*AJ123/100+AK123 -> 12157.124 | AM123: =AL123-AL122 -> -456.02796
AE124: PM | AG124: =AG119 -> 8497.054 | AH124: =AH120 -> 92.650689 | AI124: =AI121 -> 0.53544933 | AJ124: =AJ122 -> 90.294153 | AK124: =AK123 -> -1088.5564 | AM124: =+SUM(AM118:AM123) -> 12157.124
AM126: =AM124-AM118 -> -720.73229
X133: =+Z124 -> 0 | AG133: Rendimiento | AH133: CM % | AI133: Ley Cu | AJ133: Rec Cu | AK133: CuFFP-CuFP | AL133: TMF | AM133: DIF
AE134: PM | AG134: =+$G$12 -> 8497.054 | AH134: =+$G$16 -> 92.650689 | AI134: =+$G$20 -> 0.53544933 | AJ134: =+$G$21 -> 90.294153 | AK134: =+($G$6-$G$5)*1000 -> -1088.5564 | AL134: =AG134*AH134*24*$AS$20/100*AI134/100*AJ134/100+AK134 -> 12157.124 | AM134: =AL134 -> 12157.124
...

Sheet graf
E24: 1000
E26: STMG | F26: Stock pile, TMS Ac. | G26: TTO Planta, TMSD
D27: Día | E27: Transp. | F27: Acopio Pta | G27: Molido Total L1L2L3L4 | H27: Global | I27: Duro | J27: Ley Cab. | K27: Recup.Cu | L27: Ley Conc. | M27: duro | N27: RQD
E28: TMSD | F28: TMS Acum. | G28: TMSD | H28: % | I28: % | J28: Cu% | K28: Cu% | L28: Cu% | M28: %
D29: 46082.792 | E29: 178.58428 | F29: 681.32143 | G29: 98.057836 | H29: 91.25968 | I29: 62.156635 | J29: 0.57768798 | K29: 91.16282 | L29: 24.56 | M29: 62.156635 | N29: 80.621353
D30: 46083.792 | E30: 131.18715 | F30: 641.09304 | G30: 170.4369 | H30: 86.528962 | I30: 87.753082 | J30: 0.55229969 | K30: 92.159479 | L30: 30.560018 | M30: 87.753082 | N30: 92.158539
D31: 46084.792 | E31: 217.13384 | F31: 672.52956 | G31: 158.18682 | H31: 72.81 | I31: 87.695641 | J31: 0.53249797 | K31: 91.369202 | L31: 29.315374 | M31: 87.695641 | N31: 90.481964
D32: 46085.792 | E32: 132.73308 | F32: 646.13539 | G32: 156.04744 | H32: 71.738517 | I32: 60.02779 | J32: 0.50968564 | K32: 89.989232 | L32: 26.130492 | M32: 60.02779 | N32: 72.676598
D33: 46086.792 | E33: 194.2185 | F33: 675.7768 | G33: 164.03885 | H33: 72.81 | I33: 57.888607 | J33: 0.50356763 | K33: 89.94882 | L33: 23.372672 | M33: 57.888607 | N33: 71.63089
D34: 46087.792 | E34: 176.98069 | F34: 699.37618 | G34: 152.8785 | H34: 72.794432 | I34: 47.643745 | J34: 0.48054678 | K34: 90.812763 | L34: 22.585462 | M34: 47.643745 | N34: 61.548969
D35: 46088.792 | E35: 159.2836 | F35: 711.98206 | G35: 146.19827 | H35: 73.342621 | I35: 69.931587 | J35: 0.4906047 | K35: 91.99522 | L35: 26.337203 | M35: 69.931587 | N35: 75.483803
D36: 46089.792 | E36: 184.59308 | F36: 727.61628 | G36: 168.40505 | H36: 86.863706 | I36: 65.604004 | J36: 0.45280786 | K36: 89.26565 | L36: 24.68447 | M36: 65.604004 | N36: 74.989967
D37: 46090.792 | E37: 206.34555 | F37: 725.80846 | G37: 178.66145 | H37: 88.758792 | I37: 51.043968 | J37: 0.4921403 | K37: 90.683867 | L37: 23.722168 | M37: 51.043968 | N37: 66.209373
D38: 46091.792 | E38: 93.058756 | F38: 641.42626 | G38: 176.85918 | H38: 93.041992 | I38: 54.683159 | J38: 0.46573364 | K38: 90.64768 | L38: 24.57618 | M38: 54.683159 | N38: 63.325966
D39: 46092.792 | E39: 47.366838 | F39: 507.40133 | G39: 180.79912 | H39: 99.899183 | I39: 56.822449 | J39: 0.47658157 | K39: 90.386545 | L39: 26.432666 | M39: 56.822449 | N39: 76.92334
D40: 46093.792 | E40: 164.024 | F40: 486.20879 | G40: 184.08919 | H40: 96.073389 | I40: 43.550209 | J40: 0.50065835 | K40: 89.64925 | L40: 26.275215 | M40: 43.550209 | N40: 67.635406
... D59: 46112.792 | E59: 270 | F59: 720.64663 | G59: 306.3766 | H59: 97.887183 | I59: 69.378764 | J59: 0.57187199 | K59: 91.042828 | L59: 29.094089 | M59: 69.378764 | N59: 78.829289

Sheet BDGT ORI
I3: PROGRAMA DE PRODUCCIÓN 2025 | M3: bdgt original
D4: Unidad | F4: ='R+RP+B'!F4 -> 46023 | G4: ='R+RP+B'!G4 -> 46054 | H4: ='R+RP+B'!H4 -> 46082 | I4: ='R+RP+B'!I4 -> 46113 | J4: ='R+RP+B'!J4 -> 46143 | K4: ='R+RP+B'!K4 -> 46174 | L4: ='R+RP+B'!L4 -> 46204 | M4: ='R+RP+B'!M4 -> 46235 | ... Q4: ='R+RP+B'!Q4 -> 46357 | S4: Acum. | U4: Acumulado | V4: Acumulado
F5: BDGT | G5: BDGT | H5: BDGT | I5: BDGT | J5: BDGT | K5: BDGT | L5: BDGT | M5: BDGT | N5: BDGT | O5: BDGT | P5: BDGT | Q5: BDGT | R5: BDGT | U5: hasta este mas | V5: hasta el mes anterior
C6: Dia | F6: 31 | G6: 29 | H6: 31 | I6: 30 | J6: 31 | K6: 30 | L6: 31 | M6: 31 | N6: 30 | O6: 31 | P6: 30 | Q6: 31 | S6: =SUM(F6:Q6) -> 366 | U6: =IF(MONTH(Factores!$D$2)=1,SUM($F6:F6),IF(MONTH(Factores!$D$2)=2,SUM($F6:G6),IF(MONTH(Factores!$D$2)=3,SUM($F6:H6),IF(MONTH(Factores!$D$2)=4,SUM($F6:I6),IF(MONTH(Factores!$D$2)=5,SUM($F6:J6),IF(MONTH(Factores!$D$2)=6,SUM($F6:K6),IF(MONTH(Factores!$D$2)=7,SUM($F6:L6),IF(MONTH(Factores!$D$2)=8,SUM($F6:M6),IF(MONTH(Factores!$D$2)=9,SUM($F6:N6),IF(MONTH(Factores!$D$2)=10,SUM($F6:O6),IF(MONTH(Factores!$D$2)=11,SUM($F6:P6),IF(MONTH(Factores!$D$2)=12,SUM($F6:Q6))))))))))))) -> 91 | V6: =IF(MONTH(Factores!$D$2)=1,SUM($F6:F6),IF(MONTH(Factores!$D$2)=2,SUM($F6:F6),IF(MONTH(Factores!$D$2)=3,SUM($F6:G6),IF(MONTH(Factores!$D$2)=4,SUM($F6:H6),IF(MONTH(Factores!$D$2)=5,SUM($F6:I6),IF(MONTH(Factores!$D$2)=6,SUM($F6:J6),IF(MONTH(Factores!$D$2)=7,SUM($F6:K6),IF(MONTH(Factores!$D$2)=8,SUM($F6:L6),IF(MONTH(Factores!$D$2)=9,SUM($F6:M6),IF(MONTH(Factores!$D$2)=10,SUM($F6:N6),IF(MONTH(Factores!$D$2)=11,SUM($F6:O6),IF(MONTH(Factores!$D$2)=12,SUM($F6:P6))))))))))))) -> 60
C7: Toneladas de mineral Mined | D7: kton
C8: Mineral Baja Ley | D8: kton
C9: Esteril | D9: kton
C10: Stock | D10: kton
C11: Extracción | D11: Mton | S11: =SUM(F11:Q11) -> 0 | U11: =IF(MONTH(Factores!$D$2)=1,SUM($F11:F11),IF(MONTH(Factores!$D$2)=2,SUM($F11:G11),IF(MONTH(Factores!$D$2)=3,SUM($F11:H11),IF(MONTH(Factores!$D$2)=4,SUM($F11:I11),IF(MONTH(Factores!$D$2)=5,SUM($F11:J11),IF(MONTH(Factores!$D$2)=6,SUM($F11:K11),IF(MONTH(Factores!$D$2)=7,SUM($F11:L11),IF(MONTH(Factores!$D$2)=8,SUM($F11:M11),IF(MONTH(Factores!$D$2)=9,SUM($F11:N11),IF(MONTH(Factores!$D$2)=10,SUM($F11:O11),IF(MONTH(Factores!$D$2)=11,SUM($F11:P11),IF(MONTH(Factores!$D$2)=12,SUM($F11:Q11))))))))))))) -> 0 | V11: =IF(MONTH(Factores!$D$2)=1,SUM($F11:F11),IF(MONTH(Factores!$D$2)=2,SUM($F11:F11),IF(MONTH(Factores!$D$2)=3,SUM($F11:G11),IF(MONTH(Factores!$D$2)=4,SUM($F11:H11),IF(MONTH(Factores!$D$2)=5,SUM($F11:I11),IF(MONTH(Factores!$D$2)=6,SUM($F11:J11),IF(MONTH(Factores!$D$2)=7,SUM($F11:K11),IF(MONTH(Factores!$D$2)=8,SUM($F11:L11),IF(MONTH(Factores!$D$2)=9,SUM($F11:M11),IF(MONTH(Factores!$D$2)=10,SUM($F11:N11),IF(MONTH(Factores!$D$2)=11,SUM($F11:O11),IF(MONTH(Factores!$D$2)=12,SUM($F11:P11))))))))))))) -> 0
C13: Fino Cu Equivalente Producido | D13: ktons | S13: =SUM(F13:Q13) -> 0 | U13: =IF(MONTH(Factores!$D$2)=1,SUM($F13:F13),IF(MONTH(Factores!$D$2)=2,SUM($F13:G13),IF(MONTH(Factores!$D$2)=3,SUM($F13:H13),IF(MONTH(Factores!$D$2)=4,SUM($F13:I13),IF(MONTH(Factores!$D$2)=5,SUM($F13:J13),IF(MONTH(Factores!$D$2)=6,SUM($F13:K13),IF(MONTH(Factores!$D$2)=7,SUM($F13:L13),IF(MONTH(Factores!$D$2)=8,SUM($F13:M13),IF(MONTH(Factores!$D$2)=9,SUM($F13:N13),IF(MONTH(Factores!$D$2)=10,SUM($F13:O13),IF(MONTH(Factores!$D$2)=11,SUM($F13:P13),IF(MONTH(Factores!$D$2)=12,SUM($F13:Q13))))))))))))) -> 0 | V13: =IF(MONTH(Factores!$D$2)=1,SUM($F13:F13),IF(MONTH(Factores!$D$2)=2,SUM($F13:F13),IF(MONTH(Factores!$D$2)=3,SUM($F13:G13),IF(MONTH(Factores!$D$2)=4,SUM($F13:H13),IF(MONTH(Factores!$D$2)=5,SUM($F13:I13),IF(MONTH(Factores!$D$2)=6,SUM($F13:J13),IF(MONTH(Factores!$D$2)=7,SUM($F13:K13),IF(MONTH(Factores!$D$2)=8,SUM($F13:L13),IF(MONTH(Factores!$D$2)=9,SUM($F13:M13),IF(MONTH(Factores!$D$2)=10,SUM($F13:N13),IF(MONTH(Factores!$D$2)=11,SUM($F13:O13),IF(MONTH(Factores!$D$2)=12,SUM($F13:P13))))))))))))) -> 0
C14: Fino Cu Equivalente Filtrado | D14: ktons | S14: =SUM(F14:Q14) -> 0 | U14: =IF(MONTH(Factores!$D$2)=1,SUM($F14:F14),IF(MONTH(Factores!$D$2)=2,SUM($F14:G14),IF(MONTH(Factores!$D$2)=3,SUM($F14:H14),IF(MONTH(Factores!$D$2)=4,SUM($F14:I14),IF(MONTH(Factores!$D$2)=5,SUM($F14:J14),IF(MONTH(Factores!$D$2)=6,SUM($F14:K14),IF(MONTH(Factores!$D$2)=7,SUM($F14:L14),IF(MONTH(Factores!$D$2)=8,SUM($F14:M14),IF(MONTH(Factores!$D$2)=9,SUM($F14:N14),IF(MONTH(Factores!$D$2)=10,SUM($F14:O14),IF(MONTH(Factores!$D$2)=11,SUM($F14:P14),IF(MONTH(Factores!$D$2)=12,SUM($F14:Q14))))))))))))) -> 0 | V14: =IF(MONTH(Factores!$D$2)=1,SUM($F14:F14),IF(MONTH(Factores!$D$2)=2,SUM($F14:F14),IF(MONTH(Factores!$D$2)=3,SUM($F14:G14),IF(MONTH(Factores!$D$2)=4,SUM($F14:H14),IF(MONTH(Factores!$D$2)=5,SUM($F14:I14),IF(MONTH(Factores!$D$2)=6,SUM($F14:J14),IF(MONTH(Factores!$D$2)=7,SUM($F14:K14),IF(MONTH(Factores!$D$2)=8,SUM($F14:L14),IF(MONTH(Factores!$D$2)=9,SUM($F14:M14),IF(MONTH(Factores!$D$2)=10,SUM($F14:N14),IF(MONTH(Factores!$D$2)=11,SUM($F14:O14),IF(MONTH(Factores!$D$2)=12,SUM($F14:P14))))))))))))) -> 0
C15: Fino Cu Producido | D15: ktons | F15: 24.614905 | G15: 23.455272 | H15: 27.277609 | I15: 26.261028 | J15: 29.807136 | K15: 29.219651 | L15: 23.123375 | M15: 24.938278 | N15: 28.458821 | O15: 28.82859 | P15: 29.822426 | Q15: 31.475032 | S15: =SUM(F15:Q15) -> 327.28212 | U15: =IF(MONTH(Factores!$D$2)=1,SUM($F15:F15),IF(MONTH(Factores!$D$2)=2,SUM($F15:G15),IF(MONTH(Factores!$D$2)=3,SUM($F15:H15),IF(MONTH(Factores!$D$2)=4,SUM($F15:I15),IF(MONTH(Factores!$D$2)=5,SUM($F15:J15),IF(MONTH(Factores!$D$2)=6,SUM($F15:K15),IF(MONTH(Factores!$D$2)=7,SUM($F15:L15),IF(MONTH(Factores!$D$2)=8,SUM($F15:M15),IF(MONTH(Factores!$D$2)=9,SUM($F15:N15),IF(MONTH(Factores!$D$2)=10,SUM($F15:O15),IF(MONTH(Factores!$D$2)=11,SUM($F15:P15),IF(MONTH(Factores!$D$2)=12,SUM($F15:Q15))))))))))))) -> 75.347786 | V15: =IF(MONTH(Factores!$D$2)=1,SUM($F15:F15),IF(MONTH(Factores!$D$2)=2,SUM($F15:F15),IF(MONTH(Factores!$D$2)=3,SUM($F15:G15),IF(MONTH(Factores!$D$2)=4,SUM($F15:H15),IF(MONTH(Factores!$D$2)=5,SUM($F15:I15),IF(MONTH(Factores!$D$2)=6,SUM($F15:J15),IF(MONTH(Factores!$D$2)=7,SUM($F15:K15),IF(MONTH(Factores!$D$2)=8,SUM($F15:L15),IF(MONTH(Factores!$D$2)=9,SUM($F15:M15),IF(MONTH(Factores!$D$2)=10,SUM($F15:N15),IF(MONTH(Factores!$D$2)=11,SUM($F15:O15),IF(MONTH(Factores!$D$2)=12,SUM($F15:P15))))))))))))) -> 48.070177
C16: Fino Cu Filtrado Pagable | D16: ktons | F16: 23.777998 | G16: 22.657793 | H16: 26.350171 | I16: 25.368153 | J16: 28.793693 | K16: 28.226182 | L16: 22.33718 | M16: 24.090377 | N16: 27.491221 | O16: 27.848418 | P16: 28.808464 | Q16: 30.40488 | S16: =SUM(F16:Q16) -> 316.15453 | U16: =IF(MONTH(Factores!$D$2)=1,SUM($F16:F16),IF(MONTH(Factores!$D$2)=2,SUM($F16:G16),IF(MONTH(Factores!$D$2)=3,SUM($F16:H16),IF(MONTH(Factores!$D$2)=4,SUM($F16:I16),IF(MONTH(Factores!$D$2)=5,SUM($F16:J16),IF(MONTH(Factores!$D$2)=6,SUM($F16:K16),IF(MONTH(Factores!$D$2)=7,SUM($F16:L16),IF(MONTH(Factores!$D$2)=8,SUM($F16:M16),IF(MONTH(Factores!$D$2)=9,SUM($F16:N16),IF(MONTH(Factores!$D$2)=10,SUM($F16:O16),IF(MONTH(Factores!$D$2)=11,SUM($F16:P16),IF(MONTH(Factores!$D$2)=12,SUM($F16:Q16))))))))))))) -> 72.785961 | V16: =IF(MONTH(Factores!$D$2)=1,SUM($F16:F16),IF(MONTH(Factores!$D$2)=2,SUM($F16:F16),IF(MONTH(Factores!$D$2)=3,SUM($F16:G16),IF(MONTH(Factores!$D$2)=4,SUM($F16:H16),IF(MONTH(Factores!$D$2)=5,SUM($F16:I16),IF(MONTH(Factores!$D$2)=6,SUM($F16:J16),IF(MONTH(Factores!$D$2)=7,SUM($F16:K16),IF(MONTH(Factores!$D$2)=8,SUM($F16:L16),IF(MONTH(Factores!$D$2)=9,SUM($F16:M16),IF(MONTH(Factores!$D$2)=10,SUM($F16:N16),IF(MONTH(Factores!$D$2)=11,SUM($F16:O16),IF(MONTH(Factores!$D$2)=12,SUM($F16:P16))))))))))))) -> 46.435791
C17: Fino Mo Producido | D17: ktons | F17: 0.83986064 | G17: 0.91272777 | H17: 0.99521526 | I17: 1.1689092 | J17: 1.1986114 | K17: 1.2198837 | L17: 0.82486301 | M17: 1.0567662 | N17: 1.357995 | O17: 1.0812537 | P17: 1.2835249 | Q17: 1.3547179 | S17: =SUM(F17:Q17) -> 13.294329 | U17: =IF(MONTH(Factores!$D$2)=1,SUM($F17:F17),IF(MONTH(Factores!$D$2)=2,SUM($F17:G17),IF(MONTH(Factores!$D$2)=3,SUM($F17:H17),IF(MONTH(Factores!$D$2)=4,SUM($F17:I17),IF(MONTH(Factores!$D$2)=5,SUM($F17:J17),IF(MONTH(Factores!$D$2)=6,SUM($F17:K17),IF(MONTH(Factores!$D$2)=7,SUM($F17:L17),IF(MONTH(Factores!$D$2)=8,SUM($F17:M17),IF(MONTH(Factores!$D$2)=9,SUM($F17:N17),IF(MONTH(Factores!$D$2)=10,SUM($F17:O17),IF(MONTH(Factores!$D$2)=11,SUM($F17:P17),IF(MONTH(Factores!$D$2)=12,SUM($F17:Q17))))))))))))) -> 2.7478037 | V17: =IF(MONTH(Factores!$D$2)=1,SUM($F17:F17),IF(MONTH(Factores!$D$2)=2,SUM($F17:F17),IF(MONTH(Factores!$D$2)=3,SUM($F17:G17),IF(MONTH(Factores!$D$2)=4,SUM($F17:H17),IF(MONTH(Factores!$D$2)=5,SUM($F17:I17),IF(MONTH(Factores!$D$2)=6,SUM($F17:J17),IF(MONTH(Factores!$D$2)=7,SUM($F17:K17),IF(MONTH(Factores!$D$2)=8,SUM($F17:L17),IF(MONTH(Factores!$D$2)=9,SUM($F17:M17),IF(MONTH(Factores!$D$2)=10,SUM($F17:N17),IF(MONTH(Factores!$D$2)=11,SUM($F17:O17),IF(MONTH(Factores!$D$2)=12,SUM($F17:P17))))))))))))) -> 1.7525884
C18: Fino Mo Envasado Pagable | D18: ktons | F18: 0.83566133 | G18: 0.90816413 | H18: 0.99023918 | I18: 1.1630647 | J18: 1.1926184 | K18: 1.2137843 | L18: 0.82073869 | M18: 1.0514823 | N18: 1.351205 | O18: 1.0758475 | P18: 1.2771073 | Q18: 1.3479443 | S18: =SUM(F18:Q18) -> 13.227857 | U18: =IF(MONTH(Factores!$D$2)=1,SUM($F18:F18),IF(MONTH(Factores!$D$2)=2,SUM($F18:G18),IF(MONTH(Factores!$D$2)=3,SUM($F18:H18),IF(MONTH(Factores!$D$2)=4,SUM($F18:I18),IF(MONTH(Factores!$D$2)=5,SUM($F18:J18),IF(MONTH(Factores!$D$2)=6,SUM($F18:K18),IF(MONTH(Factores!$D$2)=7,SUM($F18:L18),IF(MONTH(Factores!$D$2)=8,SUM($F18:M18),IF(MONTH(Factores!$D$2)=9,SUM($F18:N18),IF(MONTH(Factores!$D$2)=10,SUM($F18:O18),IF(MONTH(Factores!$D$2)=11,SUM($F18:P18),IF(MONTH(Factores!$D$2)=12,SUM($F18:Q18))))))))))))) -> 2.7340646 | V18: =IF(MONTH(Factores!$D$2)=1,SUM($F18:F18),IF(MONTH(Factores!$D$2)=2,SUM($F18:F18),IF(MONTH(Factores!$D$2)=3,SUM($F18:G18),IF(MONTH(Factores!$D$2)=4,SUM($F18:H18),IF(MONTH(Factores!$D$2)=5,SUM($F18:I18),IF(MONTH(Factores!$D$2)=6,SUM($F18:J18),IF(MONTH(Factores!$D$2)=7,SUM($F18:K18),IF(MONTH(Factores!$D$2)=8,SUM($F18:L18),IF(MONTH(Factores!$D$2)=9,SUM($F18:M18),IF(MONTH(Factores!$D$2)=10,SUM($F18:N18),IF(MONTH(Factores!$D$2)=11,SUM($F18:O18),IF(MONTH(Factores!$D$2)=12,SUM($F18:P18))))))))))))) -> 1.7438255
C20: Mineral Procesado Planta | D20: ktons | F20: 5607.9044 | G20: 5222.8705 | H20: 5115.5852 | I20: 5879.0851 | J20: 6219.2205 | K20: 6022.8239 | L20: 5113.1375 | M20: 5314.0765 | N20: 5878.2009 | O20: 6213.1358 | P20: 5781.6331 | Q20: 6183.5338 | S20: =SUM(F20:Q20) -> 68551.207 | U20: =IF(MONTH(Factores!$D$2)=1,SUM($F20:F20),IF(MONTH(Factores!$D$2)=2,SUM($F20:G20),IF(MONTH(Factores!$D$2)=3,SUM($F20:H20),IF(MONTH(Factores!$D$2)=4,SUM($F20:I20),IF(MONTH(Factores!$D$2)=5,SUM($F20:J20),IF(MONTH(Factores!$D$2)=6,SUM($F20:K20),IF(MONTH(Factores!$D$2)=7,SUM($F20:L20),IF(MONTH(Factores!$D$2)=8,SUM($F20:M20),IF(MONTH(Factores!$D$2)=9,SUM($F20:N20),IF(MONTH(Factores!$D$2)=10,SUM($F20:O20),IF(MONTH(Factores!$D$2)=11,SUM($F20:P20),IF(MONTH(Factores!$D$2)=12,SUM($F20:Q20))))))))))))) -> 15946.36 | V20: =IF(MONTH(Factores!$D$2)=1,SUM($F20:F20),IF(MONTH(Factores!$D$2)=2,SUM($F20:F20),IF(MONTH(Factores!$D$2)=3,SUM($F20:G20),IF(MONTH(Factores!$D$2)=4,SUM($F20:H20),IF(MONTH(Factores!$D$2)=5,SUM($F20:I20),IF(MONTH(Factores!$D$2)=6,SUM($F20:J20),IF(MONTH(Factores!$D$2)=7,SUM($F20:K20),IF(MONTH(Factores!$D$2)=8,SUM($F20:L20),IF(MONTH(Factores!$D$2)=9,SUM($F20:M20),IF(MONTH(Factores!$D$2)=10,SUM($F20:N20),IF(MONTH(Factores!$D$2)=11,SUM($F20:O20),IF(MONTH(Factores!$D$2)=12,SUM($F20:P20))))))))))))) -> 10830.775
C21: Mineral Procesado Planta | D21: ktpd | F21: 180.90014 | G21: 186.53109 | H21: 165.01888 | I21: 195.9695 | J21: 200.62002 | K21: 200.7608 | L21: 164.93992 | M21: 171.42182 | N21: 195.94003 | O21: 200.42374 | P21: 192.7211 | Q21: 199.46883 | S21: =+S20/S6 -> 187.29838 | U21: =U20/U6 -> 175.23473 | V21: =V20/V6 -> 180.51292
C22: Rendimiento Pta | D22: Tph | F22: 8278.1672 | G22: 8684.4809 | H22: 8745.2728 | I22: 8512.0482 | J22: 8702.6721 | K22: 8750.6559 | L22: 8432.7098 | M22: 9072.7109 | N22: 8628.0742 | O22: 8684.6607 | P22: 8236.0167 | Q22: 8709.1354 | S22: =S20*1000/S31 -> 8573.3478 | U22: =U20*1000/U31 -> 8685.5195 | V22: =V20*1000/V31 -> 8393.8596
C23: Mineral Duro (Sin M3) | D23: % | F23: 38.464285 | G23: 31.029229 | H23: 32.672111 | I23: 15.646154 | J23: 21.243943 | K23: 28.454345 | L23: 43.717974 | M23: 36.10178 | N23: 53.294909 | O23: 48.980152 | P23: 63.198635 | Q23: 65.554278 | S23: =SUMPRODUCT(F23:Q23,F20:Q20)/SUM(F20:Q20) -> 40.030142 | U23: =IF(MONTH(Factores!$D$2)=1,SUMPRODUCT($F$20:$F$20,$F23:F23)/SUM($F$20:$F$20),IF(MONTH(Factores!$D$2)=2,SUMPRODUCT($F$20:$G$20,$F23:G23)/SUM($F$20:$G$20),IF(MONTH(Factores!$D$2)=3,SUMPRODUCT($F$20:$H$20,$F23:H23)/SUM($F$20:$H$20),IF(MONTH(Factores!$D$2)=4,SUMPRODUCT($F$20:$I$20,$F23:I23)/SUM($F$20:$I$20),IF(MONTH(Factores!$D$2)=5,SUMPRODUCT($F$20:$J$20,$F23:J23)/SUM($F$20:$J$20),IF(MONTH(Factores!$D$2)=6,SUMPRODUCT($F$20:$K$20,$F23:K23)/SUM($F$20:$K$20),IF(MONTH(Factores!$D$2)=7,SUMPRODUCT($F$20:$L$20,$F23:L23)/SUM($F$20:$L$20),IF(MONTH(Factores!$D$2)=8,SUMPRODUCT($F$20:$M$20,$F23:M23)/SUM($F$20:$M$20),IF(MONTH(Factores!$D$2)=9,SUMPRODUCT($F$20:$N$20,$F23:N23)/SUM($F$20:$N$20),IF(MONTH(Factores!$D$2)=10,SUMPRODUCT($F$20:$O$20,$F23:O23)/SUM($F$20:$O$20),IF(MONTH(Factores!$D$2)=11,SUMPRODUCT($F$20:$P$20,$F23:P23)/SUM($F$20:$P$20),IF(MONTH(Factores!$D$2)=12,SUMPRODUCT($F$20:$Q$20,$F23:Q23)/SUM($F$20:$Q$20))))))))))))) -> 34.170973 | V23: =IF(MONTH(Factores!$D$2)=1,SUMPRODUCT($F$20:$F$20,$F23:F23)/SUM($F$20:$F$20),IF(MONTH(Factores!$D$2)=2,SUMPRODUCT($F$20:$F$20,$F23:F23)/SUM($F$20:$F$20),IF(MONTH(Factores!$D$2)=3,SUMPRODUCT($F$20:$G$20,$F23:G23)/SUM($F$20:$G$20),IF(MONTH(Factores!$D$2)=4,SUMPRODUCT($F$20:$H$20,$F23:H23)/SUM($F$20:$H$20),IF(MONTH(Factores!$D$2)=5,SUMPRODUCT($F$20:$I$20,$F23:I23)/SUM($F$20:$I$20),IF(MONTH(Factores!$D$2)=6,SUMPRODUCT($F$20:$J$20,$F23:J23)/SUM($F$20:$J$20),IF(MONTH(Factores!$D$2)=7,SUMPRODUCT($F$20:$K$20,$F23:K23)/SUM($F$20:$K$20),IF(MONTH(Factores!$D$2)=8,SUMPRODUCT($F$20:$L$20,$F23:L23)/SUM($F$20:$L$20),IF(MONTH(Factores!$D$2)=9,SUMPRODUCT($F$20:$M$20,$F23:M23)/SUM($F$20:$M$20),IF(MONTH(Factores!$D$2)=10,SUMPRODUCT($F$20:$N$20,$F23:N23)/SUM($F$20:$N$20),IF(MONTH(Factores!$D$2)=11,SUMPRODUCT($F$20:$O$20,$F23:O23)/SUM($F$20:$O$20),IF(MONTH(Factores!$D$2)=12,SUMPRODUCT($F$20:$P$20,$F23:P23)/SUM($F$20:$P$20))))))))))))) -> 34.878915
C24: Axb | D24: - | F24: 37.25541 | G24: 35.921331 | H24: 36.784395 | I24: 35.513843 | J24: 36.439688 | K24: 35.694447 | L24: 36.664253 | M24: 36.916859 | N24: 35.950088 | O24: 37.69751 | P24: 37.738177 | Q24: 37.898027 | S24: =SUMPRODUCT(F24:Q24,F20:Q20)/SUM(F20:Q20) -> 36.714593 | U24: =IF(MONTH(Factores!$D$2)=1,SUMPRODUCT($F$20:$F$20,$F24:F24)/SUM($F$20:$F$20),IF(MONTH(Factores!$D$2)=2,SUMPRODUCT($F$20:$G$20,$F24:G24)/SUM($F$20:$G$20),IF(MONTH(Factores!$D$2)=3,SUMPRODUCT($F$20:$H$20,$F24:H24)/SUM($F$20:$H$20),IF(MONTH(Factores!$D$2)=4,SUMPRODUCT($F$20:$I$20,$F24:I24)/SUM($F$20:$I$20),IF(MONTH(Factores!$D$2)=5,SUMPRODUCT($F$20:$J$20,$F24:J24)/SUM($F$20:$J$20),IF(MONTH(Factores!$D$2)=6,SUMPRODUCT($F$20:$K$20,$F24:K24)/SUM($F$20:$K$20),IF(MONTH(Factores!$D$2)=7,SUMPRODUCT($F$20:$L$20,$F24:L24)/SUM($F$20:$L$20),IF(MONTH(Factores!$D$2)=8,SUMPRODUCT($F$20:$M$20,$F24:M24)/SUM($F$20:$M$20),IF(MONTH(Factores!$D$2)=9,SUMPRODUCT($F$20:$N$20,$F24:N24)/SUM($F$20:$N$20),IF(MONTH(Factores!$D$2)=10,SUMPRODUCT($F$20:$O$20,$F24:O24)/SUM($F$20:$O$20),IF(MONTH(Factores!$D$2)=11,SUMPRODUCT($F$20:$P$20,$F24:P24)/SUM($F$20:$P$20),IF(MONTH(Factores!$D$2)=12,SUMPRODUCT($F$20:$Q$20,$F24:Q24)/SUM($F$20:$Q$20))))))))))))) -> 36.667361 | V24: =IF(MONTH(Factores!$D$2)=1,SUMPRODUCT($F$20:$F$20,$F24:F24)/SUM($F$20:$F$20),IF(MONTH(Factores!$D$2)=2,SUMPRODUCT($F$20:$F$20,$F24:F24)/SUM($F$20:$F$20),IF(MONTH(Factores!$D$2)=3,SUMPRODUCT($F$20:$G$20,$F24:G24)/SUM($F$20:$G$20),IF(MONTH(Factores!$D$2)=4,SUMPRODUCT($F$20:$H$20,$F24:H24)/SUM($F$20:$H$20),IF(MONTH(Factores!$D$2)=5,SUMPRODUCT($F$20:$I$20,$F24:I24)/SUM($F$20:$I$20),IF(MONTH(Factores!$D$2)=6,SUMPRODUCT($F$20:$J$20,$F24:J24)/SUM($F$20:$J$20),IF(MONTH(Factores!$D$2)=7,SUMPRODUCT($F$20:$K$20,$F24:K24)/SUM($F$20:$K$20),IF(MONTH(Factores!$D$2)=8,SUMPRODUCT($F$20:$L$20,$F24:L24)/SUM($F$20:$L$20),IF(MONTH(Factores!$D$2)=9,SUMPRODUCT($F$20:$M$20,$F24:M24)/SUM($F$20:$M$20),IF(MONTH(Factores!$D$2)=10,SUMPRODUCT($F$20:$N$20,$F24:N24)/SUM($F$20:$N$20),IF(MONTH(Factores!$D$2)=11,SUMPRODUCT($F$20:$O$20,$F24:O24)/SUM($F$20:$O$20),IF(MONTH(Factores!$D$2)=12,SUMPRODUCT($F$20:$P$20,$F24:P24)/SUM($F$20:$P$20))))))))))))) -> 36.612084
C25: Coeficiente Marcha Pta | D25: % | F25: 91.114068 | G25: 89.561092 | H25: 78.675768 | I25: 95.994174 | J25: 96.637382 | K25: 96.46407 | L25: 82.216368 | M25: 79.204991 | N25: 94.689049 | O25: 96.222585 | P25: 97.566902 | Q25: 95.495021 | S25: =S27/S31*100 -> 109.85698 | U25: =IF(MONTH(Factores!$D$2)=1,SUMPRODUCT($F$6:$F$6,$F25:F25)/SUM($F$6:$F$6),IF(MONTH(Factores!$D$2)=2,SUMPRODUCT($F$6:$G$6,$F25:G25)/SUM($F$6:$G$6),IF(MONTH(Factores!$D$2)=3,SUMPRODUCT($F$6:$H$6,$F25:H25)/SUM($F$6:$H$6),IF(MONTH(Factores!$D$2)=4,SUMPRODUCT($F$6:$I$6,$F25:I25)/SUM($F$6:$I$6),IF(MONTH(Factores!$D$2)=5,SUMPRODUCT($F$6:$J$6,$F25:J25)/SUM($F$6:$J$6),IF(MONTH(Factores!$D$2)=6,SUMPRODUCT($F$6:$K$6,$F25:K25)/SUM($F$6:$K$6),IF(MONTH(Factores!$D$2)=7,SUMPRODUCT($F$6:$L$6,$F25:L25)/SUM($F$6:$L$6),IF(MONTH(Factores!$D$2)=8,SUMPRODUCT($F$6:$M$6,$F25:M25)/SUM($F$6:$M$6),IF(MONTH(Factores!$D$2)=9,SUMPRODUCT($F$6:$N$6,$F25:N25)/SUM($F$6:$N$6),IF(MONTH(Factores!$D$2)=10,SUMPRODUCT($F$6:$O$6,$F25:O25)/SUM($F$6:$O$6),IF(MONTH(Factores!$D$2)=11,SUMPRODUCT($F$6:$P$6,$F25:P25)/SUM($F$6:$P$6),IF(MONTH(Factores!$D$2)=12,SUMPRODUCT($F$6:$Q$6,$F25:Q25)/SUM($F$6:$Q$6))))))))))))) -> 86.381941 | V25: =IF(MONTH(Factores!$D$2)=1,SUMPRODUCT($F$6:$F$6,$F25:F25)/SUM($F$6:$F$6),IF(MONTH(Factores!$D$2)=2,SUMPRODUCT($F$6:$F$6,$F25:F25)/SUM($F$6:$F$6),IF(MONTH(Factores!$D$2)=3,SUMPRODUCT($F$6:$G$6,$F25:G25)/SUM($F$6:$G$6),IF(MONTH(Factores!$D$2)=4,SUMPRODUCT($F$6:$H$6,$F25:H25)/SUM($F$6:$H$6),IF(MONTH(Factores!$D$2)=5,SUMPRODUCT($F$6:$I$6,$F25:I25)/SUM($F$6:$I$6),IF(MONTH(Factores!$D$2)=6,SUMPRODUCT($F$6:$J$6,$F25:J25)/SUM($F$6:$J$6),IF(MONTH(Factores!$D$2)=7,SUMPRODUCT($F$6:$K$6,$F25:K25)/SUM($F$6:$K$6),IF(MONTH(Factores!$D$2)=8,SUMPRODUCT($F$6:$L$6,$F25:L25)/SUM($F$6:$L$6),IF(MONTH(Factores!$D$2)=9,SUMPRODUCT($F$6:$M$6,$F25:M25)/SUM($F$6:$M$6),IF(MONTH(Factores!$D$2)=10,SUMPRODUCT($F$6:$N$6,$F25:N25)/SUM($F$6:$N$6),IF(MONTH(Factores!$D$2)=11,SUMPRODUCT($F$6:$O$6,$F25:O25)/SUM($F$6:$O$6),IF(MONTH(Factores!$D$2)=12,SUMPRODUCT($F$6:$P$6,$F25:P25)/SUM($F$6:$P$6))))))))))))) -> 90.363463
C26: Disponibilidad Pta | D26: %
C27: Horas Total | D27: Hrs | F27: 732 | G27: 696 | H27: 744 | I27: 720 | J27: 744 | K27: 720 | L27: 744 | M27: 744 | N27: 720 | O27: 744 | P27: 720 | Q27: 756 | S27: =SUM(F27:Q27) -> 8784 | U27: =IF(MONTH(Factores!$D$2)=1,SUM($F27:F27),IF(MONTH(Factores!$D$2)=2,SUM($F27:G27),IF(MONTH(Factores!$D$2)=3,SUM($F27:H27),IF(MONTH(Factores!$D$2)=4,SUM($F27:I27),IF(MONTH(Factores!$D$2)=5,SUM($F27:J27),IF(MONTH(Factores!$D$2)=6,SUM($F27:K27),IF(MONTH(Factores!$D$2)=7,SUM($F27:L27),IF(MONTH(Factores!$D$2)=8,SUM($F27:M27),IF(MONTH(Factores!$D$2)=9,SUM($F27:N27),IF(MONTH(Factores!$D$2)=10,SUM($F27:O27),IF(MONTH(Factores!$D$2)=11,SUM($F27:P27),IF(MONTH(Factores!$D$2)=12,SUM($F27:Q27))))))))))))) -> 2172 | V27: =IF(MONTH(Factores!$D$2)=1,SUM($F27:F27),IF(MONTH(Factores!$D$2)=2,SUM($F27:F27),IF(MONTH(Factores!$D$2)=3,SUM($F27:G27),IF(MONTH(Factores!$D$2)=4,SUM($F27:H27),IF(MONTH(Factores!$D$2)=5,SUM($F27:I27),IF(MONTH(Factores!$D$2)=6,SUM($F27:J27),IF(MONTH(Factores!$D$2)=7,SUM($F27:K27),IF(MONTH(Factores!$D$2)=8,SUM($F27:L27),IF(MONTH(Factores!$D$2)=9,SUM($F27:M27),IF(MONTH(Factores!$D$2)=10,SUM($F27:N27),IF(MONTH(Factores!$D$2)=11,SUM($F27:O27),IF(MONTH(Factores!$D$2)=12,SUM($F27:P27))))))))))))) -> 1428
C28: Horas Mantención | D28: Hrs | U28: =IF(MONTH(Factores!$D$2)=1,SUM($F28:F28),IF(MONTH(Factores!$D$2)=2,SUM($F28:G28),IF(MONTH(Factores!$D$2)=3,SUM($F28:H28),IF(MONTH(Factores!$D$2)=4,SUM($F28:I28),IF(MONTH(Factores!$D$2)=5,SUM($F28:J28),IF(MONTH(Factores!$D$2)=6,SUM($F28:K28),IF(MONTH(Factores!$D$2)=7,SUM($F28:L28),IF(MONTH(Factores!$D$2)=8,SUM($F28:M28),IF(MONTH(Factores!$D$2)=9,SUM($F28:N28),IF(MONTH(Factores!$D$2)=10,SUM($F28:O28),IF(MONTH(Factores!$D$2)=11,SUM($F28:P28),IF(MONTH(Factores!$D$2)=12,SUM($F28:Q28))))))))))))) -> 0 | V28: =IF(MONTH(Factores!$D$2)=1,SUM($F28:F28),IF(MONTH(Factores!$D$2)=2,SUM($F28:F28),IF(MONTH(Factores!$D$2)=3,SUM($F28:G28),IF(MONTH(Factores!$D$2)=4,SUM($F28:H28),IF(MONTH(Factores!$D$2)=5,SUM($F28:I28),IF(MONTH(Factores!$D$2)=6,SUM($F28:J28),IF(MONTH(Factores!$D$2)=7,SUM($F28:K28),IF(MONTH(Factores!$D$2)=8,SUM($F28:L28),IF(MONTH(Factores!$D$2)=9,SUM($F28:M28),IF(MONTH(Factores!$D$2)=10,SUM($F28:N28),IF(MONTH(Factores!$D$2)=11,SUM($F28:O28),IF(MONTH(Factores!$D$2)=12,SUM($F28:P28))))))))))))) -> 0
C29: Horas Detencion Operación | D29: Hrs | U29: =IF(MONTH(Factores!$D$2)=1,SUM($F29:F29),IF(MONTH(Factores!$D$2)=2,SUM($F29:G29),IF(MONTH(Factores!$D$2)=3,SUM($F29:H29),IF(MONTH(Factores!$D$2)=4,SUM($F29:I29),IF(MONTH(Factores!$D$2)=5,SUM($F29:J29),IF(MONTH(Factores!$D$2)=6,SUM($F29:K29),IF(MONTH(Factores!$D$2)=7,SUM($F29:L29),IF(MONTH(Factores!$D$2)=8,SUM($F29:M29),IF(MONTH(Factores!$D$2)=9,SUM($F29:N29),IF(MONTH(Factores!$D$2)=10,SUM($F29:O29),IF(MONTH(Factores!$D$2)=11,SUM($F29:P29),IF(MONTH(Factores!$D$2)=12,SUM($F29:Q29))))))))))))) -> 0 | V29: =IF(MONTH(Factores!$D$2)=1,SUM($F29:F29),IF(MONTH(Factores!$D$2)=2,SUM($F29:F29),IF(MONTH(Factores!$D$2)=3,SUM($F29:G29),IF(MONTH(Factores!$D$2)=4,SUM($F29:H29),IF(MONTH(Factores!$D$2)=5,SUM($F29:I29),IF(MONTH(Factores!$D$2)=6,SUM($F29:J29),IF(MONTH(Factores!$D$2)=7,SUM($F29:K29),IF(MONTH(Factores!$D$2)=8,SUM($F29:L29),IF(MONTH(Factores!$D$2)=9,SUM($F29:M29),IF(MONTH(Factores!$D$2)=10,SUM($F29:N29),IF(MONTH(Factores!$D$2)=11,SUM($F29:O29),IF(MONTH(Factores!$D$2)=12,SUM($F29:P29))))))))))))) -> 0
C30: Horas Detencion Invierno | D30: Hrs | U30: =IF(MONTH(Factores!$D$2)=1,SUM($F30:F30),IF(MONTH(Factores!$D$2)=2,SUM($F30:G30),IF(MONTH(Factores!$D$2)=3,SUM($F30:H30),IF(MONTH(Factores!$D$2)=4,SUM($F30:I30),IF(MONTH(Factores!$D$2)=5,SUM($F30:J30),IF(MONTH(Factores!$D$2)=6,SUM($F30:K30),IF(MONTH(Factores!$D$2)=7,SUM($F30:L30),IF(MONTH(Factores!$D$2)=8,SUM($F30:M30),IF(MONTH(Factores!$D$2)=9,SUM($F30:N30),IF(MONTH(Factores!$D$2)=10,SUM($F30:O30),IF(MONTH(Factores!$D$2)=11,SUM($F30:P30),IF(MONTH(Factores!$D$2)=12,SUM($F30:Q30))))))))))))) -> 0 | V30: =IF(MONTH(Factores!$D$2)=1,SUM($F30:F30),IF(MONTH(Factores!$D$2)=2,SUM($F30:F30),IF(MONTH(Factores!$D$2)=3,SUM($F30:G30),IF(MONTH(Factores!$D$2)=4,SUM($F30:H30),IF(MONTH(Factores!$D$2)=5,SUM($F30:I30),IF(MONTH(Factores!$D$2)=6,SUM($F30:J30),IF(MONTH(Factores!$D$2)=7,SUM($F30:K30),IF(MONTH(Factores!$D$2)=8,SUM($F30:L30),IF(MONTH(Factores!$D$2)=9,SUM($F30:M30),IF(MONTH(Factores!$D$2)=10,SUM($F30:N30),IF(MONTH(Factores!$D$2)=11,SUM($F30:O30),IF(MONTH(Factores!$D$2)=12,SUM($F30:P30))))))))))))) -> 0
C31: Horas Operación | D31: Hrs | F31: 667.2912 | G31: 623.03 | H31: 545.6496 | I31: 684.35971 | J31: 721.89912 | K31: 689.12036 | L31: 636.09401 | M31: 670.55015 | N31: 627.74463 | O31: 706.97811 | P31: 696.59404 | Q31: 726.53961 | S31: =SUM(F31:Q31) -> 7995.8505 | U31: =IF(MONTH(Factores!$D$2)=1,SUM($F31:F31),IF(MONTH(Factores!$D$2)=2,SUM($F31:G31),IF(MONTH(Factores!$D$2)=3,SUM($F31:H31),IF(MONTH(Factores!$D$2)=4,SUM($F31:I31),IF(MONTH(Factores!$D$2)=5,SUM($F31:J31),IF(MONTH(Factores!$D$2)=6,SUM($F31:K31),IF(MONTH(Factores!$D$2)=7,SUM($F31:L31),IF(MONTH(Factores!$D$2)=8,SUM($F31:M31),IF(MONTH(Factores!$D$2)=9,SUM($F31:N31),IF(MONTH(Factores!$D$2)=10,SUM($F31:O31),IF(MONTH(Factores!$D$2)=11,SUM($F31:P31),IF(MONTH(Factores!$D$2)=12,SUM($F31:Q31))))))))))))) -> 1835.9708 | V31: =IF(MONTH(Factores!$D$2)=1,SUM($F31:F31),IF(MONTH(Factores!$D$2)=2,SUM($F31:F31),IF(MONTH(Factores!$D$2)=3,SUM($F31:G31),IF(MONTH(Factores!$D$2)=4,SUM($F31:H31),IF(MONTH(Factores!$D$2)=5,SUM($F31:I31),IF(MONTH(Factores!$D$2)=6,SUM($F31:J31),IF(MONTH(Factores!$D$2)=7,SUM($F31:K31),IF(MONTH(Factores!$D$2)=8,SUM($F31:L31),IF(MONTH(Factores!$D$2)=9,SUM($F31:M31),IF(MONTH(Factores!$D$2)=10,SUM($F31:N31),IF(MONTH(Factores!$D$2)=11,SUM($F31:O31),IF(MONTH(Factores!$D$2)=12,SUM($F31:P31))))))))))))) -> 1290.3212
C33: Ley Alimentación Cobre | D33: % | F33: 0.49031748 | G33: 0.49938371 | H33: 0.59420757 | I33: 0.49221088 | J33: 0.53455049 | K33: 0.54026213 | L33: 0.49845913 | M33: 0.52605656 | N33: 0.53914477 | O33: 0.51866699 | P33: 0.57829312 | Q33: 0.56944061 | S33: =SUMPRODUCT(F33:Q33,F20:Q20)/SUM(F20:Q20) -> 0.53201556 | U33: =IF(MONTH(Factores!$D$2)=1,SUMPRODUCT($F$20:$F$20,$F33:F33)/SUM($F$20:$F$20),IF(MONTH(Factores!$D$2)=2,SUMPRODUCT($F$20:$G$20,$F33:G33)/SUM($F$20:$G$20),IF(MONTH(Factores!$D$2)=3,SUMPRODUCT($F$20:$H$20,$F33:H33)/SUM($F$20:$H$20),IF(MONTH(Factores!$D$2)=4,SUMPRODUCT($F$20:$I$20,$F33:I33)/SUM($F$20:$I$20),IF(MONTH(Factores!$D$2)=5,SUMPRODUCT($F$20:$J$20,$F33:J33)/SUM($F$20:$J$20),IF(MONTH(Factores!$D$2)=6,SUMPRODUCT($F$20:$K$20,$F33:K33)/SUM($F$20:$K$20),IF(MONTH(Factores!$D$2)=7,SUMPRODUCT($F$20:$L$20,$F33:L33)/SUM($F$20:$L$20),IF(MONTH(Factores!$D$2)=8,SUMPRODUCT($F$20:$M$20,$F33:M33)/SUM($F$20:$M$20),IF(MONTH(Factores!$D$2)=9,SUMPRODUCT($F$20:$N$20,$F33:N33)/SUM($F$20:$N$20),IF(MONTH(Factores!$D$2)=10,SUMPRODUCT($F$20:$O$20,$F33:O33)/SUM($F$20:$O$20),IF(MONTH(Factores!$D$2)=11,SUMPRODUCT($F$20:$P$20,$F33:P33)/SUM($F$20:$P$20),IF(MONTH(Factores!$D$2)=12,SUMPRODUCT($F$20:$Q$20,$F33:Q33)/SUM($F$20:$Q$20))))))))))))) -> 0.52661481 | V33: =IF(MONTH(Factores!$D$2)=1,SUMPRODUCT($F$20:$F$20,$F33:F33)/SUM($F$20:$F$20),IF(MONTH(Factores!$D$2)=2,SUMPRODUCT($F$20:$F$20,$F33:F33)/SUM($F$20:$F$20),IF(MONTH(Factores!$D$2)=3,SUMPRODUCT($F$20:$G$20,$F33:G33)/SUM($F$20:$G$20),IF(MONTH(Factores!$D$2)=4,SUMPRODUCT($F$20:$H$20,$F33:H33)/SUM($F$20:$H$20),IF(MONTH(Factores!$D$2)=5,SUMPRODUCT($F$20:$I$20,$F33:I33)/SUM($F$20:$I$20),IF(MONTH(Factores!$D$2)=6,SUMPRODUCT($F$20:$J$20,$F33:J33)/SUM($F$20:$J$20),IF(MONTH(Factores!$D$2)=7,SUMPRODUCT($F$20:$K$20,$F33:K33)/SUM($F$20:$K$20),IF(MONTH(Factores!$D$2)=8,SUMPRODUCT($F$20:$L$20,$F33:L33)/SUM($F$20:$L$20),IF(MONTH(Factores!$D$2)=9,SUMPRODUCT($F$20:$M$20,$F33:M33)/SUM($F$20:$M$20),IF(MONTH(Factores!$D$2)=10,SUMPRODUCT($F$20:$N$20,$F33:N33)/SUM($F$20:$N$20),IF(MONTH(Factores!$D$2)=11,SUMPRODUCT($F$20:$O$20,$F33:O33)/SUM($F$20:$O$20),IF(MONTH(Factores!$D$2)=12,SUMPRODUCT($F$20:$P$20,$F33:P33)/SUM($F$20:$P$20))))))))))))) -> 0.49468944
C34: Recuperación Global Cu | D34: % | F34: 89.520023 | G34: 89.928394 | H34: 89.737258 | I34: 90.750864 | J34: 89.659343 | K34: 89.798757 | L34: 90.726507 | M34: 89.208497 | N34: 89.798087 | O34: 89.45898 | P34: 89.195802 | Q34: 89.388367 | S34: =SUMPRODUCT(F20:Q20,F33:Q33,F34:Q34)/SUMPRODUCT(F20:Q20,F33:Q33) -> 89.739334 | U34: =IF(MONTH(Factores!$D$2)=1,SUMPRODUCT($F$20:$F$20,$F$33:$F$33,$F34:F34)/SUMPRODUCT($F$20:$F$20,$F$33:$F$33),IF(MONTH(Factores!$D$2)=2,SUMPRODUCT($F$20:$G$20,$F$33:$G$33,$F34:G34)/SUMPRODUCT($F$20:$G$20,$F$33:$G$33),IF(MONTH(Factores!$D$2)=3,SUMPRODUCT($F$20:$H$20,$F$33:$H$33,$F34:H34)/SUMPRODUCT($F$20:$H$20,$F$33:$H$33),IF(MONTH(Factores!$D$2)=4,SUMPRODUCT($F$20:$I$20,$F$33:$I$33,$F34:I34)/SUMPRODUCT($F$20:$I$20,$F$33:$I$33),IF(MONTH(Factores!$D$2)=5,SUMPRODUCT($F$20:$J$20,$F$33:$J$33,$F34:J34)/SUMPRODUCT($F$20:$J$20,$F$33:$J$33),IF(MONTH(Factores!$D$2)=6,SUMPRODUCT($F$20:$K$20,$F$33:$K$33,$F34:K34)/SUMPRODUCT($F$20:$K$20,$F$33:$K$33),IF(MONTH(Factores!$D$2)=7,SUMPRODUCT($F$20:$L$20,$F$33:$L$33,$F34:L34)/SUMPRODUCT($F$20:$L$20,$F$33:$L$33),IF(MONTH(Factores!$D$2)=8,SUMPRODUCT($F$20:$M$20,$F$33:$M$33,$F34:M34)/SUMPRODUCT($F$20:$M$20,$F$33:$M$33),IF(MONTH(Factores!$D$2)=9,SUMPRODUCT($F$20:$N$20,$F$33:$N$33,$F34:N34)/SUMPRODUCT($F$20:$N$20,$F$33:$N$33),IF(MONTH(Factores!$D$2)=10,SUMPRODUCT($F$20:$O$20,$F$33:$O$33,$F34:O34)/SUMPRODUCT($F$20:$O$20,$F$33:$O$33),IF(MONTH(Factores!$D$2)=11,SUMPRODUCT($F$20:$P$20,$F$33:$P$33,$F34:P34)/SUMPRODUCT($F$20:$P$20,$F$33:$P$33),IF(MONTH(Factores!$D$2)=12,SUMPRODUCT($F$20:$Q$20,$F$33:$Q$33,$F34:Q34)/SUMPRODUCT($F$20:$Q$20,$F$33:$Q$33))))))))))))) -> 89.725493 | V34: =IF(MONTH(Factores!$D$2)=1,SUMPRODUCT($F$20:$F$20,$F$33:$F$33,$F34:F34)/SUMPRODUCT($F$20:$F$20,$F$33:$F$33),IF(MONTH(Factores!$D$2)=2,SUMPRODUCT($F$20:$F$20,$F$33:$F$33,$F34:F34)/SUMPRODUCT($F$20:$F$20,$F$33:$F$33),IF(MONTH(Factores!$D$2)=3,SUMPRODUCT($F$20:$G$20,$F$33:$G$33,$F34:G34)/SUMPRODUCT($F$20:$G$20,$F$33:$G$33),IF(MONTH(Factores!$D$2)=4,SUMPRODUCT($F$20:$H$20,$F$33:$H$33,$F34:H34)/SUMPRODUCT($F$20:$H$20,$F$33:$H$33),IF(MONTH(Factores!$D$2)=5,SUMPRODUCT($F$20:$I$20,$F$33:$I$33,$F34:I34)/SUMPRODUCT($F$20:$I$20,$F$33:$I$33),IF(MONTH(Factores!$D$2)=6,SUMPRODUCT($F$20:$J$20,$F$33:$J$33,$F34:J34)/SUMPRODUCT($F$20:$J$20,$F$33:$J$33),IF(MONTH(Factores!$D$2)=7,SUMPRODUCT($F$20:$K$20,$F$33:$K$33,$F34:K34)/SUMPRODUCT($F$20:$K$20,$F$33:$K$33),IF(MONTH(Factores!$D$2)=8,SUMPRODUCT($F$20:$L$20,$F$33:$L$33,$F34:L34)/SUMPRODUCT($F$20:$L$20,$F$33:$L$33),IF(MONTH(Factores!$D$2)=9,SUMPRODUCT($F$20:$M$20,$F$33:$M$33,$F34:M34)/SUMPRODUCT($F$20:$M$20,$F$33:$M$33),IF(MONTH(Factores!$D$2)=10,SUMPRODUCT($F$20:$N$20,$F$33:$N$33,$F34:N34)/SUMPRODUCT($F$20:$N$20,$F$33:$N$33),IF(MONTH(Factores!$D$2)=11,SUMPRODUCT($F$20:$O$20,$F$33:$O$33,$F34:O34)/SUMPRODUCT($F$20:$O$20,$F$33:$O$33),IF(MONTH(Factores!$D$2)=12,SUMPRODUCT($F$20:$P$20,$F$33:$P$33,$F34:P34)/SUMPRODUCT($F$20:$P$20,$F$33:$P$33))))))))))))) -> 89.718818
C35: Concentrado Cu Producido | D35: ktons | F35: 89.110927 | G35: 84.171301 | H35: 90.892581 | I35: 92.263072 | J35: 101.86319 | K35: 103.56013 | L35: 76.758648 | M35: 81.551769 | N35: 94.318199 | O35: 97.434661 | P35: 98.533999 | Q35: 102.64168 | S35: =SUM(F35:Q35) -> 1113.1002 | U35: =IF(MONTH(Factores!$D$2)=1,SUM($F35:F35),IF(MONTH(Factores!$D$2)=2,SUM($F35:G35),IF(MONTH(Factores!$D$2)=3,SUM($F35:H35),IF(MONTH(Factores!$D$2)=4,SUM($F35:I35),IF(MONTH(Factores!$D$2)=5,SUM($F35:J35),IF(MONTH(Factores!$D$2)=6,SUM($F35:K35),IF(MONTH(Factores!$D$2)=7,SUM($F35:L35),IF(MONTH(Factores!$D$2)=8,SUM($F35:M35),IF(MONTH(Factores!$D$2)=9,SUM($F35:N35),IF(MONTH(Factores!$D$2)=10,SUM($F35:O35),IF(MONTH(Factores!$D$2)=11,SUM($F35:P35),IF(MONTH(Factores!$D$2)=12,SUM($F35:Q35))))))))))))) -> 264.17481 | V35: =IF(MONTH(Factores!$D$2)=1,SUM($F35:F35),IF(MONTH(Factores!$D$2)=2,SUM($F35:F35),IF(MONTH(Factores!$D$2)=3,SUM($F35:G35),IF(MONTH(Factores!$D$2)=4,SUM($F35:H35),IF(MONTH(Factores!$D$2)=5,SUM($F35:I35),IF(MONTH(Factores!$D$2)=6,SUM($F35:J35),IF(MONTH(Factores!$D$2)=7,SUM($F35:K35),IF(MONTH(Factores!$D$2)=8,SUM($F35:L35),IF(MONTH(Factores!$D$2)=9,SUM($F35:M35),IF(MONTH(Factores!$D$2)=10,SUM($F35:N35),IF(MONTH(Factores!$D$2)=11,SUM($F35:O35),IF(MONTH(Factores!$D$2)=12,SUM($F35:P35))))))))))))) -> 173.28223
C36: Ley Concentrado Cu | D36: % | F36: 27.622768 | G36: 27.866115 | H36: 30.010821 | I36: 28.463206 | J36: 29.261932 | K36: 28.215153 | L36: 30.124781 | M36: 30.57969 | N36: 30.173202 | O36: 29.587613 | P36: 30.266128 | Q36: 30.664963 | S36: =S15/S35*100 -> 29.402756 | U36: =U15/U35*100 -> 28.521942 | V36: =V15/V35*100 -> 27.740973
C38: Ley Alimentación Mo | D38: ppm | F38: 179.78398 | G38: 209.52561 | H38: 231.98672 | I38: 236.94845 | J38: 229.03083 | K38: 240.44486 | L38: 194.46641 | M38: 235.97812 | N38: 273.69761 | O38: 208.13685 | P38: 263.55913 | Q38: 259.99786 | S38: =SUMPRODUCT(F38:Q38,F20:Q20)/SUM(F20:Q20) -> 231.02079 | U38: =IF(MONTH(Factores!$D$2)=1,SUMPRODUCT($F$20:$F$20,$F38:F38)/SUM($F$20:$F$20),IF(MONTH(Factores!$D$2)=2,SUMPRODUCT($F$20:$G$20,$F38:G38)/SUM($F$20:$G$20),IF(MONTH(Factores!$D$2)=3,SUMPRODUCT($F$20:$H$20,$F38:H38)/SUM($F$20:$H$20),IF(MONTH(Factores!$D$2)=4,SUMPRODUCT($F$20:$I$20,$F38:I38)/SUM($F$20:$I$20),IF(MONTH(Factores!$D$2)=5,SUMPRODUCT($F$20:$J$20,$F38:J38)/SUM($F$20:$J$20),IF(MONTH(Factores!$D$2)=6,SUMPRODUCT($F$20:$K$20,$F38:K38)/SUM($F$20:$K$20),IF(MONTH(Factores!$D$2)=7,SUMPRODUCT($F$20:$L$20,$F38:L38)/SUM($F$20:$L$20),IF(MONTH(Factores!$D$2)=8,SUMPRODUCT($F$20:$M$20,$F38:M38)/SUM($F$20:$M$20),IF(MONTH(Factores!$D$2)=9,SUMPRODUCT($F$20:$N$20,$F38:N38)/SUM($F$20:$N$20),IF(MONTH(Factores!$D$2)=10,SUMPRODUCT($F$20:$O$20,$F38:O38)/SUM($F$20:$O$20),IF(MONTH(Factores!$D$2)=11,SUMPRODUCT($F$20:$P$20,$F38:P38)/SUM($F$20:$P$20),IF(MONTH(Factores!$D$2)=12,SUMPRODUCT($F$20:$Q$20,$F38:Q38)/SUM($F$20:$Q$20))))))))))))) -> 206.27179 | V38: =IF(MONTH(Factores!$D$2)=1,SUMPRODUCT($F$20:$F$20,$F38:F38)/SUM($F$20:$F$20),IF(MONTH(Factores!$D$2)=2,SUMPRODUCT($F$20:$F$20,$F38:F38)/SUM($F$20:$F$20),IF(MONTH(Factores!$D$2)=3,SUMPRODUCT($F$20:$G$20,$F38:G38)/SUM($F$20:$G$20),IF(MONTH(Factores!$D$2)=4,SUMPRODUCT($F$20:$H$20,$F38:H38)/SUM($F$20:$H$20),IF(MONTH(Factores!$D$2)=5,SUMPRODUCT($F$20:$I$20,$F38:I38)/SUM($F$20:$I$20),IF(MONTH(Factores!$D$2)=6,SUMPRODUCT($F$20:$J$20,$F38:J38)/SUM($F$20:$J$20),IF(MONTH(Factores!$D$2)=7,SUMPRODUCT($F$20:$K$20,$F38:K38)/SUM($F$20:$K$20),IF(MONTH(Factores!$D$2)=8,SUMPRODUCT($F$20:$L$20,$F38:L38)/SUM($F$20:$L$20),IF(MONTH(Factores!$D$2)=9,SUMPRODUCT($F$20:$M$20,$F38:M38)/SUM($F$20:$M$20),IF(MONTH(Factores!$D$2)=10,SUMPRODUCT($F$20:$N$20,$F38:N38)/SUM($F$20:$N$20),IF(MONTH(Factores!$D$2)=11,SUMPRODUCT($F$20:$O$20,$F38:O38)/SUM($F$20:$O$20),IF(MONTH(Factores!$D$2)=12,SUMPRODUCT($F$20:$P$20,$F38:P38)/SUM($F$20:$P$20))))))))))))) -> 194.12614
C39: Recuperación Global Mo | D39: % | F39: 83.302041 | G39: 83.405539 | H39: 83.860718 | I39: 83.910666 | J39: 84.148913 | K39: 84.236979 | L39: 82.956376 | M39: 84.271235 | N39: 84.407831 | O39: 83.611843 | P39: 84.231725 | Q39: 84.264052 | S39: =SUMPRODUCT(F20:Q20,F38:Q38,F39:Q39)/SUMPRODUCT(F20:Q20,F38:Q38) -> 83.946047 | U39: =IF(MONTH(Factores!$D$2)=1,SUMPRODUCT($F$20:$F$20,$F$38:$F$38,$F39:F39)/SUMPRODUCT($F$20:$F$20,$F$38:$F$38),IF(MONTH(Factores!$D$2)=2,SUMPRODUCT($F$20:$G$20,$F$38:$G$38,$F39:G39)/SUMPRODUCT($F$20:$G$20,$F$38:$G$38),IF(MONTH(Factores!$D$2)=3,SUMPRODUCT($F$20:$H$20,$F$38:$H$38,$F39:H39)/SUMPRODUCT($F$20:$H$20,$F$38:$H$38),IF(MONTH(Factores!$D$2)=4,SUMPRODUCT($F$20:$I$20,$F$38:$I$38,$F39:I39)/SUMPRODUCT($F$20:$I$20,$F$38:$I$38),IF(MONTH(Factores!$D$2)=5,SUMPRODUCT($F$20:$J$20,$F$38:$J$38,$F39:J39)/SUMPRODUCT($F$20:$J$20,$F$38:$J$38),IF(MONTH(Factores!$D$2)=6,SUMPRODUCT($F$20:$K$20,$F$38:$K$38,$F39:K39)/SUMPRODUCT($F$20:$K$20,$F$38:$K$38),IF(MONTH(Factores!$D$2)=7,SUMPRODUCT($F$20:$L$20,$F$38:$L$38,$F39:L39)/SUMPRODUCT($F$20:$L$20,$F$38:$L$38),IF(MONTH(Factores!$D$2)=8,SUMPRODUCT($F$20:$M$20,$F$38:$M$38,$F39:M39)/SUMPRODUCT($F$20:$M$20,$F$38:$M$38),IF(MONTH(Factores!$D$2)=9,SUMPRODUCT($F$20:$N$20,$F$38:$N$38,$F39:N39)/SUMPRODUCT($F$20:$N$20,$F$38:$N$38),IF(MONTH(Factores!$D$2)=10,SUMPRODUCT($F$20:$O$20,$F$38:$O$38,$F39:O39)/SUMPRODUCT($F$20:$O$20,$F$38:$O$38),IF(MONTH(Factores!$D$2)=11,SUMPRODUCT($F$20:$P$20,$F$38:$P$38,$F39:P39)/SUMPRODUCT($F$20:$P$20,$F$38:$P$38),IF(MONTH(Factores!$D$2)=12,SUMPRODUCT($F$20:$Q$20,$F$38:$Q$38,$F39:Q39)/SUMPRODUCT($F$20:$Q$20,$F$38:$Q$38))))))))))))) -> 83.53804 | V39: =IF(MONTH(Factores!$D$2)=1,SUMPRODUCT($F$20:$F$20,$F$38:$F$38,$F39:F39)/SUMPRODUCT($F$20:$F$20,$F$38:$F$38),IF(MONTH(Factores!$D$2)=2,SUMPRODUCT($F$20:$F$20,$F$38:$F$38,$F39:F39)/SUMPRODUCT($F$20:$F$20,$F$38:$F$38),IF(MONTH(Factores!$D$2)=3,SUMPRODUCT($F$20:$G$20,$F$38:$G$38,$F39:G39)/SUMPRODUCT($F$20:$G$20,$F$38:$G$38),IF(MONTH(Factores!$D$2)=4,SUMPRODUCT($F$20:$H$20,$F$38:$H$38,$F39:H39)/SUMPRODUCT($F$20:$H$20,$F$38:$H$38),IF(MONTH(Factores!$D$2)=5,SUMPRODUCT($F$20:$I$20,$F$38:$I$38,$F39:I39)/SUMPRODUCT($F$20:$I$20,$F$38:$I$38),IF(MONTH(Factores!$D$2)=6,SUMPRODUCT($F$20:$J$20,$F$38:$J$38,$F39:J39)/SUMPRODUCT($F$20:$J$20,$F$38:$J$38),IF(MONTH(Factores!$D$2)=7,SUMPRODUCT($F$20:$K$20,$F$38:$K$38,$F39:K39)/SUMPRODUCT($F$20:$K$20,$F$38:$K$38),IF(MONTH(Factores!$D$2)=8,SUMPRODUCT($F$20:$L$20,$F$38:$L$38,$F39:L39)/SUMPRODUCT($F$20:$L$20,$F$38:$L$38),IF(MONTH(Factores!$D$2)=9,SUMPRODUCT($F$20:$M$20,$F$38:$M$38,$F39:M39)/SUMPRODUCT($F$20:$M$20,$F$38:$M$38),IF(MONTH(Factores!$D$2)=10,SUMPRODUCT($F$20:$N$20,$F$38:$N$38,$F39:N39)/SUMPRODUCT($F$20:$N$20,$F$38:$N$38),IF(MONTH(Factores!$D$2)=11,SUMPRODUCT($F$20:$O$20,$F$38:$O$38,$F39:O39)/SUMPRODUCT($F$20:$O$20,$F$38:$O$38),IF(MONTH(Factores!$D$2)=12,SUMPRODUCT($F$20:$P$20,$F$38:$P$38,$F39:P39)/SUMPRODUCT($F$20:$P$20,$F$38:$P$38))))))))))))) -> 83.355909
C40: Recuperación Colectiva Mo | D40: % | F40: =IF(F38>0,3.3127*LN(F38)+75.778,3.3127*LN(F38)+75.778) -> 92.97673 | G40: =IF(G38>0,3.3127*LN(G38)+75.778,3.3127*LN(G38)+75.778) -> 93.483871 | H40: =IF(H38>0,3.3127*LN(H38)+75.778,3.3127*LN(H38)+75.778) -> 93.821217 | I40: =IF(I38>0,3.3127*LN(I38)+75.778,3.3127*LN(I38)+75.778) -> 93.891322 | J40: =IF(J38>0,3.3127*LN(J38)+75.778,3.3127*LN(J38)+75.778) -> 93.778737 | K40: =IF(K38>0,3.3127*LN(K38)+75.778,3.3127*LN(K38)+75.778) -> 93.939847 | L40: =IF(L38>0,3.3127*LN(L38)+75.778,3.3127*LN(L38)+75.778) -> 93.236788 | M40: =IF(M38>0,3.3127*LN(M38)+75.778,3.3127*LN(M38)+75.778) -> 93.877729 | ... Q40: =IF(Q38>0,3.3127*LN(Q38)+75.778,3.3127*LN(Q38)+75.778) -> 94.198843 | S40: =SUMPRODUCT(F20:Q20,F38:Q38,F40:Q40)/SUMPRODUCT(F20:Q20,F38:Q38) -> 93.830424 | U40: =IF(MONTH(Factores!$D$2)=1,SUMPRODUCT($F$20:$F$20,$F$38:$F$38,$F40:F40)/SUMPRODUCT($F$20:$F$20,$F$38:$F$38),IF(MONTH(Factores!$D$2)=2,SUMPRODUCT($F$20:$G$20,$F$38:$G$38,$F40:G40)/SUMPRODUCT($F$20:$G$20,$F$38:$G$38),IF(MONTH(Factores!$D$2)=3,SUMPRODUCT($F$20:$H$20,$F$38:$H$38,$F40:H40)/SUMPRODUCT($F$20:$H$20,$F$38:$H$38),IF(MONTH(Factores!$D$2)=4,SUMPRODUCT($F$20:$I$20,$F$38:$I$38,$F40:I40)/SUMPRODUCT($F$20:$I$20,$F$38:$I$38),IF(MONTH(Factores!$D$2)=5,SUMPRODUCT($F$20:$J$20,$F$38:$J$38,$F40:J40)/SUMPRODUCT($F$20:$J$20,$F$38:$J$38),IF(MONTH(Factores!$D$2)=6,SUMPRODUCT($F$20:$K$20,$F$38:$K$38,$F40:K40)/SUMPRODUCT($F$20:$K$20,$F$38:$K$38),IF(MONTH(Factores!$D$2)=7,SUMPRODUCT($F$20:$L$20,$F$38:$L$38,$F40:L40)/SUMPRODUCT($F$20:$L$20,$F$38:$L$38),IF(MONTH(Factores!$D$2)=8,SUMPRODUCT($F$20:$M$20,$F$38:$M$38,$F40:M40)/SUMPRODUCT($F$20:$M$20,$F$38:$M$38),IF(MONTH(Factores!$D$2)=9,SUMPRODUCT($F$20:$N$20,$F$38:$N$38,$F40:N40)/SUMPRODUCT($F$20:$N$20,$F$38:$N$38),IF(MONTH(Factores!$D$2)=10,SUMPRODUCT($F$20:$O$20,$F$38:$O$38,$F40:O40)/SUMPRODUCT($F$20:$O$20,$F$38:$O$38),IF(MONTH(Factores!$D$2)=11,SUMPRODUCT($F$20:$P$20,$F$38:$P$38,$F40:P40)/SUMPRODUCT($F$20:$P$20,$F$38:$P$38),IF(MONTH(Factores!$D$2)=12,SUMPRODUCT($F$20:$Q$20,$F$38:$Q$38,$F40:Q40)/SUMPRODUCT($F$20:$Q$20,$F$38:$Q$38))))))))))))) -> 93.450137 | V40: =IF(MONTH(Factores!$D$2)=1,SUMPRODUCT($F$20:$F$20,$F$38:$F$38,$F40:F40)/SUMPRODUCT($F$20:$F$20,$F$38:$F$38),IF(MONTH(Factores!$D$2)=2,SUMPRODUCT($F$20:$F$20,$F$38:$F$38,$F40:F40)/SUMPRODUCT($F$20:$F$20,$F$38:$F$38),IF(MONTH(Factores!$D$2)=3,SUMPRODUCT($F$20:$G$20,$F$38:$G$38,$F40:G40)/SUMPRODUCT($F$20:$G$20,$F$38:$G$38),IF(MONTH(Factores!$D$2)=4,SUMPRODUCT($F$20:$H$20,$F$38:$H$38,$F40:H40)/SUMPRODUCT($F$20:$H$20,$F$38:$H$38),IF(MONTH(Factores!$D$2)=5,SUMPRODUCT($F$20:$I$20,$F$38:$I$38,$F40:I40)/SUMPRODUCT($F$20:$I$20,$F$38:$I$38),IF(MONTH(Factores!$D$2)=6,SUMPRODUCT($F$20:$J$20,$F$38:$J$38,$F40:J40)/SUMPRODUCT($F$20:$J$20,$F$38:$J$38),IF(MONTH(Factores!$D$2)=7,SUMPRODUCT($F$20:$K$20,$F$38:$K$38,$F40:K40)/SUMPRODUCT($F$20:$K$20,$F$38:$K$38),IF(MONTH(Factores!$D$2)=8,SUMPRODUCT($F$20:$L$20,$F$38:$L$38,$F40:L40)/SUMPRODUCT($F$20:$L$20,$F$38:$L$38),IF(MONTH(Factores!$D$2)=9,SUMPRODUCT($F$20:$M$20,$F$38:$M$38,$F40:M40)/SUMPRODUCT($F$20:$M$20,$F$38:$M$38),IF(MONTH(Factores!$D$2)=10,SUMPRODUCT($F$20:$N$20,$F$38:$N$38,$F40:N40)/SUMPRODUCT($F$20:$N$20,$F$38:$N$38),IF(MONTH(Factores!$D$2)=11,SUMPRODUCT($F$20:$O$20,$F$38:$O$38,$F40:O40)/SUMPRODUCT($F$20:$O$20,$F$38:$O$38),IF(MONTH(Factores!$D$2)=12,SUMPRODUCT($F$20:$P$20,$F$38:$P$38,$F40:P40)/SUMPRODUCT($F$20:$P$20,$F$38:$P$38))))))))))))) -> 93.240686
C41: Recuperación Selectiva Mo | D41: % | F41: =IF(F38>0,2.5316*LN(F38)+77.156,2.5316*LN(F38)+77.156) -> 90.299449 | G41: =IF(G38>0,2.5316*LN(G38)+77.156,2.5316*LN(G38)+77.156) -> 90.687012 | H41: =IF(H38>0,2.5316*LN(H38)+77.156,2.5316*LN(H38)+77.156) -> 90.944815 | I41: =IF(I38>0,2.5316*LN(I38)+77.156,2.5316*LN(I38)+77.156) -> 90.99839 | J41: =IF(J38>0,2.5316*LN(J38)+77.156,2.5316*LN(J38)+77.156) -> 90.912351 | K41: =IF(K38>0,2.5316*LN(K38)+77.156,2.5316*LN(K38)+77.156) -> 91.035474 | L41: =IF(L38>0,2.5316*LN(L38)+77.156,2.5316*LN(L38)+77.156) -> 90.498189 | M41: =IF(M38>0,2.5316*LN(M38)+77.156,2.5316*LN(M38)+77.156) -> 90.988002 | ... Q41: =IF(Q38>0,2.5316*LN(Q38)+77.156,2.5316*LN(Q38)+77.156) -> 91.233401 | S41: =SUMPRODUCT(F20:Q20,F38:Q38,F40:Q40,F41:Q41)/SUMPRODUCT(F20:Q20,F38:Q38,F40:Q40) -> 90.953068 | U41: =IF(MONTH(Factores!$D$2)=1,SUMPRODUCT($F$20:$F$20,$F$38:$F$38,$F$40:$F$40,$F41:F41)/SUMPRODUCT($F$20:$F$20,$F$38:$F$38,$F$40:$F$40),IF(MONTH(Factores!$D$2)=2,SUMPRODUCT($F$20:$G$20,$F$38:$G$38,$F$40:$G$40,$F41:G41)/SUMPRODUCT($F$20:$G$20,$F$38:$G$38,$F$40:$G$40),IF(MONTH(Factores!$D$2)=3,SUMPRODUCT($F$20:$H$20,$F$38:$H$38,$F$40:$H$40,$F41:H41)/SUMPRODUCT($F$20:$H$20,$F$38:$H$38,$F$40:$H$40),IF(MONTH(Factores!$D$2)=4,SUMPRODUCT($F$20:$I$20,$F$38:$I$38,$F$40:$I$40,$F41:I41)/SUMPRODUCT($F$20:$I$20,$F$38:$I$38,$F$40:$I$40),IF(MONTH(Factores!$D$2)=5,SUMPRODUCT($F$20:$J$20,$F$38:$J$38,$F$40:$J$40,$F41:J41)/SUMPRODUCT($F$20:$J$20,$F$38:$J$38,$F$40:$J$40),IF(MONTH(Factores!$D$2)=6,SUMPRODUCT($F$20:$K$20,$F$38:$K$38,$F$40:$K$40,$F41:K41)/SUMPRODUCT($F$20:$K$20,$F$38:$K$38,$F$40:$K$40),IF(MONTH(Factores!$D$2)=7,SUMPRODUCT($F$20:$L$20,$F$38:$L$38,$F$40:$L$40,$F41:L41)/SUMPRODUCT($F$20:$L$20,$F$38:$L$38,$F$40:$L$40),IF(MONTH(Factores!$D$2)=8,SUMPRODUCT($F$20:$M$20,$F$38:$M$38,$F$40:$M$40,$F41:M41)/SUMPRODUCT($F$20:$M$20,$F$38:$M$38,$F$40:$M$40),IF(MONTH(Factores!$D$2)=9,SUMPRODUCT($F$20:$N$20,$F$38:$N$38,$F$40:$N$40,$F41:N41)/SUMPRODUCT($F$20:$N$20,$F$38:$N$38,$F$40:$N$40),IF(MONTH(Factores!$D$2)=10,SUMPRODUCT($F$20:$O$20,$F$38:$O$38,$F$40:$O$40,$F41:O41)/SUMPRODUCT($F$20:$O$20,$F$38:$O$38,$F$40:$O$40),IF(MONTH(Factores!$D$2)=11,SUMPRODUCT($F$20:$P$20,$F$38:$P$38,$F$40:$P$40,$F41:P41)/SUMPRODUCT($F$20:$P$20,$F$38:$P$38,$F$40:$P$40),IF(MONTH(Factores!$D$2)=12,SUMPRODUCT($F$20:$Q$20,$F$38:$Q$38,$F$40:$Q$40,$F41:Q41)/SUMPRODUCT($F$20:$Q$20,$F$38:$Q$38,$F$40:$Q$40))))))))))))) -> 90.662203 | V41: =IF(MONTH(Factores!$D$2)=1,SUMPRODUCT($F$20:$F$20,$F$38:$F$38,$F$40:$F$40,$F41:F41)/SUMPRODUCT($F$20:$F$20,$F$38:$F$38,$F$40:$F$40),IF(MONTH(Factores!$D$2)=2,SUMPRODUCT($F$20:$F$20,$F$38:$F$38,$F$40:$F$40,$F41:F41)/SUMPRODUCT($F$20:$F$20,$F$38:$F$38,$F$40:$F$40),IF(MONTH(Factores!$D$2)=3,SUMPRODUCT($F$20:$G$20,$F$38:$G$38,$F$40:$G$40,$F41:G41)/SUMPRODUCT($F$20:$G$20,$F$38:$G$38,$F$40:$G$40),IF(MONTH(Factores!$D$2)=4,SUMPRODUCT($F$20:$H$20,$F$38:$H$38,$F$40:$H$40,$F41:H41)/SUMPRODUCT($F$20:$H$20,$F$38:$H$38,$F$40:$H$40),IF(MONTH(Factores!$D$2)=5,SUMPRODUCT($F$20:$I$20,$F$38:$I$38,$F$40:$I$40,$F41:I41)/SUMPRODUCT($F$20:$I$20,$F$38:$I$38,$F$40:$I$40),IF(MONTH(Factores!$D$2)=6,SUMPRODUCT($F$20:$J$20,$F$38:$J$38,$F$40:$J$40,$F41:J41)/SUMPRODUCT($F$20:$J$20,$F$38:$J$38,$F$40:$J$40),IF(MONTH(Factores!$D$2)=7,SUMPRODUCT($F$20:$K$20,$F$38:$K$38,$F$40:$K$40,$F41:K41)/SUMPRODUCT($F$20:$K$20,$F$38:$K$38,$F$40:$K$40),IF(MONTH(Factores!$D$2)=8,SUMPRODUCT($F$20:$L$20,$F$38:$L$38,$F$40:$L$40,$F41:L41)/SUMPRODUCT($F$20:$L$20,$F$38:$L$38,$F$40:$L$40),IF(MONTH(Factores!$D$2)=9,SUMPRODUCT($F$20:$M$20,$F$38:$M$38,$F$40:$M$40,$F41:M41)/SUMPRODUCT($F$20:$M$20,$F$38:$M$38,$F$40:$M$40),IF(MONTH(Factores!$D$2)=10,SUMPRODUCT($F$20:$N$20,$F$38:$N$38,$F$40:$N$40,$F41:N41)/SUMPRODUCT($F$20:$N$20,$F$38:$N$38,$F$40:$N$40),IF(MONTH(Factores!$D$2)=11,SUMPRODUCT($F$20:$O$20,$F$38:$O$38,$F$40:$O$40,$F41:O41)/SUMPRODUCT($F$20:$O$20,$F$38:$O$38,$F$40:$O$40),IF(MONTH(Factores!$D$2)=12,SUMPRODUCT($F$20:$P$20,$F$38:$P$38,$F$40:$P$40,$F41:P41)/SUMPRODUCT($F$20:$P$20,$F$38:$P$38,$F$40:$P$40))))))))))))) -> 90.501694
C42: Concentrado Mo Producido | D42: ktons | F42: =+F17/F43*100 -> 1.5552975 | G42: =+G17/G43*100 -> 1.6902366 | H42: =+H17/H43*100 -> 1.8429912 | I42: =+I17/I43*100 -> 2.1646467 | J42: =+J17/J43*100 -> 2.2196508 | K42: =+K17/K43*100 -> 2.2590439 | L42: =+L17/L43*100 -> 1.5275241 | M42: =+M17/M43*100 -> 1.9569744 | ... Q42: =+Q17/Q43*100 -> 2.5087368 | S42: =SUM(F42:Q42) -> 24.619127 | U42: =IF(MONTH(Factores!$D$2)=1,SUM($F42:F42),IF(MONTH(Factores!$D$2)=2,SUM($F42:G42),IF(MONTH(Factores!$D$2)=3,SUM($F42:H42),IF(MONTH(Factores!$D$2)=4,SUM($F42:I42),IF(MONTH(Factores!$D$2)=5,SUM($F42:J42),IF(MONTH(Factores!$D$2)=6,SUM($F42:K42),IF(MONTH(Factores!$D$2)=7,SUM($F42:L42),IF(MONTH(Factores!$D$2)=8,SUM($F42:M42),IF(MONTH(Factores!$D$2)=9,SUM($F42:N42),IF(MONTH(Factores!$D$2)=10,SUM($F42:O42),IF(MONTH(Factores!$D$2)=11,SUM($F42:P42),IF(MONTH(Factores!$D$2)=12,SUM($F42:Q42))))))))))))) -> 5.0885253 | V42: =IF(MONTH(Factores!$D$2)=1,SUM($F42:F42),IF(MONTH(Factores!$D$2)=2,SUM($F42:F42),IF(MONTH(Factores!$D$2)=3,SUM($F42:G42),IF(MONTH(Factores!$D$2)=4,SUM($F42:H42),IF(MONTH(Factores!$D$2)=5,SUM($F42:I42),IF(MONTH(Factores!$D$2)=6,SUM($F42:J42),IF(MONTH(Factores!$D$2)=7,SUM($F42:K42),IF(MONTH(Factores!$D$2)=8,SUM($F42:L42),IF(MONTH(Factores!$D$2)=9,SUM($F42:M42),IF(MONTH(Factores!$D$2)=10,SUM($F42:N42),IF(MONTH(Factores!$D$2)=11,SUM($F42:O42),IF(MONTH(Factores!$D$2)=12,SUM($F42:P42))))))))))))) -> 3.2455341
C43: Ley Concentrado Mo | D43: % | F43: 54 | G43: 54 | H43: 54 | I43: 54 | J43: 54 | K43: 54 | L43: 54 | M43: 54 | N43: 54 | O43: 54 | P43: 54 | Q43: 54 | S43: =S17/S42*100 -> 54 | U43: =U17/U42*100 -> 54 | V43: =V17/V42*100 -> 54
C45: Ley de Oro en Mineral | D45: g/t | F45: 0.035325723 | G45: 0.032482592 | H45: 0.042501892 | I45: 0.035471027 | J45: 0.040944129 | K45: 0.033668506 | L45: 0.0508335 | M45: 0.052105841 | N45: 0.044304228 | O45: 0.048711775 | P45: 0.052945087 | Q45: 0.054842407 | S45: =SUMPRODUCT(F45:Q45,F20:Q20)/SUM(F20:Q20) -> 0.043708333 | U45: =IF(MONTH(Factores!$D$2)=1,SUMPRODUCT($F$20:$F$20,$F45:F45)/SUM($F$20:$F$20),IF(MONTH(Factores!$D$2)=2,SUMPRODUCT($F$20:$G$20,$F45:G45)/SUM($F$20:$G$20),IF(MONTH(Factores!$D$2)=3,SUMPRODUCT($F$20:$H$20,$F45:H45)/SUM($F$20:$H$20),IF(MONTH(Factores!$D$2)=4,SUMPRODUCT($F$20:$I$20,$F45:I45)/SUM($F$20:$I$20),IF(MONTH(Factores!$D$2)=5,SUMPRODUCT($F$20:$J$20,$F45:J45)/SUM($F$20:$J$20),IF(MONTH(Factores!$D$2)=6,SUMPRODUCT($F$20:$K$20,$F45:K45)/SUM($F$20:$K$20),IF(MONTH(Factores!$D$2)=7,SUMPRODUCT($F$20:$L$20,$F45:L45)/SUM($F$20:$L$20),IF(MONTH(Factores!$D$2)=8,SUMPRODUCT($F$20:$M$20,$F45:M45)/SUM($F$20:$M$20),IF(MONTH(Factores!$D$2)=9,SUMPRODUCT($F$20:$N$20,$F45:N45)/SUM($F$20:$N$20),IF(MONTH(Factores!$D$2)=10,SUMPRODUCT($F$20:$O$20,$F45:O45)/SUM($F$20:$O$20),IF(MONTH(Factores!$D$2)=11,SUMPRODUCT($F$20:$P$20,$F45:P45)/SUM($F$20:$P$20),IF(MONTH(Factores!$D$2)=12,SUMPRODUCT($F$20:$Q$20,$F45:Q45)/SUM($F$20:$Q$20))))))))))))) -> 0.036696631 | V45: =IF(MONTH(Factores!$D$2)=1,SUMPRODUCT($F$20:$F$20,$F45:F45)/SUM($F$20:$F$20),IF(MONTH(Factores!$D$2)=2,SUMPRODUCT($F$20:$F$20,$F45:F45)/SUM($F$20:$F$20),IF(MONTH(Factores!$D$2)=3,SUMPRODUCT($F$20:$G$20,$F45:G45)/SUM($F$20:$G$20),IF(MONTH(Factores!$D$2)=4,SUMPRODUCT($F$20:$H$20,$F45:H45)/SUM($F$20:$H$20),IF(MONTH(Factores!$D$2)=5,SUMPRODUCT($F$20:$I$20,$F45:I45)/SUM($F$20:$I$20),IF(MONTH(Factores!$D$2)=6,SUMPRODUCT($F$20:$J$20,$F45:J45)/SUM($F$20:$J$20),IF(MONTH(Factores!$D$2)=7,SUMPRODUCT($F$20:$K$20,$F45:K45)/SUM($F$20:$K$20),IF(MONTH(Factores!$D$2)=8,SUMPRODUCT($F$20:$L$20,$F45:L45)/SUM($F$20:$L$20),IF(MONTH(Factores!$D$2)=9,SUMPRODUCT($F$20:$M$20,$F45:M45)/SUM($F$20:$M$20),IF(MONTH(Factores!$D$2)=10,SUMPRODUCT($F$20:$N$20,$F45:N45)/SUM($F$20:$N$20),IF(MONTH(Factores!$D$2)=11,SUMPRODUCT($F$20:$O$20,$F45:O45)/SUM($F$20:$O$20),IF(MONTH(Factores!$D$2)=12,SUMPRODUCT($F$20:$P$20,$F45:P45)/SUM($F$20:$P$20))))))))))))) -> 0.033954694
C46: Ley de Oro en Concentrado | D46: g/t | F46: 1.5561761 | G46: 1.4108926 | H46: 1.6744539 | I46: 1.5821718 | J46: 1.7498804 | K46: 1.3706591 | L46: 2.3703267 | M46: 2.3767246 | N46: 1.9328232 | O46: 2.1743495 | P46: 2.1746438 | Q46: 2.312744 | S46: =SUMPRODUCT(F46:Q46,F35:Q35)/SUM(F35:Q35) -> 1.8842701 | U46: =IF(MONTH(Factores!$D$2)=1,SUMPRODUCT($F$35:$F$35,$F46:F46)/SUM($F$35:$F$35),IF(MONTH(Factores!$D$2)=2,SUMPRODUCT($F$35:$G$35,$F46:G46)/SUM($F$35:$G$35),IF(MONTH(Factores!$D$2)=3,SUMPRODUCT($F$35:$H$35,$F46:H46)/SUM($F$35:$H$35),IF(MONTH(Factores!$D$2)=4,SUMPRODUCT($F$35:$I$35,$F46:I46)/SUM($F$35:$I$35),IF(MONTH(Factores!$D$2)=5,SUMPRODUCT($F$35:$J$35,$F46:J46)/SUM($F$35:$J$35),IF(MONTH(Factores!$D$2)=6,SUMPRODUCT($F$35:$K$35,$F46:K46)/SUM($F$35:$K$35),IF(MONTH(Factores!$D$2)=7,SUMPRODUCT($F$35:$L$35,$F46:L46)/SUM($F$35:$L$35),IF(MONTH(Factores!$D$2)=8,SUMPRODUCT($F$35:$M$35,$F46:M46)/SUM($F$35:$M$35),IF(MONTH(Factores!$D$2)=9,SUMPRODUCT($F$35:$N$35,$F46:N46)/SUM($F$35:$N$35),IF(MONTH(Factores!$D$2)=10,SUMPRODUCT($F$35:$O$35,$F46:O46)/SUM($F$35:$O$35),IF(MONTH(Factores!$D$2)=11,SUMPRODUCT($F$35:$P$35,$F46:P46)/SUM($F$35:$P$35),IF(MONTH(Factores!$D$2)=12,SUMPRODUCT($F$35:$Q$35,$F46:Q46)/SUM($F$35:$Q$35))))))))))))) -> 1.5505808 | V46: =IF(MONTH(Factores!$D$2)=1,SUMPRODUCT($F$35:$F$35,$F46:F46)/SUM($F$35:$F$35),IF(MONTH(Factores!$D$2)=2,SUMPRODUCT($F$35:$F$35,$F46:F46)/SUM($F$35:$F$35),IF(MONTH(Factores!$D$2)=3,SUMPRODUCT($F$35:$G$35,$F46:G46)/SUM($F$35:$G$35),IF(MONTH(Factores!$D$2)=4,SUMPRODUCT($F$35:$H$35,$F46:H46)/SUM($F$35:$H$35),IF(MONTH(Factores!$D$2)=5,SUMPRODUCT($F$35:$I$35,$F46:I46)/SUM($F$35:$I$35),IF(MONTH(Factores!$D$2)=6,SUMPRODUCT($F$35:$J$35,$F46:J46)/SUM($F$35:$J$35),IF(MONTH(Factores!$D$2)=7,SUMPRODUCT($F$35:$K$35,$F46:K46)/SUM($F$35:$K$35),IF(MONTH(Factores!$D$2)=8,SUMPRODUCT($F$35:$L$35,$F46:L46)/SUM($F$35:$L$35),IF(MONTH(Factores!$D$2)=9,SUMPRODUCT($F$35:$M$35,$F46:M46)/SUM($F$35:$M$35),IF(MONTH(Factores!$D$2)=10,SUMPRODUCT($F$35:$N$35,$F46:N46)/SUM($F$35:$N$35),IF(MONTH(Factores!$D$2)=11,SUMPRODUCT($F$35:$O$35,$F46:O46)/SUM($F$35:$O$35),IF(MONTH(Factores!$D$2)=12,SUMPRODUCT($F$35:$P$35,$F46:P46)/SUM($F$35:$P$35))))))))))))) -> 1.4856051
C47: Onzas de oro PAGABLES | D47: oz | F47: 4012.5756 | G47: 3436.3034 | H47: 4403.8768 | I47: 4223.9141 | J47: 5157.7366 | K47: 4107.292 | L47: 5264.6445 | M47: 5608.4878 | N47: 5274.9842 | O47: 6130.2243 | P47: 6200.2295 | Q47: 6868.8624 | S47: =SUM(F47:Q47) -> 60689.131 | U47: =IF(MONTH(Factores!$D$2)=1,SUM($F47:F47),IF(MONTH(Factores!$D$2)=2,SUM($F47:G47),IF(MONTH(Factores!$D$2)=3,SUM($F47:H47),IF(MONTH(Factores!$D$2)=4,SUM($F47:I47),IF(MONTH(Factores!$D$2)=5,SUM($F47:J47),IF(MONTH(Factores!$D$2)=6,SUM($F47:K47),IF(MONTH(Factores!$D$2)=7,SUM($F47:L47),IF(MONTH(Factores!$D$2)=8,SUM($F47:M47),IF(MONTH(Factores!$D$2)=9,SUM($F47:N47),IF(MONTH(Factores!$D$2)=10,SUM($F47:O47),IF(MONTH(Factores!$D$2)=11,SUM($F47:P47),IF(MONTH(Factores!$D$2)=12,SUM($F47:Q47))))))))))))) -> 11852.756 | V47: =IF(MONTH(Factores!$D$2)=1,SUM($F47:F47),IF(MONTH(Factores!$D$2)=2,SUM($F47:F47),IF(MONTH(Factores!$D$2)=3,SUM($F47:G47),IF(MONTH(Factores!$D$2)=4,SUM($F47:H47),IF(MONTH(Factores!$D$2)=5,SUM($F47:I47),IF(MONTH(Factores!$D$2)=6,SUM($F47:J47),IF(MONTH(Factores!$D$2)=7,SUM($F47:K47),IF(MONTH(Factores!$D$2)=8,SUM($F47:L47),IF(MONTH(Factores!$D$2)=9,SUM($F47:M47),IF(MONTH(Factores!$D$2)=10,SUM($F47:N47),IF(MONTH(Factores!$D$2)=11,SUM($F47:O47),IF(MONTH(Factores!$D$2)=12,SUM($F47:P47))))))))))))) -> 7448.879
C49: Ley de Plata Mineral | D49: g/t | F49: 1.2239938 | G49: 1.1931734 | H49: 1.5361728 | I49: 1.3725417 | J49: 1.4068097 | K49: 1.3427446 | L49: 1.5981504 | M49: 1.5891755 | N49: 1.4615151 | O49: 1.5574569 | P49: 1.6507955 | Q49: 1.6938529 | S49: =SUMPRODUCT(F49:Q49,F20:Q20)/SUM(F20:Q20) -> 1.4698872 | U49: =IF(MONTH(Factores!$D$2)=1,SUMPRODUCT($F$20:$F$20,$F49:F49)/SUM($F$20:$F$20),IF(MONTH(Factores!$D$2)=2,SUMPRODUCT($F$20:$G$20,$F49:G49)/SUM($F$20:$G$20),IF(MONTH(Factores!$D$2)=3,SUMPRODUCT($F$20:$H$20,$F49:H49)/SUM($F$20:$H$20),IF(MONTH(Factores!$D$2)=4,SUMPRODUCT($F$20:$I$20,$F49:I49)/SUM($F$20:$I$20),IF(MONTH(Factores!$D$2)=5,SUMPRODUCT($F$20:$J$20,$F49:J49)/SUM($F$20:$J$20),IF(MONTH(Factores!$D$2)=6,SUMPRODUCT($F$20:$K$20,$F49:K49)/SUM($F$20:$K$20),IF(MONTH(Factores!$D$2)=7,SUMPRODUCT($F$20:$L$20,$F49:L49)/SUM($F$20:$L$20),IF(MONTH(Factores!$D$2)=8,SUMPRODUCT($F$20:$M$20,$F49:M49)/SUM($F$20:$M$20),IF(MONTH(Factores!$D$2)=9,SUMPRODUCT($F$20:$N$20,$F49:N49)/SUM($F$20:$N$20),IF(MONTH(Factores!$D$2)=10,SUMPRODUCT($F$20:$O$20,$F49:O49)/SUM($F$20:$O$20),IF(MONTH(Factores!$D$2)=11,SUMPRODUCT($F$20:$P$20,$F49:P49)/SUM($F$20:$P$20),IF(MONTH(Factores!$D$2)=12,SUMPRODUCT($F$20:$Q$20,$F49:Q49)/SUM($F$20:$Q$20))))))))))))) -> 1.3140461 | V49: =IF(MONTH(Factores!$D$2)=1,SUMPRODUCT($F$20:$F$20,$F49:F49)/SUM($F$20:$F$20),IF(MONTH(Factores!$D$2)=2,SUMPRODUCT($F$20:$F$20,$F49:F49)/SUM($F$20:$F$20),IF(MONTH(Factores!$D$2)=3,SUMPRODUCT($F$20:$G$20,$F49:G49)/SUM($F$20:$G$20),IF(MONTH(Factores!$D$2)=4,SUMPRODUCT($F$20:$H$20,$F49:H49)/SUM($F$20:$H$20),IF(MONTH(Factores!$D$2)=5,SUMPRODUCT($F$20:$I$20,$F49:I49)/SUM($F$20:$I$20),IF(MONTH(Factores!$D$2)=6,SUMPRODUCT($F$20:$J$20,$F49:J49)/SUM($F$20:$J$20),IF(MONTH(Factores!$D$2)=7,SUMPRODUCT($F$20:$K$20,$F49:K49)/SUM($F$20:$K$20),IF(MONTH(Factores!$D$2)=8,SUMPRODUCT($F$20:$L$20,$F49:L49)/SUM($F$20:$L$20),IF(MONTH(Factores!$D$2)=9,SUMPRODUCT($F$20:$M$20,$F49:M49)/SUM($F$20:$M$20),IF(MONTH(Factores!$D$2)=10,SUMPRODUCT($F$20:$N$20,$F49:N49)/SUM($F$20:$N$20),IF(MONTH(Factores!$D$2)=11,SUMPRODUCT($F$20:$O$20,$F49:O49)/SUM($F$20:$O$20),IF(MONTH(Factores!$D$2)=12,SUMPRODUCT($F$20:$P$20,$F49:P49)/SUM($F$20:$P$20))))))))))))) -> 1.2091314
